Workbook

Sheet China
C2: LSEG | D2: LSEG | I2: LSEG | L2: LSEG | M2: LSEG
C3: CNCPI=ECI (ECONOMIC) | D3: CNGDP=ECI (ECONOMIC) | H3: https://fred.stlouisfed.org/series/intdsrcnm193n | I3: aCNGBOND (ECONOMIC) | V3: fred.stlouisfed.org/series/QCNN628BIS
B4: Date | C4: GDP YoY (%) | D4: CPI YoY (%) | G4: Date | H4: Cash Rate (%) | I4: 10Y Bond Yield (%) | K4: Date | L4: CNY/USD | M4: Exports YoY (%)
B5: 42552 | C5: 6.7 | D5: 1.8 | G5: 42583 | H5: 2.9 | I5: 2.81 | K5: 42614 | L5: 6.6685 | M5: -10.4 | V5: observation_date | W5: QCNN628BIS
B6: 42644 | C6: 6.8 | D6: 2.1 | G6: 42614 | H6: 2.9 | I6: 2.77 | K6: 42644 | L6: 6.7735 | M6: -7.9 | V6: 38443 | W6: 75.8675
B7: 42736 | C7: 7 | D7: 2.5 | G7: 42644 | H7: 2.9 | I7: 2.74 | K7: 42675 | L7: 6.8837 | M7: -1.5 | V7: 38534 | W7: 77.0645
B8: 42826 | C8: 7 | D8: 1.2 | G8: 42675 | H8: 2.9 | I8: 2.94 | K8: 42705 | L8: 6.943 | M8: -6.2 | V8: 38626 | W8: 77.9195
B9: 42917 | C9: 6.9 | D9: 1.4 | G9: 42705 | H9: 2.9 | I9: 3.07 | K9: 42736 | L9: 6.8768 | M9: 6.6 | V9: 38718 | W9: 78.005
B10: 43009 | C10: 6.8 | D10: 1.9 | G10: 42736 | H10: 2.9 | I10: 3.36 | K10: 42767 | L10: 6.8665 | M10: -2.4 | V10: 38808 | W10: 79.544
B11: 43101 | C11: 6.9 | D11: 1.5 | G11: 42767 | H11: 2.9 | I11: 3.36 | K11: 42795 | L11: 6.8832 | M11: 15.4 | V11: 38899 | W11: 80.855
B12: 43191 | C12: 6.9 | D12: 1.8 | G12: 42795 | H12: 2.9 | I12: 3.31 | K12: 42826 | L12: 6.89 | M12: 6.5 | V12: 38991 | W12: 81.824
B13: 43282 | C13: 6.7 | D13: 2.1 | G13: 42826 | H13: 2.9 | I13: 3.48 | K13: 42856 | L13: 6.8098 | M13: 7.6 | V13: 39083 | W13: 82.1375
B14: 43374 | C14: 6.5 | D14: 2.5 | G14: 42856 | H14: 2.9 | I14: 3.67 | K14: 42887 | L14: 6.7793 | M14: 10.3 | V14: 39173 | W14: 84.218
B15: 43466 | C15: 6.4 | D15: 1.7 | G15: 42887 | H15: 2.9 | I15: 3.58 | K15: 42917 | L15: 6.724 | M15: 6.4 | V15: 39264 | W15: 86.498
B16: 43556 | C16: 6.1 | D16: 2.5 | G16: 42917 | H16: 2.9 | I16: 3.63 | K16: 42948 | L16: 6.5888 | M16: 4.9 | V16: 39356 | W16: 89.1486
B17: 43647 | C17: 6 | D17: 2.8 | G17: 42948 | H17: 2.9 | I17: 3.67 | K17: 42979 | L17: 6.6533 | M17: 7.9 | V17: 39448 | W17: 89.8611
... B44: 46113 | C44: 4.3 | D44: 1.2 | G44: 43770 | H44: 2.9 | I44: 3.19 | K44: 43800 | L44: 6.9618 | M44: 7.9 | V44: 41913 | W44: 109.1557
G45: 43800 | H45: 2.9 | I45: 3.17 | K45: 43831 | L45: 6.9364 | M45: -2.9 | V45: 42005 | W45: 107.8162
G46: 43831 | H46: 2.9 | I46: 3.05 | K46: 43862 | L46: 6.9906 | M46: -40.6 | V46: 42095 | W46: 107.5882
G47: 43862 | H47: 2.9 | I47: 2.8 | K47: 43891 | L47: 7.0808 | M47: -6.9 | V47: 42186 | W47: 108.2437
G48: 43891 | H48: 2.9 | I48: 2.66 | K48: 43922 | L48: 7.06 | M48: 3.1 | V48: 42278 | W48: 108.8422
G49: 43922 | H49: 2.9 | I49: 2.51 | K49: 43952 | L49: 7.1348 | M49: -3.5 | V49: 42370 | W49: 111.5332
G50: 43952 | H50: 2.9 | I50: 2.71 | K50: 43983 | L50: 7.0651 | M50: 0.2 | V50: 42461 | W50: 113.8325
G51: 43983 | H51: 2.9 | I51: 2.9 | K51: 44013 | L51: 6.9744 | M51: 6.8 | V51: 42552 | W51: 116.4238
G52: 44013 | H52: 2.9 | I52: 2.97 | K52: 44044 | L52: 6.8474 | M52: 9.1 | V52: 42644 | W52: 119.1975
G53: 44044 | H53: 2.9 | I53: 3.05 | K53: 44075 | L53: 6.7896 | M53: 9.4 | V53: 42736 | W53: 120.6209
G54: 44075 | H54: 2.9 | I54: 3.15 | K54: 44105 | L54: 6.6919 | M54: 10.9 | V54: 42826 | W54: 122.9931
G55: 44105 | H55: 2.9 | I55: 3.19 | K55: 44136 | L55: 6.576 | M55: 20.6 | V55: 42917 | W55: 124.38
G56: 44136 | H56: 2.9 | I56: 3.28 | K56: 44166 | L56: 6.525 | M56: 18.1 | V56: 43009 | W56: 125.1464
... G89: 45139 | H89: 2.9 | I89: 2.59 | K89: 45170 | L89: 7.301 | M89: -6.8 | V89: 46023 | W89: 113.9785
G90: 45170 | H90: 2.9 | I90: 2.71 | K90: 45200 | L90: 7.3158 | M90: -6.6
G91: 45200 | H91: 2.9 | I91: 2.71 | K91: 45231 | L91: 7.136 | M91: 0.7
G92: 45231 | H92: 2.9 | I92: 2.69 | K92: 45261 | L92: 7.0978 | M92: 2.3
G93: 45261 | H93: 2.9 | I93: 2.58 | K93: 45292 | L93: 7.1673 | M93: 7.7
G94: 45292 | H94: 2.9 | I94: 2.44 | K94: 45323 | L94: 7.1877 | M94: 6.3
G95: 45323 | H95: 2.9 | I95: 2.36 | K95: 45352 | L95: 7.2203 | M95: -7.6
G96: 45352 | H96: 2.9 | I96: 2.3 | K96: 45383 | L96: 7.2401 | M96: 1.3
G97: 45383 | H97: 2.9 | I97: 2.31 | K97: 45413 | L97: 7.2415 | M97: 7.4
G98: 45413 | H98: 2.9 | I98: 2.32 | K98: 45444 | L98: 7.2672 | M98: 8.5
G99: 45444 | H99: 2.9 | I99: 2.21 | K99: 45474 | L99: 7.2193 | M99: 6.9
G100: 45474 | H100: 2.9 | I100: 2.15 | K100: 45505 | L100: 7.09 | M100: 8.6
G101: 45505 | H101: 2.9 | I101: 2.18 | K101: 45536 | L101: 7.0176 | M101: 2.4
... G111: 45809 | H111: 2.9 | I111: 1.65 | K111: 45839 | L111: 7.2002 | M111: 7.1
K112: 45870 | L112: 7.1304 | M112: 4.3
K113: 45901 | L113: 7.119 | M113: 8.2
K114: 45931 | L114: 7.1169 | M114: -1.2
K115: 45962 | L115: 7.075 | M115: 5.9
K116: 45992 | L116: 6.9931 | M116: 6.6
K117: 46023 | L117: 6.951 | M117: 10
K118: 46054 | L118: 6.8579 | M118: 39.6
K119: 46082 | L119: 6.898 | M119: 2.5
K120: 46113 | L120: 6.8273 | M120: 14
K121: 46143 | L121: 6.7662 | M121: 19.2
K122: 46174 | L122: 6.7851 | M122: 27
K123: 46204 | L123: 6.7509 | M123: 23.9

Sheet Emerging
A2: LSEG | R2: Nominal Emerging Market Economies U.S. Dollar Index
B3: INCAPA=ECI (ECONOMIC) | C3: MXACUR=ECI (ECONOMIC) | D3: ZAGDPY=ECI (ECONOMIC) | E3: IDGDP=ECI (ECONOMIC) | R3: observation_date | S3: TWEXEMEGSMTH | U3: https://fred.stlouisfed.org/series/TWEXEMEGSMTH?utm_
A4: Date | B4: India GDP (%) | C4: Mexico GDP (%) | D4: South Africa GDP (%) | E4: Indonesia GDP (%) | R4: 44409 | S4: 123.7116
A5: 46113 | B5: -0.5 | C5: 1.65 | D5: 1.9 | E5: 5.29 | R5: 44440 | S5: 123.464
A6: 46023 | B6: 0.7 | C6: -3.61 | D6: 0.8 | E6: 5.61 | R6: 44470 | S6: 124.3734
A7: 45931 | B7: -1.3 | C7: 1.54 | D7: 2.1 | E7: 5.39 | R7: 44501 | S7: 124.8764
A8: 45839 | B8: -1.3 | C8: 0.2 | D8: 0.7 | E8: 5.04 | R8: 44531 | S8: 125.298
A9: 45748 | B9: -0.3 | C9: -0.99 | D9: 0.9 | E9: 5.12 | R9: 44562 | S9: 124.3316
A10: 45658 | B10: 1.3 | C10: -3.21 | D10: 0.8 | E10: 4.87 | R10: 44593 | S10: 124.0418
A11: 45566 | B11: -1.1 | C11: 2.47 | D11: 0.4 | E11: 5.02 | R11: 44621 | S11: 124.7618
A12: 45474 | B12: -2.2 | C12: -0.54 | D12: 0.4 | E12: 4.95 | R12: 44652 | S12: 124.5443
A13: 45383 | B13: -0.5 | C13: -0.16 | D13: 0.5 | E13: 5.05 | R13: 44682 | S13: 126.8992
R14: 44713 | S14: 127.1571
A15: LSEG | R15: 44743 | S15: 129.7725
B16: INCPIY=ECI (ECONOMIC) | C16: BRCPIY=ECI (ECONOMIC) | D16: MXCPIA=ECI (ECONOMIC) | E16: ZACPIY=ECI (ECONOMIC) | F16: IDCPI=ECI (ECONOMIC) | R16: 44774 | S16: 129.023
A17: Date | B17: India CPI (%) | C17: Brazil CPI (%) | D17: Mexico CPI (%) | E17: South Africa CPI (%) | F17: Indonesia CPI (%) | R17: 44805 | S17: 131.6451
A18: 44378 | B18: 5.07 | C18: 9.64 | D18: 5.8 | E18: 4.8 | F18: 1.57 | R18: 44835 | S18: 133.662
A19: 44470 | B19: 5.05 | C19: 10.49 | D19: 6.99 | E19: 5.43 | F19: 1.76 | R19: 44866 | S19: 131.8784
A20: 44562 | B20: 6.35 | C20: 10.74 | D20: 7.27 | E20: 5.7 | F20: 2.23 | R20: 44896 | S20: 129.7434
A21: 44652 | B21: 7.25 | C21: 11.92 | D21: 7.77 | E21: 6.63 | F21: 3.7 | R21: 44927 | S21: 126.6445
A22: 44743 | B22: 6.99 | C22: 8.66 | D22: 8.52 | E22: 7.67 | F22: 5.13 | R22: 44958 | S22: 126.758
A23: 44835 | B23: 6.13 | C23: 6.05 | D23: 8.01 | E23: 7.4 | F23: 5.48 | R23: 44986 | S23: 127.0148
A24: 44927 | B24: 6.2 | C24: 5.34 | D24: 7.46 | E24: 6.97 | F24: 5.16 | R24: 45017 | S24: 126.1816
A25: 45017 | B25: 4.61 | C25: 3.76 | D25: 5.72 | E25: 6.13 | F25: 3.99 | R25: 45047 | S25: 126.0915
A26: 45108 | B26: 6.47 | C26: 4.6 | D26: 4.63 | E26: 4.97 | F26: 2.95 | R26: 45078 | S26: 125.5637
A27: 45200 | B27: 5.35 | C27: 4.71 | D27: 4.41 | E27: 5.57 | F27: 2.81 | R27: 45108 | S27: 124.8058
A28: 45292 | B28: 5.05 | C28: 4.31 | D28: 4.57 | E28: 5.43 | F28: 2.79 | R28: 45139 | S28: 126.3969
A29: 45383 | B29: 4.94 | C29: 3.95 | D29: 4.77 | E29: 5.17 | F29: 2.78 | R29: 45170 | S29: 127.9809
... A38: 46204 | B38: 4.45 | C38: 4.44 | D38: 3.12 | E38: 4.3 | F38: 3.04 | R38: 45444 | S38: 132.1008
R39: 45474 | S39: 132.0201
A40: MSCI EM | R40: 45505 | S40: 132.808
B41: .dMIEF00000PUS (TRDPRC_1) | C41: LSEG | R41: 45536 | S41: 132.7205
A42: Date | B42: MSCI EM Index | R42: 45566 | S42: 133.7709
A43: 44440 | B43: 1253.1 | R43: 45597 | S43: 136.5813
A44: 44470 | B44: 1264.75 | R44: 45627 | S44: 137.4717
A45: 44501 | B45: 1212.42 | R45: 45658 | S45: 138.3438
A46: 44531 | B46: 1232.01 | R46: 45689 | S46: 137.6507
A47: 44562 | B47: 1208.23 | R47: 45717 | S47: 137.1056
A48: 44593 | B48: 1171.31 | R48: 45748 | S48: 136.8608
A49: 44621 | B49: 1141.79 | R49: 45778 | S49: 133.7754
A50: 44652 | B50: 1076.19 | R50: 45809 | S50: 132.2201
A51: 44682 | B51: 1077.67 | R51: 45839 | S51: 131.5744
A52: 44713 | B52: 1000.67 | R52: 45870 | S52: 132.0667
A53: 44743 | B53: 993.78 | R53: 45901 | S53: 131.425
A54: 44774 | B54: 994.11 | R54: 45931 | S54: 131.6668
... A64: 45078 | B64: 989.48 | R64: 46235 | S64: 127.3196
A65: 45108 | B65: 1046.91
A66: 45139 | B66: 980.33
A67: 45170 | B67: 952.78
A68: 45200 | B68: 915.2
A69: 45231 | B69: 987.1
A70: 45261 | B70: 1023.74
A71: 45292 | B71: 975.8
A72: 45323 | B72: 1020.94
A73: 45352 | B73: 1043.2
A74: 45383 | B74: 1045.95
A75: 45413 | B75: 1048.96
A76: 45444 | B76: 1086.25
... A103: 46266 | B103: 1726.32

Sheet Australia
B1: LSEG 7/9 | C1: LSEG 7/9 | M1: LSEG 2/9 | N1: LSEG 2/9 | Q1: LSEG 2/9 | R1: LSEG 2/9 | AB1: LSEG | AG1: https://www.rba.gov.au/statistics/tables/ | AO1: AUD unemployment | AP1: https://www.abs.gov.au/statistics/labour/employment-and-unemployment/labour-force-australia/latest-release#data-downloads
AB3: aAUCBIRAR (ECONOMIC)
A4: Date | B4: GDP Y/Y | C4: CPI Y/Y | L4: Date | M4: S&P ASX200 | N4: AUD/USD | P4: Date | Q4: S&P ASX200 | R4: AUD/USD | AA4: Date | AB4: 10Y Cashrate | AE4: Date | AF4: RBA Cash Rate (%) | AG4: 10Y ACGB Yield (%) | AI4: Date | AJ4: Fed Funds Rate (%) | AK4: SPY Close ($) | AO4: > Unemployment rate looked for full-time work ; Persons ;
A5: 46113 | B5: 2.1 | C5: 4 | L5: 44440 | M5: 7332.2 | N5: 0.7226 | P5: 44440 | Q5: =M5/$M$5*100 -> 100 | R5: =N5/$N$5*100 -> 100 | AA5: 46235 | AB5: 4.35 | AE5: 42583 | AF5: 1.5 | AG5: 1.892 | AI5: 42614 | AJ5: 0.4 | AK5: 216.3 | AO5: Percent
A6: 46023 | B6: 2.5 | C6: 4.1 | L6: 44470 | M6: 7323.7 | N6: 0.7521 | P6: 44470 | Q6: =M6/$M$5*100 -> 99.884073 | R6: =N6/$N$5*100 -> 104.08248 | AA6: 46174 | AB6: 4.35 | AE6: 42614 | AF6: 1.5 | AG6: 2.004 | AI6: 42644 | AJ6: 0.4 | AK6: 212.55 | AO6: Trend
A7: 45931 | B7: 2.6 | C7: 3.6 | L7: 44501 | M7: 7256 | N7: 0.7123 | P7: 44501 | Q7: =M7/$M$5*100 -> 98.960748 | R7: =N7/$N$5*100 -> 98.574592 | AA7: 46143 | AB7: 4.35 | AE7: 42644 | AF7: 1.5 | AG7: 2.231 | AI7: 42675 | AJ7: 0.41 | AK7: 220.38 | AO7: PERCENT
A8: 45839 | B8: 2.1 | C8: 3.2 | L8: 44531 | M8: 7444.6 | N8: 0.726 | P8: 44531 | Q8: =M8/$M$5*100 -> 101.53296 | R8: =N8/$N$5*100 -> 100.47052 | AA8: 46082 | AB8: 4.1 | AE8: 42675 | AF8: 1.5 | AG8: 2.535 | AI8: 42705 | AJ8: 0.54 | AK8: 223.53 | AO8: Month
A9: 45748 | B9: 1.9 | C9: 2.1 | L9: 44565 | M9: 6971.6 | N9: 0.7064 | P9: 44565 | Q9: =M9/$M$5*100 -> 95.081967 | R9: =N9/$N$5*100 -> 97.758096 | AA9: 46054 | AB9: 3.85 | AE9: 42705 | AF9: 1.5 | AG9: 2.799 | AI9: 42736 | AJ9: 0.65 | AK9: 227.53 | AO9: 1
A10: 45658 | B10: 1.3 | C10: 2.4 | L10: 44593 | M10: 7049.1 | N10: 0.7262 | P10: 44593 | Q10: =M10/$M$5*100 -> 96.138949 | R10: =N10/$N$5*100 -> 100.4982 | AA10: 45992 | AB10: 3.6 | AE10: 42736 | AF10: 1.5 | AG10: 2.711 | AI10: 42767 | AJ10: 0.66 | AK10: 236.47 | AO10: 28522
A11: 45566 | B11: 1.2 | C11: 2.4 | L11: 44621 | M11: 7499.6 | N11: 0.748 | P11: 44621 | Q11: =M11/$M$5*100 -> 102.28308 | R11: =N11/$N$5*100 -> 103.51508 | AA11: 45962 | AB11: 3.6 | AE11: 42767 | AF11: 1.5 | AG11: 2.738 | AI11: 42795 | AJ11: 0.79 | AK11: 235.74 | AO11: 46204
A12: 45474 | B12: 0.8 | C12: 2.9 | L12: 44652 | M12: 7435 | N12: 0.7063 | P12: 44652 | Q12: =M12/$M$5*100 -> 101.40203 | R12: =N12/$N$5*100 -> 97.744257 | AA12: 45931 | AB12: 3.6 | AE12: 42795 | AF12: 1.5 | AG12: 2.804 | AI12: 42826 | AJ12: 0.9 | AK12: 238.08 | AO12: 582
A13: 45383 | B13: 0.9 | C13: 3.8 | L13: 44683 | M13: 7211.2 | N13: 0.7173 | P13: 44683 | Q13: =M13/$M$5*100 -> 98.349745 | R13: =N13/$N$5*100 -> 99.266538 | AA13: 45901 | AB13: 3.6 | AE13: 42826 | AF13: 1.5 | AG13: 2.557 | AI13: 42856 | AJ13: 0.91 | AK13: 241.44 | AN13: Date | AO13: Australia Unemployment Rate (%)
A14: 45292 | B14: 1.1 | C14: 3.6 | L14: 44713 | M14: 6568.1 | N14: 0.6901 | P14: 44713 | Q14: =M14/$M$5*100 -> 89.578844 | R14: =N14/$N$5*100 -> 95.502353 | AA14: 45870 | AB14: 3.6 | AE14: 42856 | AF14: 1.5 | AG14: 2.548 | AI14: 42887 | AJ14: 1.04 | AK14: 241.8 | AN14: 42401 | AO14: 5.9
A15: 45200 | B15: 1.3 | C15: 4.1 | L15: 44743 | M15: 6945.2 | N15: 0.6985 | P15: 44743 | Q15: =M15/$M$5*100 -> 94.721912 | R15: =N15/$N$5*100 -> 96.664821 | AA15: 45839 | AB15: 3.85 | AE15: 42887 | AF15: 1.5 | AG15: 2.421 | AI15: 42917 | AJ15: 1.15 | AK15: 246.77 | AN15: 42430 | AO15: 5.9
A16: 45108 | B16: 2.2 | C16: 5.3 | L16: 44774 | M16: 6986.8 | N16: 0.6839 | P16: 44774 | Q16: =M16/$M$5*100 -> 95.289272 | R16: =N16/$N$5*100 -> 94.64434 | AA16: 45778 | AB16: 3.85 | AE16: 42917 | AF16: 1.5 | AG16: 2.664 | AI16: 42948 | AJ16: 1.16 | AK16: 247.49 | AN16: 42461 | AO16: 5.8
A17: 45017 | B17: 2.2 | C17: 6 | L17: 44805 | M17: 6474.2 | N17: 0.6402 | P17: 44805 | Q17: =M17/$M$5*100 -> 88.298192 | R17: =N17/$N$5*100 -> 88.596734 | AA17: 45748 | AB17: 4.1 | AE17: 42948 | AF17: 1.5 | AG17: 2.626 | AI17: 42979 | AJ17: 1.15 | AK17: 251.23 | AN17: 42491 | AO17: 5.8
A18: 44927 | B18: 2.8 | C18: 7 | L18: 44837 | M18: 6863.5 | N18: 0.6397 | P18: 44837 | Q18: =M18/$M$5*100 -> 93.607648 | R18: =N18/$N$5*100 -> 88.527539 | AA18: 45689 | AB18: 4.1 | AE18: 42979 | AF18: 1.5 | AG18: 2.71 | AI18: 43009 | AJ18: 1.15 | AK18: 257.15 | AN18: 42522 | AO18: 5.7
A19: 44835 | B19: 3.3 | C19: 7.9 | L19: 44866 | M19: 7284.2 | N19: 0.6786 | P19: 44866 | Q19: =M19/$M$5*100 -> 99.345353 | R19: =N19/$N$5*100 -> 93.910877 | AA19: 45627 | AB19: 4.35 | AE19: 43009 | AF19: 1.5 | AG19: 2.768 | AI19: 43040 | AJ19: 1.16 | AK19: 265.01 | AN19: 42552 | AO19: 5.7
A20: 44743 | B20: 6.1 | C20: 7.3 | L20: 44896 | M20: 7038.7 | N20: 0.6813 | P20: 44896 | Q20: =M20/$M$5*100 -> 95.997109 | R20: =N20/$N$5*100 -> 94.284528 | AA20: 45597 | AB20: 4.35 | AE20: 43040 | AF20: 1.5 | AG20: 2.565 | AI20: 43070 | AJ20: 1.3 | AK20: 266.86 | AN20: 42583 | AO20: 5.7
A21: 44652 | B21: 3.8 | C21: 6.2 | L21: 44929 | M21: 7476.7 | N21: 0.7054 | P21: 44929 | Q21: =M21/$M$5*100 -> 101.97076 | R21: =N21/$N$5*100 -> 97.619707 | AA21: 45536 | AB21: 4.35 | AE21: 43070 | AF21: 1.5 | AG21: 2.583 | AI21: 43101 | AJ21: 1.41 | AK21: 281.9 | AN21: 42614 | AO21: 5.8
A22: 44562 | B22: 3.6 | C22: 5.1 | L22: 44958 | M22: 7258.4 | N22: 0.6728 | P22: 44958 | Q22: =M22/$M$5*100 -> 98.993481 | R22: =N22/$N$5*100 -> 93.10822 | AA22: 45505 | AB22: 4.35 | AE22: 43101 | AF22: 1.5 | AG22: 2.747 | AI22: 43132 | AJ22: 1.42 | AK22: 271.65 | AN22: 42644 | AO22: 5.8
A23: 44470 | B23: 4.9 | C23: 3.5 | L23: 44986 | M23: 7177.8 | N23: 0.6685 | P23: 44986 | Q23: =M23/$M$5*100 -> 97.89422 | R23: =N23/$N$5*100 -> 92.513147 | AA23: 45444 | AB23: 4.35 | AE23: 43132 | AF23: 1.5 | AG23: 2.845 | AI23: 43160 | AJ23: 1.51 | AK23: 263.15 | AN23: 42675 | AO23: 5.9
A24: 44378 | B24: 4.7 | C24: 3.1 | L24: 45019 | M24: 7309.2 | N24: 0.6607 | P24: 45019 | Q24: =M24/$M$5*100 -> 99.686315 | R24: =N24/$N$5*100 -> 91.433712 | AA24: 45413 | AB24: 4.35 | AE24: 43160 | AF24: 1.5 | AG24: 2.713 | AI24: 43191 | AJ24: 1.69 | AK24: 264.51 | AN24: 42705 | AO24: 6
A25: 44287 | B25: 10.2 | C25: 3.8 | L25: 45047 | M25: 7091.3 | N25: 0.65 | P25: 45047 | Q25: =M25/$M$5*100 -> 96.714492 | R25: =N25/$N$5*100 -> 89.952948 | AA25: 45352 | AB25: 4.35 | AE25: 43191 | AF25: 1.5 | AG25: 2.734 | AI25: 43221 | AJ25: 1.7 | AK25: 270.94 | AN25: 42736 | AO25: 6
G26: 40 | L26: 45078 | M26: 7203.3 | N26: 0.6666 | P26: 45078 | Q26: =M26/$M$5*100 -> 98.242001 | R26: =N26/$N$5*100 -> 92.250208 | AA26: 45323 | AB26: 4.35 | AE26: 43221 | AF26: 1.5 | AG26: 2.79 | AI26: 43252 | AJ26: 1.82 | AK26: 271.28 | AN26: 42767 | AO26: 5.9
L27: 45110 | M27: 7410.4 | N27: 0.672 | P27: 45110 | Q27: =M27/$M$5*100 -> 101.06653 | R27: =N27/$N$5*100 -> 92.997509 | AA27: 45261 | AB27: 4.35 | AE27: 43252 | AF27: 1.5 | AG27: 2.697 | AI27: 43282 | AJ27: 1.91 | AK27: 281.33 | AN27: 42795 | AO27: 5.9
L28: 45139 | M28: 7305.3 | N28: 0.6483 | P28: 45139 | Q28: =M28/$M$5*100 -> 99.633125 | R28: =N28/$N$5*100 -> 89.717686 | AA28: 45231 | AB28: 4.35 | AE28: 43282 | AF28: 1.5 | AG28: 2.637 | AI28: 43313 | AJ28: 1.91 | AK28: 290.31 | AN28: 42826 | AO28: 5.8
L29: 45170 | M29: 7048.6 | N29: 0.6434 | P29: 45170 | Q29: =M29/$M$5*100 -> 96.13213 | R29: =N29/$N$5*100 -> 89.039579 | AA29: 45200 | AB29: 4.1 | AE29: 43313 | AF29: 1.5 | AG29: 2.59 | AI29: 43344 | AJ29: 1.95 | AK29: 290.72 | AN29: 42856 | AO29: 5.7
L30: 45201 | M30: 6780.7 | N30: 0.6336 | P30: 45201 | Q30: =M30/$M$5*100 -> 92.478383 | R30: =N30/$N$5*100 -> 87.683366 | AA30: 45170 | AB30: 4.1 | AE30: 43344 | AF30: 1.5 | AG30: 2.631 | AI30: 43374 | AJ30: 2.19 | AK30: 270.63 | AN30: 42887 | AO30: 5.6
L31: 45231 | M31: 7087.3 | N31: 0.6605 | P31: 45231 | Q31: =M31/$M$5*100 -> 96.659938 | R31: =N31/$N$5*100 -> 91.406034 | AA31: 45139 | AB31: 4.1 | AE31: 43374 | AF31: 1.5 | AG31: 2.682 | AI31: 43405 | AJ31: 2.2 | AK31: 275.65 | AN31: 42917 | AO31: 5.5
L32: 45261 | M32: 7590.8 | N32: 0.681 | P32: 45261 | Q32: =M32/$M$5*100 -> 103.52691 | R32: =N32/$N$5*100 -> 94.243011 | AA32: 45108 | AB32: 4.1 | AE32: 43405 | AF32: 1.5 | AG32: 2.683 | AI32: 43435 | AJ32: 2.27 | AK32: 249.92 | AN32: 42948 | AO32: 5.5
L33: 45293 | M33: 7680.7 | N33: 0.6565 | P33: 45293 | Q33: =M33/$M$5*100 -> 104.75301 | R33: =N33/$N$5*100 -> 90.852477 | AA33: 45078 | AB33: 4.1 | AE33: 43435 | AF33: 1.5 | AG33: 2.431 | AI33: 43466 | AJ33: 2.4 | AK33: 269.93 | AN33: 42979 | AO33: 5.5
L34: 45323 | M34: 7698.7 | N34: 0.6495 | P34: 45323 | Q34: =M34/$M$5*100 -> 104.9985 | R34: =N34/$N$5*100 -> 89.883753 | AA34: 45047 | AB34: 3.85 | AE34: 43466 | AF34: 1.5 | AG34: 2.271 | AI34: 43497 | AJ34: 2.4 | AK34: 278.68 | AN34: 43009 | AO34: 5.5
L35: 45352 | M35: 7896.9 | N35: 0.6521 | P35: 45352 | Q35: =M35/$M$5*100 -> 107.70164 | R35: =N35/$N$5*100 -> 90.243565 | AA35: 45017 | AB35: 3.6 | AE35: 43497 | AF35: 1.5 | AG35: 2.126 | AI35: 43525 | AJ35: 2.41 | AK35: 282.48 | AN35: 43040 | AO35: 5.5
L36: 45384 | M36: 7664.1 | N36: 0.6472 | P36: 45384 | Q36: =M36/$M$5*100 -> 104.52661 | R36: =N36/$N$5*100 -> 89.565458 | AA36: 44986 | AB36: 3.6 | AE36: 43525 | AF36: 1.5 | AG36: 1.957 | AI36: 43556 | AJ36: 2.42 | AK36: 294.02 | AN36: 43070 | AO36: 5.5
L37: 45413 | M37: 7701.7 | N37: 0.6652 | P37: 45413 | Q37: =M37/$M$5*100 -> 105.03942 | R37: =N37/$N$5*100 -> 92.056463 | AA37: 44958 | AB37: 3.35 | AE37: 43556 | AF37: 1.5 | AG37: 1.865 | AI37: 43586 | AJ37: 2.39 | AK37: 275.27 | AN37: 43101 | AO37: 5.6
L38: 45446 | M38: 7767.5 | N38: 0.6667 | P38: 45446 | Q38: =M38/$M$5*100 -> 105.93683 | R38: =N38/$N$5*100 -> 92.264046 | AA38: 44896 | AB38: 3.1 | AE38: 43586 | AF38: 1.5 | AG38: 1.655 | AI38: 43617 | AJ38: 2.38 | AK38: 293 | AN38: 43132 | AO38: 5.6
... L65: 46266 | M65: 9005.9 | N65: 0.7207 | P65: 46266 | Q65: =M65/$M$5*100 -> 122.82671 | R65: =N65/$N$5*100 -> 99.737061 | AA65: 44013 | AB65: 0.25 | AE65: 44409 | AF65: 0.1 | AG65: 1.135 | AI65: 44440 | AJ65: 0.08 | AK65: 429.14 | AN65: 43952 | AO65: 7.3
N66: 0.7315 | AA66: 43983 | AB66: 0.25 | AE66: 44440 | AF66: 0.1 | AG66: 1.282 | AI66: 44470 | AJ66: 0.08 | AK66: 459.25 | AN66: 43983 | AO66: 7.4
AA67: 43952 | AB67: 0.25 | AE67: 44470 | AF67: 0.1 | AG67: 1.71 | AI67: 44501 | AJ67: 0.08 | AK67: 455.56 | AN67: 44013 | AO67: 7.5
AA68: 43922 | AB68: 0.25 | AE68: 44501 | AF68: 0.1 | AG68: 1.806 | AI68: 44531 | AJ68: 0.08 | AK68: 474.96 | AN68: 44044 | AO68: 7.5
AA69: 43891 | AB69: 0.5 | AE69: 44531 | AF69: 0.1 | AG69: 1.609 | AI69: 44562 | AJ69: 0.08 | AK69: 449.91 | AN69: 44075 | AO69: 7.4
AA70: 43862 | AB70: 0.75 | AE70: 44562 | AF70: 0.1 | AG70: 1.888 | AI70: 44593 | AJ70: 0.08 | AK70: 436.63 | AN70: 44105 | AO70: 7.3
AA71: 43800 | AB71: 0.75 | AE71: 44593 | AF71: 0.1 | AG71: 2.111 | AI71: 44621 | AJ71: 0.2 | AK71: 451.64 | AN71: 44136 | AO71: 7.1
AA72: 43770 | AB72: 0.75 | AE72: 44621 | AF72: 0.1 | AG72: 2.5 | AI72: 44652 | AJ72: 0.33 | AK72: 412 | AN72: 44166 | AO72: 6.8
AA73: 43739 | AB73: 0.75 | AE73: 44652 | AF73: 0.1 | AG73: 3.008 | AI73: 44682 | AJ73: 0.77 | AK73: 412.93 | AN73: 44197 | AO73: 6.6
AA74: 43709 | AB74: 1 | AE74: 44682 | AF74: 0.35 | AG74: 3.381 | AI74: 44713 | AJ74: 1.21 | AK74: 377.25 | AN74: 44228 | AO74: 6
AA75: 43678 | AB75: 1 | AE75: 44713 | AF75: 0.85 | AG75: 3.767 | AI75: 44743 | AJ75: 1.68 | AK75: 411.99 | AN75: 44256 | AO75: 5.7
AA76: 43647 | AB76: 1 | AE76: 44743 | AF76: 1.35 | AG76: 3.429 | AI76: 44774 | AJ76: 2.33 | AK76: 395.18 | AN76: 44287 | AO76: 5.5
AA77: 43617 | AB77: 1.25 | AE77: 44774 | AF77: 1.85 | AG77: 3.361 | AI77: 44805 | AJ77: 2.56 | AK77: 357.18 | AN77: 44317 | AO77: 5.2
AA78: 43586 | AB78: 1.5 | AE78: 44805 | AF78: 2.35 | AG78: 3.747 | AI78: 44835 | AJ78: 3.08 | AK78: 386.21 | AN78: 44348 | AO78: 5
... AA108: 42583 | AB108: 1.5 | AE108: 45717 | AF108: 4.1 | AG108: 4.421 | AI108: 45748 | AJ108: 4.33 | AK108: 554.54 | AN108: 45261 | AO108: 3.7
AE109: 45748 | AF109: 4.1 | AG109: 4.267 | AI109: 45778 | AJ109: 4.33 | AK109: 589.39 | AN109: 45292 | AO109: 3.7
AE110: 45778 | AF110: 3.85 | AG110: 4.35 | AI110: 45809 | AJ110: 4.33 | AK110: 617.85 | AN110: 45323 | AO110: 3.7
AE111: 45809 | AF111: 3.85 | AG111: 4.208 | AI111: 45839 | AJ111: 4.33 | AK111: 632.08 | AN111: 45352 | AO111: 3.8
AE112: 45839 | AF112: 3.85 | AG112: 4.291 | AI112: 45870 | AJ112: 4.33 | AK112: 645.05 | AN112: 45383 | AO112: 3.8
AE113: 45870 | AF113: 3.6 | AG113: 4.275 | AI113: 45901 | AJ113: 4.22 | AK113: 666.18 | AN113: 45413 | AO113: 3.8
AE114: 45901 | AF114: 3.6 | AG114: 4.298 | AI114: 45931 | AJ114: 4.09 | AK114: 682.06 | AN114: 45444 | AO114: 3.9
AE115: 45931 | AF115: 3.6 | AG115: 4.234 | AI115: 45962 | AJ115: 3.88 | AK115: 683.39 | AN115: 45474 | AO115: 3.9
AE116: 45962 | AF116: 3.6 | AG116: 4.416 | AI116: 45992 | AJ116: 3.72 | AK116: 681.92 | AN116: 45505 | AO116: 3.9
AE117: 45992 | AF117: 3.6 | AG117: 4.719 | AI117: 46023 | AJ117: 3.64 | AK117: 691.97 | AN117: 45536 | AO117: 3.9
AE118: 46023 | AF118: 3.6 | AG118: 4.75 | AI118: 46054 | AJ118: 3.64 | AK118: 685.99 | AN118: 45566 | AO118: 3.9
AE119: 46054 | AF119: 3.85 | AG119: 4.758 | AI119: 46082 | AJ119: 3.64 | AK119: 650.34 | AN119: 45597 | AO119: 3.9
AE120: 46082 | AF120: 4.1 | AG120: 4.926 | AI120: 46113 | AJ120: 3.64 | AK120: 718.66 | AN120: 45627 | AO120: 4
... AE124: 46204 | AF124: 4.35 | AG124: 4.919 | AI124: 46235 | AJ124: 3.63 | AK124: 767.05 | AN124: 45748 | AO124: 4.1
AE125: 46235 | AF125: 4.35 | AG125: 5.015 | AN125: 45778 | AO125: 4.1
AN126: 45809 | AO126: 4.1
AN127: 45839 | AO127: 4.2
AN128: 45870 | AO128: 4.2
AN129: 45901 | AO129: 4.2
AN130: 45931 | AO130: 4.2
AN131: 45962 | AO131: 4.2
AN132: 45992 | AO132: 4.1
AN133: 46023 | AO133: 4.1
AN134: 46054 | AO134: 4.1
AN135: 46082 | AO135: 4.2
AN136: 46113 | AO136: 4.2
AN137: 46143 | AO137: 4.2
... AN139: 46204 | AO139: 4.3

Sheet US
A1: Oil Prices | B1: LSEG 7/9 | N1: US CPI | O1: LSEG7/9 | AD1: Federal funds effective rate | AH1: S&P 500 index - LSEG 7/9 | AL1: LSEG | AP1: LSEG
B2: WTC- (MID_PRICE) | C2: .DXY (TRDPRC_1) | F2: LSEG | G2: LSEG | N2: fred.stlouisfed.org/series/CPIAUCSL | O2: fred.stlouisfed.org/graph/?g=rocU | V2: https://fred.stlouisfed.org/series/dgs10 , 7/9/26 | AD2: https://fred.stlouisfed.org/series/fedfunds | AE2: 46272
P3: USGDPA=ECI (ECONOMIC) | V3: Date | W3: US 10 yr treasury yield - | AD3: observation_date | AE3: FEDFUNDS | AH3: Date | AI3: SPY (TRDPRC_1) | AK3: Date | AL3: Fed Funds Rate (%) | AM3: SPY Close ($) | AN3: SPY YoY Return (%) | AP3: Date | AQ3: Fed Funds Rate (%) RHS | AR3: SPY Close ($) LHS
A4: Date | B4: WTC Oil Price | C4: USD Index | E4: Date | F4: WTC Oil Price | G4: USD Index | N4: Date | O4: CPI YoY Inflation (%) | P4: Real GDP Growth, Annualized (%) | V4: 42619 | W4: 1.55 | AD4: 42583 | AE4: 0.4 | AI4: Close | AK4: 42614 | AL4: 0.4 | AM4: 216.3 | AP4: 42979 | AQ4: 1.15 | AR4: 16.148867
A5: 44440 | B5: 75.22 | C5: 94.23 | E5: 44440 | F5: =B5/$B$5*100 -> 100 | G5: =C5/$B$5*100 -> 125.27253 | N5: 44470 | O5: 6.24 | P5: 6.5 | V5: 42620 | W5: 1.54 | AD5: 42614 | AE5: 0.4 | AH5: 46266 | AI5: 770.19 | AK5: 42644 | AL5: 0.4 | AM5: 212.55 | AP5: 43009 | AQ5: 1.15 | AR5: 20.983298
A6: 44470 | B6: 83.5 | C6: 94.123 | E6: 44470 | F6: =B6/$B$5*100 -> 111.00771 | G6: =C6/$B$5*100 -> 125.13028 | N6: 44562 | O6: 7.56 | P6: 2 | V6: 42621 | W6: 1.61 | AD6: 42644 | AE6: 0.4 | AH6: 46237 | AI6: 767.05 | AK6: 42675 | AL6: 0.41 | AM6: 220.38 | AP6: 43040 | AQ6: 1.16 | AR6: 20.251384
A7: 44501 | B7: 66.14 | C7: 95.994 | E7: 44501 | F7: =B7/$B$5*100 -> 87.928742 | G7: =C7/$B$5*100 -> 127.61765 | N7: 44652 | O7: 8.23 | P7: 6.9 | V7: 42622 | W7: 1.67 | AD7: 42675 | AE7: 0.41 | AH7: 46204 | AI7: 747.03 | AK7: 42705 | AL7: 0.54 | AM7: 223.53 | AP7: 43070 | AQ7: 1.3 | AR7: 19.384423
A8: 44531 | B8: 75.33 | C8: 95.968 | E8: 44531 | F8: =B8/$B$5*100 -> 100.14624 | G8: =C8/$B$5*100 -> 127.58309 | N8: 44743 | O8: 8.46 | P8: -1.4 | V8: 42625 | W8: 1.68 | AD8: 42705 | AE8: 0.54 | AH8: 46174 | AI8: 746.77 | AK8: 42736 | AL8: 0.65 | AM8: 227.53 | AP8: 43101 | AQ8: 1.41 | AR8: 23.89575
A9: 44564 | B9: 89.16 | C9: 96.54 | E9: 44564 | F9: =B9/$B$5*100 -> 118.53231 | G9: =C9/$B$5*100 -> 128.34353 | N9: 44835 | O9: 7.76 | P9: -0.9 | V9: 42626 | W9: 1.73 | AD9: 42736 | AE9: 0.65 | AH9: 46143 | AI9: 756.48 | AK9: 42767 | AL9: 0.66 | AM9: 236.47 | AP9: 43132 | AQ9: 1.42 | AR9: 14.877151
A10: 44593 | B10: 96.13 | C10: 96.707 | E10: 44593 | F10: =B10/$B$5*100 -> 127.79846 | G10: =C10/$B$5*100 -> 128.56554 | N10: 44927 | O10: 6.33 | P10: 2.6 | V10: 42627 | W10: 1.7 | AD10: 42767 | AE10: 0.66 | AH10: 46113 | AI10: 718.66 | AK10: 42795 | AL10: 0.79 | AM10: 235.74 | AP10: 43160 | AQ10: 1.51 | AR10: 11.627216
A11: 44621 | B11: 100.53 | C11: 98.312 | E11: 44621 | F11: =B11/$B$5*100 -> 133.64797 | G11: =C11/$B$5*100 -> 130.69928 | N11: 45017 | O11: 4.95 | P11: 2.9 | V11: 42628 | W11: 1.71 | AD11: 42795 | AE11: 0.79 | AH11: 46083 | AI11: 650.34 | AK11: 42826 | AL11: 0.9 | AM11: 238.08 | AP11: 43191 | AQ11: 1.69 | AR11: 11.10131
A12: 44652 | B12: 104.59 | C12: 102.959 | E12: 44652 | F12: =B12/$B$5*100 -> 139.04547 | G12: =C12/$B$5*100 -> 136.87716 | N12: 45108 | O12: 3.29 | P12: 1.1 | V12: 42629 | W12: 1.7 | AD12: 42826 | AE12: 0.9 | AH12: 46055 | AI12: 685.99 | AK12: 42856 | AL12: 0.91 | AM12: 241.44 | AP12: 43221 | AQ12: 1.7 | AR12: 12.218357
A13: 44683 | B13: 114.38 | C13: 101.752 | E13: 44683 | F13: =B13/$B$5*100 -> 152.06062 | G13: =C13/$B$5*100 -> 135.27253 | N13: 45200 | O13: 3.25 | P13: 2.4 | V13: 42632 | W13: 1.7 | AD13: 42856 | AE13: 0.91 | AH13: 46023 | AI13: 691.97 | AK13: 42887 | AL13: 1.04 | AM13: 241.8 | AP13: 43252 | AQ13: 1.82 | AR13: 12.191894
A14: 44713 | B14: 107.76 | C14: 104.685 | E14: 44713 | F14: =B14/$B$5*100 -> 143.25977 | G14: =C14/$B$5*100 -> 139.17176 | N14: 45292 | O14: 3.09 | P14: 4.9 | V14: 42633 | W14: 1.69 | AD14: 42887 | AE14: 1.04 | AH14: 45992 | AI14: 681.92 | AK14: 42917 | AL14: 1.15 | AM14: 246.77 | AP14: 43282 | AQ14: 1.91 | AR14: 14.004944
A15: 44743 | B15: 101.31 | C15: 105.903 | E15: 44743 | F15: =B15/$B$5*100 -> 134.68492 | G15: =C15/$B$5*100 -> 140.79101 | N15: 45383 | O15: 3.36 | P15: 3.3 | V15: 42634 | W15: 1.66 | AD15: 42917 | AE15: 1.15 | AH15: 45964 | AI15: 683.39 | AK15: 42948 | AL15: 1.16 | AM15: 247.49 | AP15: 43313 | AQ15: 1.91 | AR15: 17.301709
A16: 44774 | B16: 90.09 | C16: 108.7 | E16: 44774 | F16: =B16/$B$5*100 -> 119.76868 | G16: =C16/$B$5*100 -> 144.50944 | N16: 45474 | O16: 2.94 | P16: 1.6 | V16: 42635 | W16: 1.63 | AD16: 42948 | AE16: 1.16 | AH16: 45931 | AI16: 682.06 | AK16: 42979 | AL16: 1.15 | AM16: 251.23 | AN16: =(AM16/AM4-1)*100 -> 16.148867 | AP16: 43344 | AQ16: 1.95 | AR16: 15.718664
A17: 44805 | B17: 79.91 | C17: 112.117 | E17: 44805 | F17: =B17/$B$5*100 -> 106.23504 | G17: =C17/$B$5*100 -> 149.05211 | N17: 45566 | O17: 2.58 | P17: 2.8 | V17: 42636 | W17: 1.62 | AD17: 42979 | AE17: 1.15 | AH17: 45901 | AI17: 666.18 | AK17: 43009 | AL17: 1.15 | AM17: 257.15 | AN17: =(AM17/AM5-1)*100 -> 20.983298 | AP17: 43374 | AQ17: 2.19 | AR17: 5.2420766
A18: 44837 | B18: 86.54 | C18: 111.527 | E18: 44837 | F18: =B18/$B$5*100 -> 115.04919 | G18: =C18/$B$5*100 -> 148.26775 | N18: 45658 | O18: 2.99 | P18: 2.8 | V18: 42639 | W18: 1.59 | AD18: 43009 | AE18: 1.15 | AH18: 45870 | AI18: 645.05 | AK18: 43040 | AL18: 1.16 | AM18: 265.01 | AN18: =(AM18/AM6-1)*100 -> 20.251384 | AP18: 43405 | AQ18: 2.2 | AR18: 4.0149428
A19: 44866 | B19: 80.48 | C19: 105.95 | E19: 44866 | F19: =B19/$B$5*100 -> 106.99282 | G19: =C19/$B$5*100 -> 140.8535 | N19: 45748 | O19: 2.33 | P19: 2.3 | V19: 42640 | W19: 1.56 | AD19: 43040 | AE19: 1.16 | AH19: 45839 | AI19: 632.08 | AK19: 43070 | AL19: 1.3 | AM19: 266.86 | AN19: =(AM19/AM7-1)*100 -> 19.384423 | AP19: 43435 | AQ19: 2.27 | AR19: -6.3478978
A20: 44896 | B20: 80.16 | C20: 103.522 | E20: 44896 | F20: =B20/$B$5*100 -> 106.5674 | G20: =C20/$B$5*100 -> 137.62563 | N20: 45839 | O20: 2.74 | P20: -0.3 | V20: 42641 | W20: 1.57 | AD20: 43070 | AE20: 1.3 | AH20: 45810 | AI20: 617.85 | AK20: 43101 | AL20: 1.41 | AM20: 281.9 | AN20: =(AM20/AM8-1)*100 -> 23.89575 | AP20: 43466 | AQ20: 2.4 | AR20: -4.2461866
A21: 44929 | B21: 78.95 | C21: 102.097 | E21: 44929 | F21: =B21/$B$5*100 -> 104.95879 | G21: =C21/$B$5*100 -> 135.73119 | N21: 45931 | O21: 2.86 | P21: 3 | V21: 42642 | W21: 1.56 | AD21: 43101 | AE21: 1.41 | AH21: 45778 | AI21: 589.39 | AK21: 43132 | AL21: 1.42 | AM21: 271.65 | AN21: =(AM21/AM9-1)*100 -> 14.877151 | AP21: 43497 | AQ21: 2.4 | AR21: 2.5878888
A22: 44958 | B22: 76.88 | C22: 104.869 | E22: 44958 | F22: =B22/$B$5*100 -> 102.20686 | G22: =C22/$B$5*100 -> 139.41638 | N22: 46023 | O22: 2.39 | P22: 4.3 | V22: 42643 | W22: 1.6 | AD22: 43132 | AE22: 1.42 | AH22: 45748 | AI22: 554.54 | AK22: 43160 | AL22: 1.51 | AM22: 263.15 | AN22: =(AM22/AM10-1)*100 -> 11.627216 | AP22: 43525 | AQ22: 2.41 | AR22: 7.3456204
A23: 44986 | B23: 75.68 | C23: 102.506 | E23: 44986 | F23: =B23/$B$5*100 -> 100.61154 | G23: =C23/$B$5*100 -> 136.27493 | N23: 46113 | O23: 3.78 | P23: 1.4 | V23: 42646 | W23: 1.63 | AD23: 43160 | AE23: 1.51 | AH23: 45719 | AI23: 559.39 | AK23: 43191 | AL23: 1.69 | AM23: 264.51 | AN23: =(AM23/AM11-1)*100 -> 11.10131 | AP23: 43556 | AQ23: 2.42 | AR23: 11.156478
A24: 45019 | B24: 76.78 | C24: 101.659 | E24: 45019 | F24: =B24/$B$5*100 -> 102.07392 | G24: =C24/$B$5*100 -> 135.1489 | N24: 46204 | O24: 3.3 | P24: 2 | V24: 42647 | W24: 1.69 | AD24: 43191 | AE24: 1.69 | AH24: 45691 | AI24: 594.18 | AK24: 43221 | AL24: 1.7 | AM24: 270.94 | AN24: =(AM24/AM12-1)*100 -> 12.218357 | AP24: 43586 | AQ24: 2.39 | AR24: 1.5981398
A25: 45047 | B25: 68.11 | C25: 104.326 | E25: 45047 | F25: =B25/$B$5*100 -> 90.547727 | G25: =C25/$B$5*100 -> 138.6945 | V25: 42648 | W25: 1.72 | AD25: 43221 | AE25: 1.7 | AH25: 45658 | AI25: 601.82 | AK25: 43252 | AL25: 1.82 | AM25: 271.28 | AN25: =(AM25/AM13-1)*100 -> 12.191894 | AP25: 43617 | AQ25: 2.38 | AR25: 8.0064878
A26: 45078 | B26: 70.66 | C26: 102.912 | E26: 45078 | F26: =B26/$B$5*100 -> 93.937783 | G26: =C26/$B$5*100 -> 136.81468 | V26: 42649 | W26: 1.75 | AD26: 43252 | AE26: 1.82 | AH26: 45628 | AI26: 586.08 | AK26: 43282 | AL26: 1.91 | AM26: 281.33 | AN26: =(AM26/AM14-1)*100 -> 14.004944 | AP26: 43647 | AQ26: 2.4 | AR26: 5.7228166
A27: 45110 | B27: 81.8 | C27: 101.855 | E27: 45110 | F27: =B27/$B$5*100 -> 108.74767 | G27: =C27/$B$5*100 -> 135.40947 | V27: 42650 | W27: 1.73 | AD27: 43282 | AE27: 1.91 | AH27: 45597 | AI27: 602.55 | AK27: 43313 | AL27: 1.91 | AM27: 290.31 | AN27: =(AM27/AM15-1)*100 -> 17.301709 | AP27: 43678 | AQ27: 2.13 | AR27: 0.73714305
A28: 45139 | B28: 83.55 | C28: 103.619 | E28: 45139 | F28: =B28/$B$5*100 -> 111.07418 | G28: =C28/$B$5*100 -> 137.75459 | V28: 42653 | AD28: 43313 | AE28: 1.91 | AH28: 45566 | AI28: 568.64 | AK28: 43344 | AL28: 1.95 | AM28: 290.72 | AN28: =(AM28/AM16-1)*100 -> 15.718664 | AP28: 43709 | AQ28: 2.04 | AR28: 2.0810402
A29: 45170 | B29: 90.77 | C29: 106.224 | E29: 45170 | F29: =B29/$B$5*100 -> 120.67269 | G29: =C29/$B$5*100 -> 141.21776 | V29: 42654 | W29: 1.77 | AD29: 43344 | AE29: 1.95 | AH29: 45537 | AI29: 573.76 | AK29: 43374 | AL29: 2.19 | AM29: 270.63 | AN29: =(AM29/AM17-1)*100 -> 5.2420766 | AP29: 43739 | AQ29: 1.83 | AR29: 12.082918
A30: 45201 | B30: 81.64 | C30: 106.663 | E30: 45201 | F30: =B30/$B$5*100 -> 108.53496 | G30: =C30/$B$5*100 -> 141.80138 | V30: 42655 | W30: 1.79 | AD30: 43374 | AE30: 2.19 | AH30: 45505 | AI30: 563.68 | AK30: 43405 | AL30: 2.2 | AM30: 275.65 | AN30: =(AM30/AM18-1)*100 -> 4.0149428 | AP30: 43770 | AQ30: 1.55 | AR30: 14.025032
A31: 45231 | B31: 75.66 | C31: 103.497 | E31: 45231 | F31: =B31/$B$5*100 -> 100.58495 | G31: =C31/$B$5*100 -> 137.5924 | V31: 42656 | W31: 1.75 | AD31: 43405 | AE31: 2.2 | AH31: 45474 | AI31: 550.81 | AK31: 43435 | AL31: 2.27 | AM31: 249.92 | AN31: =(AM31/AM19-1)*100 -> -6.3478978 | AP31: 43800 | AQ31: 1.55 | AR31: 28.785211
A32: 45261 | B32: 71.89 | C32: 101.333 | E32: 45261 | F32: =B32/$B$5*100 -> 95.572986 | G32: =C32/$B$5*100 -> 134.7155 | V32: 42657 | W32: 1.8 | AD32: 43435 | AE32: 2.27 | AH32: 45446 | AI32: 544.22 | AK32: 43466 | AL32: 2.4 | AM32: 269.93 | AN32: =(AM32/AM20-1)*100 -> -4.2461866 | AP32: 43831 | AQ32: 1.55 | AR32: 19.19016
A33: 45293 | B33: 76.28 | C33: 103.274 | E33: 45293 | F33: =B33/$B$5*100 -> 101.4092 | G33: =C33/$B$5*100 -> 137.29593 | V33: 42660 | W33: 1.77 | AD33: 43466 | AE33: 2.4 | AH33: 45413 | AI33: 527.37 | AK33: 43497 | AL33: 2.4 | AM33: 278.68 | AN33: =(AM33/AM21-1)*100 -> 2.5878888 | AP33: 43862 | AQ33: 1.58 | AR33: 6.3083106
A34: 45323 | B34: 79.22 | C34: 104.156 | E34: 45323 | F34: =B34/$B$5*100 -> 105.31773 | G34: =C34/$B$5*100 -> 138.46849 | V34: 42661 | W34: 1.75 | AD34: 43497 | AE34: 2.4 | AH34: 45383 | AI34: 501.98 | AK34: 43525 | AL34: 2.41 | AM34: 282.48 | AN34: =(AM34/AM22-1)*100 -> 7.3456204 | AP34: 43891 | AQ34: 0.65 | AR34: -8.7546021
A35: 45352 | B35: 83.96 | C35: 104.546 | E35: 45352 | F35: =B35/$B$5*100 -> 111.61925 | G35: =C35/$B$5*100 -> 138.98697 | V35: 42662 | W35: 1.76 | AD35: 43525 | AE35: 2.41 | AH35: 45352 | AI35: 523.07 | AK35: 43556 | AL35: 2.42 | AM35: 294.02 | AN35: =(AM35/AM23-1)*100 -> 11.156478 | AP35: 43922 | AQ35: 0.05 | AR35: -1.2039997
A36: 45383 | B36: 83.49 | C36: 106.221 | E36: 45383 | F36: =B36/$B$5*100 -> 110.99442 | G36: =C36/$B$5*100 -> 141.21377 | V36: 42663 | W36: 1.76 | AD36: 43556 | AE36: 2.42 | AH36: 45323 | AI36: 508.08 | AK36: 43586 | AL36: 2.39 | AM36: 275.27 | AN36: =(AM36/AM24-1)*100 -> 1.5981398 | AP36: 43952 | AQ36: 0.05 | AR36: 10.553275
A37: 45413 | B37: 77.97 | C37: 104.671 | E37: 45413 | F37: =B37/$B$5*100 -> 103.65594 | G37: =C37/$B$5*100 -> 139.15315 | V37: 42664 | W37: 1.74 | AD37: 43586 | AE37: 2.39 | AH37: 45292 | AI37: 482.88 | AK37: 43617 | AL37: 2.38 | AM37: 293 | AN37: =(AM37/AM25-1)*100 -> 8.0064878 | AP37: 43983 | AQ37: 0.08 | AR37: 5.2423208
A38: 45446 | B38: 82.83 | C38: 105.866 | E38: 45446 | F38: =B38/$B$5*100 -> 110.11699 | G38: =C38/$B$5*100 -> 140.74182 | V38: 42667 | W38: 1.77 | AD38: 43617 | AE38: 2.38 | AH38: 45261 | AI38: 475.31 | AK38: 43647 | AL38: 2.4 | AM38: 297.43 | AN38: =(AM38/AM26-1)*100 -> 5.7228166 | AP38: 44013 | AQ38: 0.09 | AR38: 9.7804525
A39: 45474 | B39: 79.36 | C39: 104.096 | E39: 45474 | F39: =B39/$B$5*100 -> 105.50386 | G39: =C39/$B$5*100 -> 138.38873 | V39: 42668 | W39: 1.77 | AD39: 43647 | AE39: 2.4 | AH39: 45231 | AI39: 456.4 | AK39: 43678 | AL39: 2.13 | AM39: 292.45 | AN39: =(AM39/AM27-1)*100 -> 0.73714305 | AP39: 44044 | AQ39: 0.1 | AR39: 19.44264
A40: 45505 | B40: 74.52 | C40: 101.698 | E40: 45505 | F40: =B40/$B$5*100 -> 99.069396 | G40: =C40/$B$5*100 -> 135.20074 | V40: 42669 | W40: 1.79 | AD40: 43678 | AE40: 2.13 | AH40: 45201 | AI40: 418.2 | AK40: 43709 | AL40: 2.04 | AM40: 296.77 | AN40: =(AM40/AM28-1)*100 -> 2.0810402 | AP40: 44075 | AQ40: 0.09 | AR40: 12.844964
... A51: 45839 | B51: 70.36 | C51: 99.968 | E51: 45839 | F51: =B51/$B$5*100 -> 93.538952 | G51: =C51/$B$5*100 -> 132.90082 | V51: 42684 | W51: 2.15 | AD51: 44013 | AE51: 0.09 | AH51: 44866 | AI51: 407.68 | AK51: 44044 | AL51: 0.1 | AM51: 349.31 | AN51: =(AM51/AM39-1)*100 -> 19.44264 | AP51: 44409 | AQ51: 0.09 | AR51: 29.271993
A52: 45870 | B52: 64.36 | C52: 97.771 | E52: 45870 | F52: =B52/$B$5*100 -> 85.56235 | G52: =C52/$B$5*100 -> 129.98006 | V52: 42685 | AD52: 44044 | AE52: 0.1 | AH52: 44837 | AI52: 386.21 | AK52: 44075 | AL52: 0.09 | AM52: 334.89 | AN52: =(AM52/AM40-1)*100 -> 12.844964 | AP52: 44440 | AQ52: 0.08 | AR52: 28.14357
A53: 45902 | B53: 63.17 | C53: 97.775 | E53: 45902 | F53: =B53/$B$5*100 -> 83.980324 | G53: =C53/$B$5*100 -> 129.98538 | V53: 42688 | W53: 2.23 | AD53: 44075 | AE53: 0.09 | AH53: 44805 | AI53: 357.18 | AK53: 44105 | AL53: 0.09 | AM53: 326.54 | AN53: =(AM53/AM41-1)*100 -> 7.6517324 | AP53: 44470 | AQ53: 0.08 | AR53: 40.641269
A54: 45931 | B54: 61.75 | C54: 99.804 | E54: 45931 | F54: =B54/$B$5*100 -> 82.092529 | G54: =C54/$B$5*100 -> 132.6828 | V54: 42689 | W54: 2.23 | AD54: 44105 | AE54: 0.09 | AH54: 44774 | AI54: 395.18 | AK54: 44136 | AL54: 0.09 | AM54: 362.06 | AN54: =(AM54/AM42-1)*100 -> 15.192008 | AP54: 44501 | AQ54: 0.08 | AR54: 25.824449
A55: 45964 | B55: 58.58 | C55: 99.444 | E55: 45964 | F55: =B55/$B$5*100 -> 77.878224 | G55: =C55/$B$5*100 -> 132.2042 | V55: 42690 | W55: 2.22 | AD55: 44136 | AE55: 0.09 | AH55: 44743 | AI55: 411.99 | AK55: 44166 | AL55: 0.09 | AM55: 373.88 | AN55: =(AM55/AM43-1)*100 -> 16.162307 | AP55: 44531 | AQ55: 0.08 | AR55: 27.035412
A56: 45992 | B56: 57.26 | C56: 98.322 | E56: 45992 | F56: =B56/$B$5*100 -> 76.123371 | G56: =C56/$B$5*100 -> 130.71258 | V56: 42691 | W56: 2.29 | AD56: 44166 | AE56: 0.09 | AH56: 44713 | AI56: 377.25 | AK56: 44197 | AL56: 0.09 | AM56: 370.07 | AN56: =(AM56/AM44-1)*100 -> 15.025021 | AP56: 44562 | AQ56: 0.08 | AR56: 21.574297
A57: 46024 | B57: 64.5 | C57: 96.991 | E57: 46024 | F57: =B57/$B$5*100 -> 85.748471 | G57: =C57/$B$5*100 -> 128.9431 | V57: 42692 | W57: 2.34 | AD57: 44197 | AE57: 0.09 | AH57: 44683 | AI57: 412.93 | AK57: 44228 | AL57: 0.08 | AM57: 380.36 | AN57: =(AM57/AM45-1)*100 -> 28.387227 | AP57: 44593 | AQ57: 0.08 | AR57: 14.793879
A58: 46055 | B58: 66.96 | C58: 97.608 | E58: 46055 | F58: =B58/$B$5*100 -> 89.018878 | G58: =C58/$B$5*100 -> 129.76336 | V58: 42695 | W58: 2.33 | AD58: 44228 | AE58: 0.08 | AH58: 44652 | AI58: 412 | AK58: 44256 | AL58: 0.07 | AM58: 396.33 | AN58: =(AM58/AM46-1)*100 -> 53.765276 | AP58: 44621 | AQ58: 0.2 | AR58: 13.955542
A59: 46083 | B59: 102.86 | C59: 99.961 | E59: 46083 | F59: =B59/$B$5*100 -> 136.74555 | G59: =C59/$B$5*100 -> 132.89152 | V59: 42696 | W59: 2.31 | AD59: 44256 | AE59: 0.07 | AH59: 44621 | AI59: 451.64 | AK59: 44287 | AL59: 0.07 | AM59: 417.3 | AN59: =(AM59/AM47-1)*100 -> 43.658772 | AP59: 44652 | AQ59: 0.33 | AR59: -1.2700695
A60: 46113 | B60: 108.64 | C60: 98.056 | E60: 46113 | F60: =B60/$B$5*100 -> 144.42967 | G60: =C60/$B$5*100 -> 130.35895 | V60: 42697 | W60: 2.36 | AD60: 44287 | AE60: 0.07 | AH60: 44593 | AI60: 436.63 | AK60: 44317 | AL60: 0.06 | AM60: 420.04 | AN60: =(AM60/AM48-1)*100 -> 38.025762 | AP60: 44682 | AQ60: 0.77 | AR60: -1.6926959
A61: 46143 | B61: 91.16 | C61: 98.908 | E61: 46143 | F61: =B61/$B$5*100 -> 121.19117 | G61: =C61/$B$5*100 -> 131.49162 | V61: 42698 | AD61: 44317 | AE61: 0.06 | AH61: 44564 | AI61: 449.91 | AK61: 44348 | AL61: 0.08 | AM61: 428.06 | AN61: =(AM61/AM49-1)*100 -> 38.818264 | AP61: 44713 | AQ61: 1.21 | AR61: -11.869831
A62: 46174 | B62: 70.56 | C62: 101.187 | E62: 46174 | F62: =B62/$B$5*100 -> 93.804839 | G62: =C62/$B$5*100 -> 134.5214 | V62: 42699 | W62: 2.36 | AD62: 44348 | AE62: 0.08 | AH62: 44531 | AI62: 474.96 | AK62: 44378 | AL62: 0.1 | AM62: 438.51 | AN62: =(AM62/AM50-1)*100 -> 34.298052 | AP62: 44743 | AQ62: 1.68 | AR62: -6.0477526
A63: 46204 | B63: 86.16 | C63: 99.914 | E63: 46204 | F63: =B63/$B$5*100 -> 114.544 | G63: =C63/$B$5*100 -> 132.82903 | V63: 42702 | W63: 2.32 | AD63: 44378 | AE63: 0.1 | AH63: 44501 | AI63: 455.56 | AK63: 44409 | AL63: 0.09 | AM63: 451.56 | AN63: =(AM63/AM51-1)*100 -> 29.271993 | AP63: 44774 | AQ63: 2.33 | AR63: -12.485605
A64: 46237 | B64: 87.03 | C64: 99.428 | E64: 46237 | F64: =B64/$B$5*100 -> 115.70061 | G64: =C64/$B$5*100 -> 132.18293 | V64: 42703 | W64: 2.3 | AD64: 44409 | AE64: 0.09 | AH64: 44470 | AI64: 459.25 | AK64: 44440 | AL64: 0.08 | AM64: 429.14 | AN64: =(AM64/AM52-1)*100 -> 28.14357 | AP64: 44805 | AQ64: 2.56 | AR64: -16.768421
A65: 46266 | B65: 92.69 | C65: 99.166 | E65: 46266 | F65: =B65/$B$5*100 -> 123.22521 | G65: =C65/$B$5*100 -> 131.83462 | V65: 42704 | W65: 2.37 | AD65: 44440 | AE65: 0.08 | AH65: 44440 | AI65: 429.14 | AK65: 44470 | AL65: 0.08 | AM65: 459.25 | AN65: =(AM65/AM53-1)*100 -> 40.641269 | AP65: 44835 | AQ65: 3.08 | AR65: -15.904192
V66: 42705 | W66: 2.45 | AD66: 44470 | AE66: 0.08 | AH66: 44410 | AI66: 451.56 | AK66: 44501 | AL66: 0.08 | AM66: 455.56 | AN66: =(AM66/AM54-1)*100 -> 25.824449 | AP66: 44866 | AQ66: 3.78 | AR66: -10.510141
V67: 42706 | W67: 2.4 | AD67: 44501 | AE67: 0.08 | AH67: 44378 | AI67: 438.51 | AK67: 44531 | AL67: 0.08 | AM67: 474.96 | AN67: =(AM67/AM55-1)*100 -> 27.035412 | AP67: 44896 | AQ67: 4.1 | AR67: -19.481641
V68: 42709 | W68: 2.39 | AD68: 44531 | AE68: 0.08 | AH68: 44348 | AI68: 428.06 | AK68: 44562 | AL68: 0.08 | AM68: 449.91 | AN68: =(AM68/AM56-1)*100 -> 21.574297 | AP68: 44927 | AQ68: 4.33 | AR68: -9.6530417
V69: 42710 | W69: 2.39 | AD69: 44562 | AE69: 0.08 | AH69: 44319 | AI69: 420.04 | AK69: 44593 | AL69: 0.08 | AM69: 436.63 | AN69: =(AM69/AM57-1)*100 -> 14.793879 | AP69: 44958 | AQ69: 4.57 | AR69: -9.2458145
V70: 42711 | W70: 2.34 | AD70: 44593 | AE70: 0.08 | AH70: 44287 | AI70: 417.3 | AK70: 44621 | AL70: 0.2 | AM70: 451.64 | AN70: =(AM70/AM58-1)*100 -> 13.955542 | AP70: 44986 | AQ70: 4.65 | AR70: -9.3547959
V71: 42712 | W71: 2.4 | AD71: 44621 | AE71: 0.2 | AH71: 44256 | AI71: 396.33 | AK71: 44652 | AL71: 0.33 | AM71: 412 | AN71: =(AM71/AM59-1)*100 -> -1.2700695 | AP71: 45017 | AQ71: 4.83 | AR71: 0.9538835
V72: 42713 | W72: 2.47 | AD72: 44652 | AE72: 0.33 | AH72: 44228 | AI72: 380.36 | AK72: 44682 | AL72: 0.77 | AM72: 412.93 | AN72: =(AM72/AM60-1)*100 -> -1.6926959 | AP72: 45047 | AQ72: 5.06 | AR72: 1.1914852
V73: 42716 | W73: 2.49 | AD73: 44682 | AE73: 0.77 | AH73: 44197 | AI73: 370.07 | AK73: 44713 | AL73: 1.21 | AM73: 377.25 | AN73: =(AM73/AM61-1)*100 -> -11.869831 | AP73: 45078 | AQ73: 5.08 | AR73: 17.502982
V74: 42717 | W74: 2.48 | AD74: 44713 | AE74: 1.21 | AH74: 44166 | AI74: 373.88 | AK74: 44743 | AL74: 1.68 | AM74: 411.99 | AN74: =(AM74/AM62-1)*100 -> -6.0477526 | AP74: 45108 | AQ74: 5.12 | AR74: 11.116775
V75: 42718 | W75: 2.54 | AD75: 44743 | AE75: 1.68 | AH75: 44137 | AI75: 362.06 | AK75: 44774 | AL75: 2.33 | AM75: 395.18 | AN75: =(AM75/AM63-1)*100 -> -12.485605 | AP75: 45139 | AQ75: 5.33 | AR75: 13.960727
V76: 42719 | W76: 2.6 | AD76: 44774 | AE76: 2.33 | AH76: 44105 | AI76: 326.54 | AK76: 44805 | AL76: 2.56 | AM76: 357.18 | AN76: =(AM76/AM64-1)*100 -> -16.768421 | AP76: 45170 | AQ76: 5.33 | AR76: 19.681953
V77: 42720 | W77: 2.6 | AD77: 44805 | AE77: 2.56 | AH77: 44075 | AI77: 334.89 | AK77: 44835 | AL77: 3.08 | AM77: 386.21 | AN77: =(AM77/AM65-1)*100 -> -15.904192 | AP77: 45200 | AQ77: 5.33 | AR77: 8.2830584
... V82: 42727 | W82: 2.55 | AD82: 44958 | AE82: 4.57 | AH82: 43922 | AI82: 290.48 | AK82: 44986 | AL82: 4.65 | AM82: 409.39 | AN82: =(AM82/AM70-1)*100 -> -9.3547959 | AP82: 45352 | AQ82: 5.33 | AR82: 27.768143
V83: 42730 | AD83: 44986 | AE83: 4.65 | AH83: 43892 | AI83: 257.75 | AK83: 45017 | AL83: 4.83 | AM83: 415.93 | AN83: =(AM83/AM71-1)*100 -> 0.9538835 | AP83: 45383 | AQ83: 5.33 | AR83: 20.688577
V84: 42731 | W84: 2.57 | AD84: 45017 | AE84: 4.83 | AH84: 43864 | AI84: 296.26 | AK84: 45047 | AL84: 5.06 | AM84: 417.85 | AN84: =(AM84/AM72-1)*100 -> 1.1914852 | AP84: 45413 | AQ84: 5.33 | AR84: 26.210363
V85: 42732 | W85: 2.51 | AD85: 45047 | AE85: 5.06 | AH85: 43831 | AI85: 321.73 | AK85: 45078 | AL85: 5.08 | AM85: 443.28 | AN85: =(AM85/AM73-1)*100 -> 17.502982 | AP85: 45444 | AQ85: 5.33 | AR85: 22.77116
V86: 42733 | W86: 2.49 | AD86: 45078 | AE86: 5.08 | AH86: 43801 | AI86: 321.86 | AK86: 45108 | AL86: 5.12 | AM86: 457.79 | AN86: =(AM86/AM74-1)*100 -> 11.116775 | AP86: 45474 | AQ86: 5.33 | AR86: 20.31936
V87: 42734 | W87: 2.45 | AD87: 45108 | AE87: 5.12 | AH87: 43770 | AI87: 314.31 | AK87: 45139 | AL87: 5.33 | AM87: 450.35 | AN87: =(AM87/AM75-1)*100 -> 13.960727 | AP87: 45505 | AQ87: 5.33 | AR87: 25.164872
V88: 42737 | AD88: 45139 | AE88: 5.33 | AH88: 43739 | AI88: 303.33 | AK88: 45170 | AL88: 5.33 | AM88: 427.48 | AN88: =(AM88/AM76-1)*100 -> 19.681953 | AP88: 45536 | AQ88: 5.13 | AR88: 34.219145
V89: 42738 | W89: 2.45 | AD89: 45170 | AE89: 5.33 | AH89: 43710 | AI89: 296.77 | AK89: 45200 | AL89: 5.33 | AM89: 418.2 | AN89: =(AM89/AM77-1)*100 -> 8.2830584 | AP89: 45566 | AQ89: 4.83 | AR89: 35.973219
V90: 42739 | W90: 2.46 | AD90: 45200 | AE90: 5.33 | AH90: 43678 | AI90: 292.45 | AK90: 45231 | AL90: 5.33 | AM90: 456.4 | AN90: =(AM90/AM78-1)*100 -> 11.950549 | AP90: 45597 | AQ90: 4.64 | AR90: 32.022349
V91: 42740 | W91: 2.37 | AD91: 45231 | AE91: 5.33 | AH91: 43647 | AI91: 297.43 | AK91: 45261 | AL91: 5.33 | AM91: 475.31 | AN91: =(AM91/AM79-1)*100 -> 24.286798 | AP91: 45627 | AQ91: 4.48 | AR91: 23.304791
V92: 42741 | W92: 2.42 | AD92: 45261 | AE92: 5.33 | AH92: 43619 | AI92: 293 | AK92: 45292 | AL92: 5.33 | AM92: 482.88 | AN92: =(AM92/AM80-1)*100 -> 18.795513 | AP92: 45658 | AQ92: 4.33 | AR92: 24.631378
V93: 42744 | W93: 2.38 | AD93: 45292 | AE93: 5.33 | AH93: 43586 | AI93: 275.27 | AK93: 45323 | AL93: 5.33 | AM93: 508.08 | AN93: =(AM93/AM81-1)*100 -> 28.218846 | AP93: 45689 | AQ93: 4.33 | AR93: 16.94615
V94: 42745 | W94: 2.38 | AD94: 45323 | AE94: 5.33 | AH94: 43556 | AI94: 294.02 | AK94: 45352 | AL94: 5.33 | AM94: 523.07 | AN94: =(AM94/AM82-1)*100 -> 27.768143 | AP94: 45717 | AQ94: 4.33 | AR94: 6.9436213
V95: 42746 | W95: 2.38 | AD95: 45352 | AE95: 5.33 | AH95: 43525 | AI95: 282.48 | AK95: 45383 | AL95: 5.33 | AM95: 501.98 | AN95: =(AM95/AM83-1)*100 -> 20.688577 | AP95: 45748 | AQ95: 4.33 | AR95: 10.470537
V96: 42747 | W96: 2.36 | AD96: 45383 | AE96: 5.33 | AH96: 43497 | AI96: 278.68 | AK96: 45413 | AL96: 5.33 | AM96: 527.37 | AN96: =(AM96/AM84-1)*100 -> 26.210363 | AP96: 45778 | AQ96: 4.33 | AR96: 11.760244
V97: 42748 | W97: 2.4 | AD97: 45413 | AE97: 5.33 | AH97: 43466 | AI97: 269.93 | AK97: 45444 | AL97: 5.33 | AM97: 544.22 | AN97: =(AM97/AM85-1)*100 -> 22.77116 | AP97: 45809 | AQ97: 4.33 | AR97: 13.529455
V98: 42751 | AD98: 45444 | AE98: 5.33 | AH98: 43437 | AI98: 249.92 | AK98: 45474 | AL98: 5.33 | AM98: 550.81 | AN98: =(AM98/AM86-1)*100 -> 20.31936 | AP98: 45839 | AQ98: 4.33 | AR98: 14.754634
V99: 42752 | W99: 2.33 | AD99: 45474 | AE99: 5.33 | AH99: 43405 | AI99: 275.65 | AK99: 45505 | AL99: 5.33 | AM99: 563.68 | AN99: =(AM99/AM87-1)*100 -> 25.164872 | AP99: 45870 | AQ99: 4.33 | AR99: 14.435495
V100: 42753 | W100: 2.42 | AD100: 45505 | AE100: 5.33 | AH100: 43374 | AI100: 270.63 | AK100: 45536 | AL100: 5.13 | AM100: 573.76 | AN100: =(AM100/AM88-1)*100 -> 34.219145 | AP100: 45901 | AQ100: 4.22 | AR100: 16.10778
V101: 42754 | W101: 2.47 | AD101: 45536 | AE101: 5.13 | AH101: 43346 | AI101: 290.72 | AK101: 45566 | AL101: 4.83 | AM101: 568.64 | AN101: =(AM101/AM89-1)*100 -> 35.973219 | AP101: 45931 | AQ101: 4.09 | AR101: 19.945836
V102: 42755 | W102: 2.48 | AD102: 45566 | AE102: 4.83 | AH102: 43313 | AI102: 290.31 | AK102: 45597 | AL102: 4.64 | AM102: 602.55 | AN102: =(AM102/AM90-1)*100 -> 32.022349 | AP102: 45962 | AQ102: 3.88 | AR102: 13.416314
V103: 42758 | W103: 2.41 | AD103: 45597 | AE103: 4.64 | AH103: 43283 | AI103: 281.33 | AK103: 45627 | AL103: 4.48 | AM103: 586.08 | AN103: =(AM103/AM91-1)*100 -> 23.304791 | AP103: 45992 | AQ103: 3.72 | AR103: 16.352716
V104: 42759 | W104: 2.47 | AD104: 45627 | AE104: 4.48 | AH104: 43252 | AI104: 271.28 | AK104: 45658 | AL104: 4.33 | AM104: 601.82 | AN104: =(AM104/AM92-1)*100 -> 24.631378 | AP104: 46023 | AQ104: 3.64 | AR104: 14.979562
V105: 42760 | W105: 2.53 | AD105: 45658 | AE105: 4.33 | AH105: 43221 | AI105: 270.94 | AK105: 45689 | AL105: 4.33 | AM105: 594.18 | AN105: =(AM105/AM93-1)*100 -> 16.94615 | AP105: 46054 | AQ105: 3.64 | AR105: 15.451547
V106: 42761 | W106: 2.51 | AD106: 45689 | AE106: 4.33 | AH106: 43192 | AI106: 264.51 | AK106: 45717 | AL106: 4.33 | AM106: 559.39 | AN106: =(AM106/AM94-1)*100 -> 6.9436213 | AP106: 46082 | AQ106: 3.64 | AR106: 16.258782
V107: 42762 | W107: 2.49 | AD107: 45717 | AE107: 4.33 | AH107: 43160 | AI107: 263.15 | AK107: 45748 | AL107: 4.33 | AM107: 554.54 | AN107: =(AM107/AM95-1)*100 -> 10.470537 | AP107: 46113 | AQ107: 3.64 | AR107: 29.595701
V108: 42765 | W108: 2.49 | AD108: 45748 | AE108: 4.33 | AH108: 43132 | AI108: 271.65 | AK108: 45778 | AL108: 4.33 | AM108: 589.39 | AN108: =(AM108/AM96-1)*100 -> 11.760244 | AP108: 46143 | AQ108: 3.63 | AR108: 28.34965
V109: 42766 | W109: 2.45 | AD109: 45778 | AE109: 4.33 | AH109: 43102 | AI109: 281.9 | AK109: 45809 | AL109: 4.33 | AM109: 617.85 | AN109: =(AM109/AM97-1)*100 -> 13.529455 | AP109: 46174 | AQ109: 3.63 | AR109: 20.865906
V110: 42767 | W110: 2.48 | AD110: 45809 | AE110: 4.33 | AH110: 43070 | AI110: 266.86 | AK110: 45839 | AL110: 4.33 | AM110: 632.08 | AN110: =(AM110/AM98-1)*100 -> 14.754634 | AP110: 46204 | AQ110: 3.63 | AR110: 18.185989
V111: 42768 | W111: 2.48 | AD111: 45839 | AE111: 4.33 | AH111: 43040 | AI111: 265.01 | AK111: 45870 | AL111: 4.33 | AM111: 645.05 | AN111: =(AM111/AM99-1)*100 -> 14.435495 | AP111: 46235 | AQ111: 3.63 | AR111: 18.913263
V112: 42769 | W112: 2.49 | AD112: 45870 | AE112: 4.33 | AH112: 43010 | AI112: 257.15 | AK112: 45901 | AL112: 4.22 | AM112: 666.18 | AN112: =(AM112/AM100-1)*100 -> 16.10778
V113: 42772 | W113: 2.42 | AD113: 45901 | AE113: 4.22 | AH113: 42979 | AI113: 251.23 | AK113: 45931 | AL113: 4.09 | AM113: 682.06 | AN113: =(AM113/AM101-1)*100 -> 19.945836
V114: 42773 | W114: 2.4 | AD114: 45931 | AE114: 4.09 | AH114: 42948 | AI114: 247.49 | AK114: 45962 | AL114: 3.88 | AM114: 683.39 | AN114: =(AM114/AM102-1)*100 -> 13.416314
...

Sheet Euro
A1: Euro 10 yr GDP - LSEG 7/9 | E1: EURO STOXX 50 indexed performance - LSEG 7/9 | O1: data columns Q-V sourced from LSEG | P1: Date | Q1: STOXX 50 | R1: Oil & Gas Index | S1: EUR/USD | T1: STOXX 50 (Indexed) | U1: Oil & Gas Index (Indexed) | V1: EUR/USD (Indexed) | AI1: fred.stlouisfed.org/series/ECBDFR
E2: Euro oil and gas index | P2: 42552 | Q2: 3002.24 | R2: 279.53 | S2: 1.1238 | T2: =Q2/$Q$2*100 -> 100 | U2: =R2/$R$2*100 -> 100 | V2: =S2/$S$2*100 -> 100 | AI2: fred.stlouisfed.org/series/IRLTLT01DEM156N
A3: Date | B3: Euro Area Real GDP YoY (%) | C3: Euro Area HICP Inflation YoY (%) | F3: .STOXX50E (TRDPRC_1) | G3: .SXEE (TRDPRC_1) | I3: LSEG 7/9 | P3: 42644 | Q3: 3290.52 | R3: 324.01 | S3: 1.0513 | T3: =Q3/$Q$2*100 -> 109.60216 | U3: =R3/$R$2*100 -> 115.91242 | V3: =S3/$S$2*100 -> 93.548674
A4: 42552 | B4: 1.6 | C4: 0.27 | E4: Date | F4: STOXX 50 | G4: Oil & Gas Index | I4: Date | J4: EUR= (BID) | P4: 42736 | Q4: 3500.93 | R4: 319.2 | S4: 1.0649 | T4: =Q4/$Q$2*100 -> 116.6106 | U4: =R4/$R$2*100 -> 114.19168 | V4: =S4/$S$2*100 -> 94.758854 | AI4: Date | AJ4: ECB Deposit Facility Rate (%) | AK4: German 10Y Bund Yield (%)
A5: 42644 | B5: 1.8 | C5: 0.73 | E5: 46029 | F5: 6392.93 | G5: 591.56 | I5: Date | J5: Euro/USD | P5: 42826 | Q5: 3441.88 | R5: 288.48 | S5: 1.1423 | T5: =Q5/$Q$2*100 -> 114.64373 | U5: =R5/$R$2*100 -> 103.2018 | V5: =S5/$S$2*100 -> 101.6462 | AI5: 42614 | AJ5: -0.4 | AK5: -0.084090909
A6: 42736 | B6: 1.7 | C6: 1.73 | E6: 46026 | F6: 6328.09 | G6: 570.12 | I6: 46029 | J6: 1.1609 | P6: 42917 | Q6: 3594.85 | R6: 304.08 | S6: 1.1812 | T6: =Q6/$Q$2*100 -> 119.73893 | U6: =R6/$R$2*100 -> 108.7826 | V6: =S6/$S$2*100 -> 105.10767 | AI6: 42644 | AJ6: -0.4 | AK6: 0.002
A7: 42826 | B7: 2.1 | C7: 1.53 | E7: 46054 | F7: 5569.73 | G7: 603.75 | I7: 46026 | J7: 1.1421 | P7: 43009 | Q7: 3503.96 | R7: 309.81 | S7: 1.1996 | T7: =Q7/$Q$2*100 -> 116.71152 | U7: =R7/$R$2*100 -> 110.83247 | V7: =S7/$S$2*100 -> 106.74497 | AI7: 42675 | AJ7: -0.4 | AK7: 0.18909091
A8: 42917 | B8: 2.8 | C8: 1.47 | E8: 45667 | F8: 5791.41 | G8: 440.17 | I8: 46023 | J8: 1.1552 | P8: 43101 | Q8: 3361.5 | R8: 308.83 | S8: 1.2321 | T8: =Q8/$Q$2*100 -> 111.9664 | U8: =R8/$R$2*100 -> 110.48188 | V8: =S8/$S$2*100 -> 109.63695 | AI8: 42705 | AJ8: -0.4 | AK8: 0.25190476
A9: 43009 | B9: 2.8 | C9: 1.4 | E9: 45664 | F9: 5529.96 | G9: 399.94 | I9: 45667 | J9: 1.1745 | P9: 43191 | Q9: 3395.6 | R9: 347.47 | S9: 1.1683 | T9: =Q9/$Q$2*100 -> 113.10222 | U9: =R9/$R$2*100 -> 124.30508 | V9: =S9/$S$2*100 -> 103.95978 | AI9: 42736 | AJ9: -0.4 | AK9: 0.25090909
A10: 43101 | B10: 2.5 | C10: 1.27 | E10: 45661 | F10: 5303.24 | G10: 389.92 | I10: 45664 | J10: 1.1733 | P10: 43282 | Q10: 3399.2 | R10: 364.97 | S10: 1.1608 | T10: =Q10/$Q$2*100 -> 113.22213 | U10: =R10/$R$2*100 -> 130.56559 | V10: =S10/$S$2*100 -> 103.2924 | AI10: 42767 | AJ10: -0.4 | AK10: 0.258
A11: 43191 | B11: 2.2 | C11: 1.73 | E11: 45689 | F11: 5248.39 | G11: 369.41 | I11: 45661 | J11: 1.1786 | P11: 43374 | Q11: 3001.42 | R11: 302.78 | S11: 1.1469 | T11: =Q11/$Q$2*100 -> 99.972687 | U11: =R11/$R$2*100 -> 108.31753 | V11: =S11/$S$2*100 -> 102.05553 | AI11: 42795 | AJ11: -0.4 | AK11: 0.34826087
A12: 43282 | B12: 1.7 | C12: 2.13 | E12: 45301 | F12: 4895.98 | G12: 339.28 | I12: 45658 | J12: 1.0817 | P12: 43466 | Q12: 3351.71 | R12: 339.1 | S12: 1.1217 | T12: =Q12/$Q$2*100 -> 111.64031 | U12: =R12/$R$2*100 -> 121.31077 | V12: =S12/$S$2*100 -> 99.813134 | AI12: 42826 | AJ12: -0.4 | AK12: 0.22555556
A13: 43374 | B13: 1.2 | C13: 1.9 | E13: 45298 | F13: 5000.45 | G13: 342.89 | I13: 45301 | J13: 1.0353 | P13: 43556 | Q13: 3473.69 | R13: 329.1 | S13: 1.1368 | T13: =Q13/$Q$2*100 -> 115.70327 | U13: =R13/$R$2*100 -> 117.73334 | V13: =S13/$S$2*100 -> 101.15679 | AI13: 42856 | AJ13: -0.4 | AK13: 0.33636364
A14: 43466 | B14: 1.2 | C14: 1.43 | E14: 45326 | F14: 4894.02 | G14: 355.25 | I14: 45298 | J14: 1.1134 | P14: 43647 | Q14: 3569.45 | R14: 324.06 | S14: 1.0898 | T14: =Q14/$Q$2*100 -> 118.89289 | U14: =R14/$R$2*100 -> 115.93031 | V14: =S14/$S$2*100 -> 96.974551 | AI14: 42887 | AJ14: -0.4 | AK14: 0.25047619
A15: 43556 | B15: 1.1 | C15: 1.4 | E15: 45323 | F15: 5083.42 | G15: 361.78 | I15: 45295 | J15: 1.0713 | P15: 43739 | Q15: 3745.15 | R15: 328.43 | S15: 1.121 | T15: =Q15/$Q$2*100 -> 124.74519 | U15: =R15/$R$2*100 -> 117.49365 | V15: =S15/$S$2*100 -> 99.750845 | AI15: 42917 | AJ15: -0.4 | AK15: 0.45571429
A16: 43647 | B16: 1.1 | C16: 0.93 | E16: 44967 | F16: 4521.44 | G16: 350.16 | I16: 45292 | J16: 1.0793 | P16: 43831 | Q16: 2786.9 | R16: 228.81 | S16: 1.1029 | T16: =Q16/$Q$2*100 -> 92.827356 | U16: =R16/$R$2*100 -> 81.855257 | V16: =S16/$S$2*100 -> 98.140238 | AI16: 42948 | AJ16: -0.4 | AK16: 0.34608696
A17: 43739 | B17: 1 | C17: 1 | E17: 44992 | F17: 4174.66 | G17: 356.52 | I17: 44967 | J17: 1.1036 | P17: 43922 | Q17: 3234.07 | R17: 225.69 | S17: 1.1231 | T17: =Q17/$Q$2*100 -> 107.7219 | U17: =R17/$R$2*100 -> 80.739098 | V17: =S17/$S$2*100 -> 99.937711 | AI17: 42979 | AJ17: -0.4 | AK17: 0.34714286
... A42: 46023 | B42: 0.8 | C42: 2.07 | E42: 42798 | F42: 3441.88 | G42: 288.48 | I42: 42801 | J42: 1.1812 | P42: 46204 | Q42: 6392.93 | R42: 591.56 | S42: 1.1609 | T42: =Q42/$Q$2*100 -> 212.93867 | U42: =R42/$R$2*100 -> 211.62666 | V42: =S42/$S$2*100 -> 103.3013 | AI42: 43739 | AJ42: -0.5 | AK42: -0.46954545
A43: 46113 | B43: 1 | C43: 3 | E43: 42767 | F43: 3500.93 | G43: 319.2 | I43: 42798 | J43: 1.1423 | AI43: 43770 | AJ43: -0.5 | AK43: -0.35238095
E44: 42439 | F44: 3290.52 | G44: 324.01 | I44: 42767 | J44: 1.0649 | AI44: 43800 | AJ44: -0.5 | AK44: -0.29944444
E45: 42376 | F45: 3002.24 | G45: 279.53 | I45: 42439 | J45: 1.0513 | AI45: 43831 | AJ45: -0.5 | AK45: -0.31363636
I46: 42376 | J46: 1.1238 | AI46: 43862 | AJ46: -0.5 | AK46: -0.466
AI47: 43891 | AJ47: -0.5 | AK47: -0.54136364
AI48: 43922 | AJ48: -0.5 | AK48: -0.4495
AI49: 43952 | AJ49: -0.5 | AK49: -0.5165
AI50: 43983 | AJ50: -0.5 | AK50: -0.43428571
AI51: 44013 | AJ51: -0.5 | AK51: -0.52304348
AI52: 44044 | AJ52: -0.5 | AK52: -0.52333333
AI53: 44075 | AJ53: -0.5 | AK53: -0.52409091
AI54: 44105 | AJ54: -0.5 | AK54: -0.60727273
AI55: 44136 | AJ55: -0.5 | AK55: -0.6147619
AI56: 44166 | AJ56: -0.5 | AK56: -0.6185
AI57: 44197 | AJ57: -0.5 | AK57: -0.5835
AI58: 44228 | AJ58: -0.5 | AK58: -0.4455
... AI122: 46174 | AJ122: 2.25 | AK122: 2.97

Sheet Japan
A1: Japan 10 yr GDP - LSEG 7/9 | K1: Japan Interest Rates | R1: Japan Equities — Nikkei 225 & TOPIX, LSEG 7/9 | Y1: USD/JPY — LSEG 7/9
K2: 10Y JGB Yield: LSEG 7/9 | Short-Term Rate: FRED IRSTCI01JPM156N
B3: JPGD1=ECI (ECONOMIC) | C3: JPCPO=ECI (ECONOMIC) | L3: aJPGBOND (ECONOMIC) | M3: IRSTCI01JPM156N | Q3: .N225E (TRDPRC_1) | R3: .TOPX (TRDPRC_1) | Z3: JPY= (BID)
A4: Date | B4: Japan Real GDP Growth, QoQ (%) | C4: Japan CPI Inflation, YoY (%) | K4: Date | L4: Japan 10-Year JGB Yield (%) | M4: Japan Short-Term Interest Rate (%) | P4: Date | Q4: Nikkei 225 (Close) | R4: TOPIX (Close) | U4: Date | V4: Nikkei 225 | W4: TOPIX | Y4: Date | Z4: USD/JPY (Close)
A5: 42552 | B5: 0.5 | C5: -0.4 | K5: 42522 | L5: -0.07 | M5: -0.055 | P5: 42522 | Q5: 16449.84 | R5: 1322.78 | U5: 42522 | V5: =Q5/$Q$5*100 -> 100 | W5: =R5/$R$5*100 -> 100 | Y5: 42522 | Z5: 101.33
A6: 42644 | B6: 0.2 | C6: 0.1 | K6: 42552 | L6: -0.08 | M6: -0.043 | P6: 42552 | Q6: 17425.02 | R6: 1393.02 | U6: 42552 | V6: =Q6/$Q$5*100 -> 105.9282 | W6: =R6/$R$5*100 -> 105.31003 | Y6: 42552 | Z6: 104.81
A7: 42736 | B7: 0.5 | C7: 0.4 | K7: 42583 | L7: -0.05 | M7: -0.043 | P7: 42583 | Q7: 18308.48 | R7: 1469.43 | U7: 42583 | V7: =Q7/$Q$5*100 -> 111.29883 | W7: =R7/$R$5*100 -> 111.0865 | Y7: 42583 | Z7: 114.44
A8: 42826 | B8: 1 | C8: 0.4 | K8: 42614 | L8: 0.02 | M8: -0.052 | P8: 42614 | Q8: 19114.37 | R8: 1518.61 | U8: 42614 | V8: =Q8/$Q$5*100 -> 116.19791 | W8: =R8/$R$5*100 -> 114.80443 | Y8: 42614 | Z8: 116.87
A9: 42917 | B9: 0.3 | C9: 0.4 | K9: 42644 | L9: 0.05 | M9: -0.037 | P9: 42644 | Q9: 19041.34 | R9: 1521.67 | U9: 42644 | V9: =Q9/$Q$5*100 -> 115.75395 | W9: =R9/$R$5*100 -> 115.03576 | Y9: 42644 | Z9: 112.78
A10: 43009 | B10: 0.1 | C10: 0.2 | K10: 42675 | L10: 0.09 | M10: -0.049 | P10: 42675 | Q10: 19118.99 | R10: 1535.32 | U10: 42675 | V10: =Q10/$Q$5*100 -> 116.22599 | W10: =R10/$R$5*100 -> 116.06768 | Y10: 42675 | Z10: 112.75
A11: 43101 | B11: -0.2 | C11: 1.4 | K11: 42705 | L11: 0.05 | M11: -0.044 | P11: 42705 | Q11: 18909.26 | R11: 1512.6 | U11: 42705 | V11: =Q11/$Q$5*100 -> 114.95103 | W11: =R11/$R$5*100 -> 114.35008 | Y11: 42705 | Z11: 111.38
A12: 43191 | B12: 0.5 | C12: 0.6 | K12: 42736 | L12: 0.07 | M12: -0.045 | P12: 42736 | Q12: 19196.74 | R12: 1531.8 | U12: 42736 | V12: =Q12/$Q$5*100 -> 116.69864 | W12: =R12/$R$5*100 -> 115.80157 | Y12: 42736 | Z12: 111.53
A13: 43282 | B13: -0.3 | C13: 0.9 | K13: 42767 | L13: 0.02 | M13: -0.038 | P13: 42767 | Q13: 19650.57 | R13: 1568.37 | U13: 42767 | V13: =Q13/$Q$5*100 -> 119.45751 | W13: =R13/$R$5*100 -> 118.5662 | Y13: 42767 | Z13: 110.75
A14: 43374 | B14: 0.3 | C14: 1.4 | K14: 42795 | L14: 0.04 | M14: -0.042 | P14: 42795 | Q14: 20033.43 | R14: 1611.9 | U14: 42795 | V14: =Q14/$Q$5*100 -> 121.78495 | W14: =R14/$R$5*100 -> 121.857 | Y14: 42795 | Z14: 112.35
A15: 43466 | B15: 0.5 | C15: 0.2 | K15: 42826 | L15: 0.08 | M15: -0.054 | P15: 42826 | Q15: 19925.18 | R15: 1618.61 | U15: 42826 | V15: =Q15/$Q$5*100 -> 121.12689 | W15: =R15/$R$5*100 -> 122.36426 | Y15: 42826 | Z15: 110.25
A16: 43556 | B16: 0.4 | C16: 0.9 | K16: 42856 | L16: 0.08 | M16: -0.053 | P16: 42856 | Q16: 19646.24 | R16: 1617.41 | U16: 42856 | V16: =Q16/$Q$5*100 -> 119.43119 | W16: =R16/$R$5*100 -> 122.27355 | Y16: 42856 | Z16: 109.96
... A44: 46113 | B44: 0.3 | C44: 1.4 | K44: 43709 | L44: -0.08 | M44: -0.059 | P44: 43709 | Q44: 23656.62 | R44: 1721.36 | U44: 43709 | V44: =Q44/$Q$5*100 -> 143.81064 | W44: =R44/$R$5*100 -> 130.13199 | Y44: 43709 | Z44: 108.61
K45: 43739 | L45: -0.02 | M45: -0.021 | P45: 43739 | Q45: 23205.18 | R45: 1684.44 | U45: 43739 | V45: =Q45/$Q$5*100 -> 141.0663 | W45: =R45/$R$5*100 -> 127.3409 | Y45: 43739 | Z45: 108.38
K46: 43770 | L46: -0.06 | M46: -0.043 | P46: 43770 | Q46: 21142.96 | R46: 1510.87 | U46: 43770 | V46: =Q46/$Q$5*100 -> 128.52988 | W46: =R46/$R$5*100 -> 114.2193 | Y46: 43770 | Z46: 108.07
K47: 43800 | L47: -0.15 | M47: -0.038 | P47: 43800 | Q47: 18917.01 | R47: 1403.04 | U47: 43800 | V47: =Q47/$Q$5*100 -> 114.99814 | W47: =R47/$R$5*100 -> 106.06752 | Y47: 43800 | Z47: 107.53
K48: 43831 | L48: 0.02 | M48: -0.032 | P48: 43831 | Q48: 20193.69 | R48: 1464.03 | U48: 43831 | V48: =Q48/$Q$5*100 -> 122.75919 | W48: =R48/$R$5*100 -> 110.67827 | Y48: 43831 | Z48: 107.17
K49: 43862 | L49: -0.04 | M49: -0.016 | P49: 43862 | Q49: 21877.89 | R49: 1563.67 | U49: 43862 | V49: =Q49/$Q$5*100 -> 132.99759 | W49: =R49/$R$5*100 -> 118.21089 | Y49: 43862 | Z49: 107.77
K50: 43891 | L50: 0.01 | M50: -0.047 | P50: 43891 | Q50: 22288.14 | R50: 1558.77 | U50: 43891 | V50: =Q50/$Q$5*100 -> 135.49153 | W50: =R50/$R$5*100 -> 117.84046 | Y50: 43891 | Z50: 107.92
K51: 43922 | L51: 0.03 | M51: -0.036 | P51: 43922 | Q51: 21710 | R51: 1496.06 | U51: 43922 | V51: =Q51/$Q$5*100 -> 131.97697 | W51: =R51/$R$5*100 -> 113.09968 | Y51: 43922 | Z51: 105.88
K52: 43952 | L52: 0.02 | M52: -0.047 | P52: 43952 | Q52: 23139.76 | R52: 1618.18 | U52: 43952 | V52: =Q52/$Q$5*100 -> 140.6686 | W52: =R52/$R$5*100 -> 122.33176 | Y52: 43952 | Z52: 105.89
K53: 43983 | L53: 0.05 | M53: -0.048 | P53: 43983 | Q53: 23185.12 | R53: 1625.49 | U53: 43983 | V53: =Q53/$Q$5*100 -> 140.94435 | W53: =R53/$R$5*100 -> 122.88438 | Y53: 43983 | Z53: 105.45
K54: 44013 | L54: 0.02 | M54: -0.028 | P54: 44013 | Q54: 22977.13 | R54: 1579.33 | U54: 44013 | V54: =Q54/$Q$5*100 -> 139.67996 | W54: =R54/$R$5*100 -> 119.39476 | Y54: 44013 | Z54: 104.64
K55: 44044 | L55: 0.04 | M55: -0.035 | P55: 44044 | Q55: 26433.62 | R55: 1754.92 | U55: 44044 | V55: =Q55/$Q$5*100 -> 160.69226 | W55: =R55/$R$5*100 -> 132.66908 | Y55: 44044 | Z55: 104.27
K56: 44075 | L56: 0.03 | M56: -0.054 | P56: 44075 | Q56: 27444.17 | R56: 1804.68 | U56: 44075 | V56: =Q56/$Q$5*100 -> 166.83548 | W56: =R56/$R$5*100 -> 136.43085 | Y56: 44075 | Z56: 103.24
... K125: 46174 | L125: 2.94 | M125: 0.841 | P125: 46174 | Q125: 65020.94 | R125: 4118.11 | U125: 46174 | V125: =Q125/$Q$5*100 -> 395.26792 | W125: =R125/$R$5*100 -> 311.32237 | Y125: 46174 | Z125: 156.14

Sheet RF
A1: RF
A2: Daily 10y bond yields | D2: Each daily rate is expressed per year.
A4: Date | B4: % Rf year | C4: % Rf av year | D4: Rf (decimal) | F4: %Rf daily | G4: Rf daily (decimal)
A5: observation_date | B5: DGS10 | C5: =AVERAGEIFS(B6:B1310,A6:A1310,">="&Portfolio!BV12,A6:A1310,"<="&Portfolio!BV31) -> 3.777789 | D5: =C5/100 -> 0.03777789 | F5: =C5/252 -> 0.014991226 | G5: =F5/100 -> 0.00014991226
A6: 44461 | B6: 1.32
A7: 44462 | B7: 1.41
A8: 44463 | B8: 1.47
A9: 44466 | B9: 1.48
A10: 44467 | B10: 1.54
A11: 44468 | B11: 1.55
A12: 44469 | B12: 1.52
A13: 44470 | B13: 1.48
A14: 44473 | B14: 1.49
A15: 44474 | B15: 1.54
A16: 44475 | B16: 1.53
A17: 44476 | B17: 1.58
A18: 44477 | B18: 1.61
A19: 44480
A20: 44481 | B20: 1.59
A21: 44482 | B21: 1.56
A22: 44483 | B22: 1.52
A23: 44484 | B23: 1.59
A24: 44487 | B24: 1.59
A25: 44488 | B25: 1.65
A26: 44489 | B26: 1.65
A27: 44490 | B27: 1.68
A28: 44491 | B28: 1.66
A29: 44494 | B29: 1.64
A30: 44495 | B30: 1.63
A31: 44496 | B31: 1.54
... A41: 44510 | B41: 1.56
A42: 44511
A43: 44512 | B43: 1.58
A44: 44515 | B44: 1.63
A45: 44516 | B45: 1.63
A46: 44517 | B46: 1.6
A47: 44518 | B47: 1.59
A48: 44519 | B48: 1.54
A49: 44522 | B49: 1.63
A50: 44523 | B50: 1.67
A51: 44524 | B51: 1.64
A52: 44525
A53: 44526 | B53: 1.48
A54: 44529 | B54: 1.52
A55: 44530 | B55: 1.43
A56: 44531 | B56: 1.43
A57: 44532 | B57: 1.44
A58: 44533 | B58: 1.35
A59: 44536 | B59: 1.43
A60: 44537 | B60: 1.48
A61: 44538 | B61: 1.52
A62: 44539 | B62: 1.49
A63: 44540 | B63: 1.48
A64: 44543 | B64: 1.42
... A72: 44553 | B72: 1.5
A73: 44554
A74: 44557 | B74: 1.48
A75: 44558 | B75: 1.49
A76: 44559 | B76: 1.55
A77: 44560 | B77: 1.52
A78: 44561 | B78: 1.52
A79: 44564 | B79: 1.63
A80: 44565 | B80: 1.66
A81: 44566 | B81: 1.71
A82: 44567 | B82: 1.73
A83: 44568 | B83: 1.76
A84: 44571 | B84: 1.78
A85: 44572 | B85: 1.75
... A88: 44575 | B88: 1.78
A89: 44578
A90: 44579 | B90: 1.87
A91: 44580 | B91: 1.83
A92: 44581 | B92: 1.83
A93: 44582 | B93: 1.75
A94: 44585 | B94: 1.75
A95: 44586 | B95: 1.78
A96: 44587 | B96: 1.85
A97: 44588 | B97: 1.81
A98: 44589 | B98: 1.78
A99: 44592 | B99: 1.79
A100: 44593 | B100: 1.81
A101: 44594 | B101: 1.78
... A113: 44610 | B113: 1.92
A114: 44613
A115: 44614 | B115: 1.94
A116: 44615 | B116: 1.99
A117: 44616 | B117: 1.96
A118: 44617 | B118: 1.97
A119: 44620 | B119: 1.83
A120: 44621 | B120: 1.72
A121: 44622 | B121: 1.86
A122: 44623 | B122: 1.86
A123: 44624 | B123: 1.74
A124: 44627 | B124: 1.78
A125: 44628 | B125: 1.86
A126: 44629 | B126: 1.94
... A152: 44665 | B152: 2.83
A153: 44666
A154: 44669 | B154: 2.85
A155: 44670 | B155: 2.93
...

Sheet Portfolio
B10: 60/40 | BV10: Quarterly Backtest (portfolio value, quarter to quarter)
B11: Ric | C11: Name | D11: Region | E11: Asset Class | F11: Type | G11: MER | H11: Return | I11: Return - MER | J11: Risk | K11: Drawdown | L11: Weight | M11: Total Risk | N11: Total Drawdown | O11: Total Return | BV11: Date | BW11: Aggressive | BX11: Strategic Backtest | BY11: Defensive | CA11: Column1 | CB11: 80/20 Tactical - Aggressive | CC11: 70/30 Strategic Backtest | CD11: 60/40 Tactical - Defensive
B12: BILL.AX | C12: iShares Core Cash ETF | D12: Australia | E12: Cash | F12: Defensive | G12: 0.0007 | H12: =T15 -> 0.00086268851 | I12: =H12-G12 -> 0.00016268851 | J12: =T16 -> 0.0014583498 | K12: =T18 -> -0.0015873016 | L12: 0.2 | M12: =J12*L12 -> 0.00029166995 | N12: =K12*L12 -> -0.00031746032 | O12: =I12*L12 -> 3.2537702e-05 | BV12: 44469 | CA12: Quarterly Mean | CB12: =AVERAGE(BW13:BW31) -> 0.022554304 | CC12: =AVERAGE(BX13:BX31) -> 0.02473175 | CD12: =AVERAGE(BY13:BY31) -> 0.024587001
B13: SPY.AX | C13: SPDR S&P 500 ETF Trust | D13: United States | E13: Equities | F13: Growth | G13: 0.0009 | H13: =X15 -> 0.12566444 | I13: =H13-G13 -> 0.12476444 | J13: =X16 -> 0.13229761 | K13: =X18 -> -0.16545205 | L13: 0.29 | M13: =J13*L13 -> 0.038366307 | N13: =K13*L13 -> -0.047981095 | O13: =I13*L13 -> 0.036181687 | R13: Monthly Mean | T13: =AVERAGE(S22:S83) -> 7.1890709e-05 | V13: Monthly Mean | X13: =AVERAGE(W22:W83) -> 0.010472037 | Z13: Monthly Mean | AB13: =AVERAGE(AA22:AA83) -> 0.0050774589 | AD13: Monthly Mean | AF13: =AVERAGE(AE22:AE83) -> 0.012974092 | AH13: Monthly Mean | AJ13: =AVERAGE(AI22:AI83) -> 0.015784585 | AL13: Monthly Mean | AN13: =AVERAGE(AM22:AM83) -> -0.0026154095 | AP13: Monthly Mean | AR13: =AVERAGE(AQ22:AQ83) -> 0.0038955483 | AT13: Monthly Mean | AV13: =AVERAGE(AU22:AU83) -> 4.9067197e-05 | AX13: Monthly Mean | AZ13: =AVERAGE(AY22:AY83) -> 0.0097028547 | BB13: Monthly Mean | BD13: =AVERAGE(BC22:BC83) -> 0.0033162475 | BF13: Monthly Mean | BH13: =AVERAGE(BG22:BG83) -> -0.00074885233 | BJ13: Monthly Mean | BL13: =AVERAGE(BK22:BK83) -> 0.0076708652 | BN13: Monthly Mean | BP13: =AVERAGE(BO22:BO83) -> 0.0076892299 | BR13: Monthly Mean | BT13: =AVERAGE(BS22:BS83) -> 0.0070080238 | BV13: 44561 | BW13: =BR27/BR24-1 -> 0.043367021 | BX13: =BN27/BN24-1 -> 0.042835458 | BY13: =BJ27/BJ24-1 -> 0.043336672 | CA13: Quarterly Std. Dev. | CB13: =STDEV(BW13:BW31) -> 0.050141395 | CC13: =STDEV(BX13:BX31) -> 0.050665528 | CD13: =STDEV(BY13:BY31) -> 0.042558185
B14: ESGI.AX | C14: VanEck MSCI International Sustainable Equity ETF | D14: Global | E14: Equities | F14: Growth | G14: 0.0055 | H14: =AB15 -> 0.060929507 | I14: =H14-G14 -> 0.055429507 | J14: =AB16 -> 0.12936696 | K14: =AB18 -> -0.20283323 | L14: 0.1544 | M14: =J14*L14 -> 0.019974259 | N14: =K14*L14 -> -0.03131745 | O14: =I14*L14 -> 0.0085583159 | R14: Monthly Std. Dev. | T14: =STDEV(S22:S83) -> 0.00042098931 | V14: Monthly Std. Dev. | X14: =STDEV(W22:W83) -> 0.03819103 | Z14: Monthly Std. Dev. | AB14: =STDEV(AA22:AA83) -> 0.037345025 | AD14: Monthly Std. Dev. | AF14: =STDEV(AE22:AE83) -> 0.049400651 | AH14: Monthly Std. Dev. | AJ14: =STDEV(AI22:AI83) -> 0.045561653 | AL14: Monthly Std. Dev. | AN14: =STDEV(AM22:AM83) -> 0.014913014 | AP14: Monthly Std. Dev. | AR14: =STDEV(AQ22:AQ83) -> 0.029509921 | AT14: Monthly Std. Dev. | AV14: =STDEV(AU22:AU83) -> 0.00031043957 | AX14: Monthly Std. Dev. | AZ14: =STDEV(AY22:AY83) -> 0.038613274 | BB14: Monthly Std. Dev. | BD14: =STDEV(BC22:BC83) -> 0.039333116 | BF14: Monthly Std. Dev. | BH14: =STDEV(BG22:BG83) -> 0.012067518 | BJ14: Monthly Std. Dev. | BL14: =STDEV(BK22:BK83) -> 0.02028696 | BN14: Monthly Std. Dev. | BP14: =STDEV(BO22:BO83) -> 0.023391403 | BR14: Monthly Std. Dev. | BT14: =STDEV(BS22:BS83) -> 0.024952481 | BV14: 44651 | BW14: =BR30/BR27-1 -> -0.039704137 | BX14: =BN30/BN27-1 -> -0.045421409 | BY14: =BJ30/BJ27-1 -> -0.037804718 | CA14: Mean Return (Annualised) | CB14: =CB12*4 -> 0.090217217 | CC14: =CC12*4 -> 0.098927002 | CD14: =CD12*4 -> 0.098348004
B15: HJPN.AX | C15: BetaShares Japan ETF (Currency Hedged) | D15: Japan | E15: Equities | F15: Growth | G15: 0.0056 | H15: =AF15 -> 0.1556891 | I15: =H15-G15 -> 0.1500891 | J15: =AF16 -> 0.17112888 | K15: =AF18 -> -0.21497585 | L15: 0.1 | M15: =J15*L15 -> 0.017112888 | N15: =K15*L15 -> -0.021497585 | O15: =I15*L15 -> 0.01500891 | R15: Mean Return (Annualised) | T15: =T13*12 -> 0.00086268851 | V15: Mean Return (Annualised) | X15: =X13*12 -> 0.12566444 | Z15: Mean Return (Annualised) | AB15: =AB13*12 -> 0.060929507 | AD15: Mean Return (Annualised) | AF15: =AF13*12 -> 0.1556891 | AH15: Mean Return (Annualised) | AJ15: =AJ13*12 -> 0.18941503 | AL15: Mean Return (Annualised) | AN15: =AN13*12 -> -0.031384914 | AP15: Mean Return (Annualised) | AR15: =AR13*12 -> 0.04674658 | AT15: Mean Return (Annualised) | AV15: =AV13*12 -> 0.00058880637 | AX15: Mean Return (Annualised) | AZ15: =AZ13*12 -> 0.11643426 | BB15: Mean Return (Annualised) | BD15: =BD13*12 -> 0.03979497 | BF15: Mean Return (Annualised) | BH15: =BH13*12 -> -0.0089862279 | BJ15: Mean Return (Annualised) | BL15: =BL13*12 -> 0.092050383 | BN15: Mean Return (Annualised) | BP15: =BP13*12 -> 0.092270759 | BR15: Mean Return (Annualised) | BT15: =BT13*12 -> 0.084096285 | BV15: 44742 | BW15: =BR33/BR30-1 -> -0.072070418 | BX15: =BN33/BN30-1 -> -0.057959021 | BY15: =BJ33/BJ30-1 -> -0.050118329 | CA15: Std. Dev. (Annualised) | CB15: =CB13*SQRT(4) -> 0.10028279 | CC15: =CC13*SQRT(4) -> 0.10133106 | CD15: =CD13*SQRT(4) -> 0.085116371
B16: GOLD.AX | C16: Global X Physical Gold | D16: Global | E16: Alternatives (Gold) | F16: Defensive | G16: 0.004 | H16: =AJ15 -> 0.18941503 | I16: =H16-G16 -> 0.18541503 | J16: =AJ16 -> 0.1578302 | K16: =AJ18 -> -0.22099853 | L16: 0.15 | M16: =J16*L16 -> 0.023674529 | N16: =K16*L16 -> -0.03314978 | O16: =I16*L16 -> 0.027812254 | R16: Std. Dev. (Annualised) | T16: =T14*SQRT(12) -> 0.0014583498 | V16: Std. Dev. (Annualised) | X16: =X14*SQRT(12) -> 0.13229761 | Z16: Std. Dev. (Annualised) | AB16: =AB14*SQRT(12) -> 0.12936696 | AD16: Std. Dev. (Annualised) | AF16: =AF14*SQRT(12) -> 0.17112888 | AH16: Std. Dev. (Annualised) | AJ16: =AJ14*SQRT(12) -> 0.1578302 | AL16: Std. Dev. (Annualised) | AN16: =AN14*SQRT(12) -> 0.051660197 | AP16: Std. Dev. (Annualised) | AR16: =AR14*SQRT(12) -> 0.10222536 | AT16: Std. Dev. (Annualised) | AV16: =AV14*SQRT(12) -> 0.0010753942 | AX16: Std. Dev. (Annualised) | AZ16: =AZ14*SQRT(12) -> 0.1337603 | BB16: Std. Dev. (Annualised) | BD16: =BD14*SQRT(12) -> 0.13625391 | BF16: Std. Dev. (Annualised) | BH16: =BH14*SQRT(12) -> 0.04180311 | BJ16: Std. Dev. (Annualised) | BL16: =BL14*SQRT(12) -> 0.070276091 | BN16: Std. Dev. (Annualised) | BP16: =BP14*SQRT(12) -> 0.081030196 | BR16: Std. Dev. (Annualised) | BT16: =BT14*SQRT(12) -> 0.08643793 | BV16: 44834 | BW16: =BR36/BR33-1 -> -0.021612661 | BX16: =BN36/BN33-1 -> -0.02394128 | BY16: =BJ36/BJ33-1 -> -0.018492085 | CA16: Sharpe Ratio | CB16: =(CB14-RF!$D$5)/CB15 -> 0.52291451 | CC16: =(CC14-RF!$D$5)/CC15 -> 0.60345875 | CD16: =(CD14-RF!$D$5)/CD15 -> 0.71161532
B17: VEFI.AX | C17: Vanguard Ethically Conscious Global Aggregate Bond Idx Hedged ETF | D17: Global | E17: Bonds | F17: Defensive | G17: 0.0026 | H17: =AN15 -> -0.031384914 | I17: =H17-G17 -> -0.033984914 | J17: =AN16 -> 0.051660197 | K17: =AN18 -> -0.19258517 | L17: 0.04 | M17: =J17*L17 -> 0.0020664079 | N17: =K17*L17 -> -0.0077034068 | O17: =I17*L17 -> -0.0013593966 | R17: Return-to-Variability Ratio | T17: =T15/T16 -> 0.59155117 | V17: Return-to-Variability Ratio | X17: =X15/X16 -> 0.94986174 | Z17: Return-to-Variability Ratio | AB17: =AB15/AB16 -> 0.47098197 | AD17: Return-to-Variability Ratio | AF17: =AF15/AF16 -> 0.90977691 | AH17: Return-to-Variability Ratio | AJ17: =AJ15/AJ16 -> 1.2001191 | AL17: Return-to-Variability Ratio | AN17: =AN15/AN16 -> -0.60752603 | AP17: Return-to-Variability Ratio | AR17: =AR15/AR16 -> 0.45728944 | AT17: Return-to-Variability Ratio | AV17: =AV15/AV16 -> 0.54752608 | AX17: Return-to-Variability Ratio | AZ17: =AZ15/AZ16 -> 0.87046944 | BB17: Return-to-Variability Ratio | BD17: =BD15/BD16 -> 0.29206479 | BF17: Return-to-Variability Ratio | BH17: =BH15/BH16 -> -0.21496553 | BJ17: Return-to-Variability Ratio | BL17: =BL15/BL16 -> 1.3098393 | BN17: Return-to-Variability Ratio | BP17: =BP15/BP16 -> 1.1387207 | BR17: Return-to-Variability Ratio | BT17: =BT15/BT16 -> 0.97290953 | BV17: 44925 | BW17: =BR39/BR36-1 -> 0.031804356 | BX17: =BN39/BN36-1 -> 0.038013866 | BY17: =BJ39/BJ36-1 -> 0.035109544 | CA17: Max Drawdown | CB17: =BT18 -> -0.12817182 | CC17: =BP18 -> -0.1222771 | CD17: =BL18 -> -0.10292958
B18: VBLD.AX | C18: Vanguard Global Infrastructure Index ETF | D18: Global | E18: Infrastructure | F18: Growth | G18: 0.0047 | H18: =AR15 -> 0.04674658 | I18: =H18-G18 -> 0.04204658 | J18: =AR16 -> 0.10222536 | K18: =AR18 -> -0.11622276 | L18: 0.0456 | M18: =J18*L18 -> 0.0046614766 | N18: =K18*L18 -> -0.0052997579 | O18: =I18*L18 -> 0.001917324 | R18: Max Drawdown | T18: =MIN(T22:T83) -> -0.0015873016 | V18: Max Drawdown | X18: =MIN(X22:X83) -> -0.16545205 | Z18: Max Drawdown | AB18: =MIN(AB22:AB83) -> -0.20283323 | AD18: Max Drawdown | AF18: =MIN(AF22:AF83) -> -0.21497585 | AH18: Max Drawdown | AJ18: =MIN(AJ22:AJ83) -> -0.22099853 | AL18: Max Drawdown | AN18: =MIN(AN22:AN83) -> -0.19258517 | AP18: Max Drawdown | AR18: =MIN(AR22:AR83) -> -0.11622276 | AT18: Max Drawdown | AV18: =MIN(AV22:AV83) -> -0.0013919268 | AX18: Max Drawdown | AZ18: =MIN(AZ22:AZ83) -> -0.18097976 | BB18: Max Drawdown | BD18: =MIN(BD22:BD83) -> -0.17873303 | BF18: Max Drawdown | BH18: =MIN(BH22:BH83) -> -0.11666045 | BJ18: Max Drawdown | BL18: =MIN(BL22:BL83) -> -0.10292958 | BN18: Max Drawdown | BP18: =MIN(BP22:BP83) -> -0.1222771 | BR18: Max Drawdown | BT18: =MIN(BT22:BT83) -> -0.12817182 | BV18: 45016 | BW18: =BR42/BR39-1 -> 0.047418801 | BX18: =BN42/BN39-1 -> 0.056052662 | BY18: =BJ42/BJ39-1 -> 0.053188093
B19: AAA.AX | C19: BetaShares Australian High Interest Cash ETF | D19: Australia | E19: Cash | F19: Defensive | G19: 0.0018 | H19: =AV15 -> 0.00058880637 | I19: =H19-G19 -> -0.0012111936 | J19: =AV16 -> 0.0010753942 | K19: =AV18 -> -0.0013919268 | L19: 0.01 | M19: =J19*L19 -> 1.0753942e-05 | N19: =K19*L19 -> -1.3919268e-05 | O19: =I19*L19 -> -1.2111936e-05 | BV19: 45107 | BW19: =BR45/BR42-1 -> 0.062920718 | BX19: =BN45/BN42-1 -> 0.06037837 | BY19: =BJ45/BJ42-1 -> 0.04640702
B20: VTS.AX | C20: Vanguard US Total Market Shares Index ETF | D20: United States | E20: Equities | F20: Growth | G20: 0.0003 | H20: =AZ15 -> 0.11643426 | I20: =H20-G20 -> 0.11613426 | J20: =AZ16 -> 0.1337603 | K20: =AZ18 -> -0.18097976 | L20: 0.01 | M20: =J20*L20 -> 0.001337603 | N20: =K20*L20 -> -0.0018097976 | O20: =I20*L20 -> 0.0011613426 | R20: iShares Core Cash ETF | V20: SPDR S&P 500 ETF Trust | Z20: VanEck MSCI International Sustainable Equity ETF | AD20: BetaShares Japan ETF (Currency Hedged) | AH20: Global X Physical Gold | AL20: Vanguard Ethically Conscious Global Aggregate Bond Idx Hedged ETF | AP20: Vanguard Global Infrastructure Index ETF | AT20: BetaShares Australian High Interest Cash ETF | AX20: Vanguard US Total Market Shares Index ETF | BB20: Vanguard Ethically Conscious Australian Shares ETF | BF20: Vanguard Australia Corporate Fixed Interest Index ETF | BJ20: Portfolio (60/40) | BN20: Portfolio (70/30) | BR20: Portfolio (80/20) | BV20: 45198 | BW20: =BR48/BR45-1 -> -0.018073652 | BX20: =BN48/BN45-1 -> -0.012251045 | BY20: =BJ48/BJ45-1 -> -0.010509204
L21: =SUM(L12:L20) -> 1 | M21: =SUM(M12:M20) -> 0.10749589 | N21: =SUM(N12:N20) -> -0.14909025 | O21: =SUM(O12:O20) -> 0.089300863 | Q21: Date | R21: BILL.AX | S21: Return (%) | T21: Drawdown | V21: SPY.AX | W21: Return (%) | X21: Drawdown | Z21: ESGI.AX | AA21: Return (%) | AB21: Drawdown | AD21: HJPN.AX | AE21: Return (%) | AF21: Drawdown | AH21: GOLD.AX | AI21: Return (%) | AJ21: Drawdown | AL21: VEFI.AX | AM21: Return (%) | AN21: Drawdown | AP21: VBLD.AX | AQ21: Return (%) | AR21: Drawdown | AT21: AAA.AX | AU21: Return (%) | AV21: Drawdown | AX21: VTS.AX | AY21: Return (%) | AZ21: Drawdown | BB21: VETH.AX | BC21: Return (%) | BD21: Drawdown | BF21: VACF.AX | BG21: Return (%) | BH21: Drawdown | BJ21: Value (100) | BK21: Return (%) | BL21: Drawdown | BN21: Value (100) | BO21: Return (%) | BP21: Drawdown | BR21: Value (100) | BS21: Return (%) | BT21: Drawdown | BV21: 45289 | BW21: =BR51/BR48-1 -> 0.044747265 | BX21: =BN51/BN48-1 -> 0.042906247 | BY21: =BJ51/BJ48-1 -> 0.04297003
L22: Actual portfolio | M22: =BL16 -> 0.070276091 | N22: =BL18 -> -0.10292958 | O22: =BL15-SUMPRODUCT(G12:G20,L12:L20) -> 0.089300863 | Q22: 44407 | R22: 100.24 | T22: =IF(ISNUMBER(R22),R22/MAX(R22:R$22)-1,"") -> 0 | V22: 592.2 | X22: =IF(ISNUMBER(V22),V22/MAX(V22:V$22)-1,"") -> 0 | Z22: 29.1 | AB22: =IF(ISNUMBER(Z22),Z22/MAX(Z22:Z$22)-1,"") -> 0 | AD22: 15.26 | AF22: =IF(ISNUMBER(AD22),AD22/MAX(AD22:AD$22)-1,"") -> 0 | AH22: 23.099 | AJ22: =IF(ISNUMBER(AH22),AH22/MAX(AH22:AH$22)-1,"") -> 0 | AL22: 49.89 | AN22: =IF(ISNUMBER(AL22),AL22/MAX(AL22:AL$22)-1,"") -> 0 | AP22: 59.51 | AR22: =IF(ISNUMBER(AP22),AP22/MAX(AP22:AP$22)-1,"") -> 0 | AT22: 50.09 | AV22: =IF(ISNUMBER(AT22),AT22/MAX(AT22:AT$22)-1,"") -> 0 | AX22: 306.53 | AZ22: =IF(ISNUMBER(AX22),AX22/MAX(AX22:AX$22)-1,"") -> 0 | BB22: 59.36 | BD22: =IF(ISNUMBER(BB22),BB22/MAX(BB22:BB$22)-1,"") -> 0 | BF22: 53.64 | BH22: =IF(ISNUMBER(BF22),BF22/MAX(BF22:BF$22)-1,"") -> 0 | BJ22: 100 | BL22: =IF(ISNUMBER(BJ22),BJ22/MAX(BJ$22:BJ22)-1,"") -> 0 | BN22: 100 | BP22: =IF(ISNUMBER(BN22),BN22/MAX(BN$22:BN22)-1,"") -> 0 | BR22: 100 | BT22: =IF(ISNUMBER(BR22),BR22/MAX(BR$22:BR22)-1,"") -> 0 | BV22: 45379 | BW22: =BR54/BR51-1 -> 0.11277849 | BX22: =BN54/BN51-1 -> 0.11935626 | BY22: =BJ54/BJ51-1 -> 0.1062284
Q23: 44439 | R23: 100.26 | S23: =IF(AND(ISNUMBER(R22),ISNUMBER(R23)),R23/R22-1,"") -> 0.00019952115 | T23: =IF(ISNUMBER(R23),R23/MAX(R$22:R23)-1,"") -> 0 | V23: 618.81 | W23: =IF(AND(ISNUMBER(V22),ISNUMBER(V23)),V23/V22-1,"") -> 0.044934144 | X23: =IF(ISNUMBER(V23),V23/MAX(V$22:V23)-1,"") -> 0 | Z23: 30.18 | AA23: =IF(AND(ISNUMBER(Z22),ISNUMBER(Z23)),Z23/Z22-1,"") -> 0.037113402 | AB23: =IF(ISNUMBER(Z23),Z23/MAX(Z$22:Z23)-1,"") -> 0 | AD23: 15.64 | AE23: =IF(AND(ISNUMBER(AD22),ISNUMBER(AD23)),AD23/AD22-1,"") -> 0.024901704 | AF23: =IF(ISNUMBER(AD23),AD23/MAX(AD$22:AD23)-1,"") -> 0 | AH23: 23.123 | AI23: =IF(AND(ISNUMBER(AH22),ISNUMBER(AH23)),AH23/AH22-1,"") -> 0.001039006 | AJ23: =IF(ISNUMBER(AH23),AH23/MAX(AH$22:AH23)-1,"") -> 0 | AL23: 49.9 | AM23: =IF(AND(ISNUMBER(AL22),ISNUMBER(AL23)),AL23/AL22-1,"") -> 0.00020044097 | AN23: =IF(ISNUMBER(AL23),AL23/MAX(AL$22:AL23)-1,"") -> 0 | AP23: 61.15 | AQ23: =IF(AND(ISNUMBER(AP22),ISNUMBER(AP23)),AP23/AP22-1,"") -> 0.027558394 | AR23: =IF(ISNUMBER(AP23),AP23/MAX(AP$22:AP23)-1,"") -> 0 | AT23: 50.08 | AU23: =IF(AND(ISNUMBER(AT22),ISNUMBER(AT23)),AT23/AT22-1,"") -> -0.00019964065 | AV23: =IF(ISNUMBER(AT23),AT23/MAX(AT$22:AT23)-1,"") -> -0.00019964065 | AX23: 319.51 | AY23: =IF(AND(ISNUMBER(AX22),ISNUMBER(AX23)),AX23/AX22-1,"") -> 0.042344958 | AZ23: =IF(ISNUMBER(AX23),AX23/MAX(AX$22:AX23)-1,"") -> 0 | BB23: 61.88 | BC23: =IF(AND(ISNUMBER(BB22),ISNUMBER(BB23)),BB23/BB22-1,"") -> 0.04245283 | BD23: =IF(ISNUMBER(BB23),BB23/MAX(BB$22:BB23)-1,"") -> 0 | BF23: 53.66 | BG23: =IF(AND(ISNUMBER(BF22),ISNUMBER(BF23)),BF23/BF22-1,"") -> 0.00037285608 | BH23: =IF(ISNUMBER(BF23),BF23/MAX(BF$22:BF23)-1,"") -> 0 | BJ23: =BJ22*(1+BK23) -> 102.31333 | BK23: =$L$12*S23+$L$13*W23+$L$14*AA23+$L$15*AE23+$L$16*AI23+$L$17*AM23+$L$18*AQ23+$L$19*AU23+$L$20*AY23 -> 0.02313327 | BL23: =IF(ISNUMBER(BJ23),BJ23/MAX(BJ$22:BJ23)-1,"") -> 0 | BN23: =BN22*(1+BO23) -> 102.61296 | BO23: =$L$35*W23+$L$36*S23+$L$37*AA23+$L$38*AE23+$L$39*AQ23+$L$40*AY23+$L$41*BC23+$L$42*BG23+$L$43*AI23 -> 0.026129577 | BP23: =IF(ISNUMBER(BN23),BN23/MAX(BN$22:BN23)-1,"") -> 0 | BR23: =BR22*(1+BS23) -> 102.92785 | BS23: =$L$58*W23+$L$59*AE23+$L$60*S23+$L$61*AQ23+$L$62*BC23+$L$63*AA23+$L$64*BG23+$L$65*AY23+$L$66*AI23 -> 0.029278477 | BT23: =IF(ISNUMBER(BR23),BR23/MAX(BR$22:BR23)-1,"") -> 0 | BV23: 45471 | BW23: =BR57/BR54-1 -> 0.010193016 | BX23: =BN57/BN54-1 -> 0.018704859 | BY23: =BJ57/BJ54-1 -> 0.019965397
E24: United States | F24: =SUMIF($D$12:$D$20, E24, $L$12:$L$20) -> 0.3 | H24: Growth | I24: =SUMIF($F$12:$F$20, H24, $L$12:$L$20) -> 0.6 | Q24: 44469 | R24: 100.24 | S24: =IF(AND(ISNUMBER(R23),ISNUMBER(R24)),R24/R23-1,"") -> -0.00019948135 | T24: =IF(ISNUMBER(R24),R24/MAX(R$22:R24)-1,"") -> -0.00019948135 | V24: 606.91 | W24: =IF(AND(ISNUMBER(V23),ISNUMBER(V24)),V24/V23-1,"") -> -0.019230458 | X24: =IF(ISNUMBER(V24),V24/MAX(V$22:V24)-1,"") -> -0.019230458 | Z24: 29.65 | AA24: =IF(AND(ISNUMBER(Z23),ISNUMBER(Z24)),Z24/Z23-1,"") -> -0.017561299 | AB24: =IF(ISNUMBER(Z24),Z24/MAX(Z$22:Z24)-1,"") -> -0.017561299 | AD24: 16.2 | AE24: =IF(AND(ISNUMBER(AD23),ISNUMBER(AD24)),AD24/AD23-1,"") -> 0.035805627 | AF24: =IF(ISNUMBER(AD24),AD24/MAX(AD$22:AD24)-1,"") -> 0 | AH24: 22.394 | AI24: =IF(AND(ISNUMBER(AH23),ISNUMBER(AH24)),AH24/AH23-1,"") -> -0.031527051 | AJ24: =IF(ISNUMBER(AH24),AH24/MAX(AH$22:AH24)-1,"") -> -0.031527051 | AL24: 49.28 | AM24: =IF(AND(ISNUMBER(AL23),ISNUMBER(AL24)),AL24/AL23-1,"") -> -0.01242485 | AN24: =IF(ISNUMBER(AL24),AL24/MAX(AL$22:AL24)-1,"") -> -0.01242485 | AP24: 59.74 | AQ24: =IF(AND(ISNUMBER(AP23),ISNUMBER(AP24)),AP24/AP23-1,"") -> -0.023058054 | AR24: =IF(ISNUMBER(AP24),AP24/MAX(AP$22:AP24)-1,"") -> -0.023058054 | AT24: 50.08 | AU24: =IF(AND(ISNUMBER(AT23),ISNUMBER(AT24)),AT24/AT23-1,"") -> 0 | AV24: =IF(ISNUMBER(AT24),AT24/MAX(AT$22:AT24)-1,"") -> -0.00019964065 | AX24: 313.46 | AY24: =IF(AND(ISNUMBER(AX23),ISNUMBER(AX24)),AX24/AX23-1,"") -> -0.018935245 | AZ24: =IF(ISNUMBER(AX24),AX24/MAX(AX$22:AX24)-1,"") -> -0.018935245 | BB24: 60.39 | BC24: =IF(AND(ISNUMBER(BB23),ISNUMBER(BB24)),BB24/BB23-1,"") -> -0.024078862 | BD24: =IF(ISNUMBER(BB24),BB24/MAX(BB$22:BB24)-1,"") -> -0.024078862 | BF24: 53.15 | BG24: =IF(AND(ISNUMBER(BF23),ISNUMBER(BF24)),BF24/BF23-1,"") -> -0.0095042862 | BH24: =IF(ISNUMBER(BF24),BF24/MAX(BF$22:BF24)-1,"") -> -0.0095042862 | BJ24: =BJ23*(1+BK24) -> 101.16594 | BK24: =$L$12*S24+$L$13*W24+$L$14*AA24+$L$15*AE24+$L$16*AI24+$L$17*AM24+$L$18*AQ24+$L$19*AU24+$L$20*AY24 -> -0.011214482 | BL24: =IF(ISNUMBER(BJ24),BJ24/MAX(BJ$22:BJ24)-1,"") -> -0.011214482 | BN24: =BN23*(1+BO24) -> 101.91139 | BO24: =$L$35*W24+$L$36*S24+$L$37*AA24+$L$38*AE24+$L$39*AQ24+$L$40*AY24+$L$41*BC24+$L$42*BG24+$L$43*AI24 -> -0.0068370723 | BP24: =IF(ISNUMBER(BN24),BN24/MAX(BN$22:BN24)-1,"") -> -0.0068370723 | BR24: =BR23*(1+BS24) -> 102.28925 | BS24: =$L$58*W24+$L$59*AE24+$L$60*S24+$L$61*AQ24+$L$62*BC24+$L$63*AA24+$L$64*BG24+$L$65*AY24+$L$66*AI24 -> -0.0062043459 | BT24: =IF(ISNUMBER(BR24),BR24/MAX(BR$22:BR24)-1,"") -> -0.0062043459 | BV24: 45565 | BW24: =BR60/BR57-1 -> -0.011299984 | BX24: =BN60/BN57-1 -> -0.021350007 | BY24: =BJ60/BJ57-1 -> -0.0036196006
E25: Global | F25: =SUMIF($D$12:$D$20, E25, $L$12:$L$20) -> 0.39 | H25: Defensive | I25: =SUMIF($F$12:$F$20, H25, $L$12:$L$20) -> 0.4 | Q25: 44498 | R25: 100.24 | S25: =IF(AND(ISNUMBER(R24),ISNUMBER(R25)),R25/R24-1,"") -> 0 | T25: =IF(ISNUMBER(R25),R25/MAX(R$22:R25)-1,"") -> -0.00019948135 | V25: 605 | W25: =IF(AND(ISNUMBER(V24),ISNUMBER(V25)),V25/V24-1,"") -> -0.0031470894 | X25: =IF(ISNUMBER(V25),V25/MAX(V$22:V25)-1,"") -> -0.022317028 | Z25: 29.29 | AA25: =IF(AND(ISNUMBER(Z24),ISNUMBER(Z25)),Z25/Z24-1,"") -> -0.012141653 | AB25: =IF(ISNUMBER(Z25),Z25/MAX(Z$22:Z25)-1,"") -> -0.029489728 | AD25: 16.04 | AE25: =IF(AND(ISNUMBER(AD24),ISNUMBER(AD25)),AD25/AD24-1,"") -> -0.0098765432 | AF25: =IF(ISNUMBER(AD25),AD25/MAX(AD$22:AD25)-1,"") -> -0.0098765432 | AH25: 22.154 | AI25: =IF(AND(ISNUMBER(AH24),ISNUMBER(AH25)),AH25/AH24-1,"") -> -0.010717156 | AJ25: =IF(ISNUMBER(AH25),AH25/MAX(AH$22:AH25)-1,"") -> -0.041906327 | AL25: 49.06 | AM25: =IF(AND(ISNUMBER(AL24),ISNUMBER(AL25)),AL25/AL24-1,"") -> -0.0044642857 | AN25: =IF(ISNUMBER(AL25),AL25/MAX(AL$22:AL25)-1,"") -> -0.016833667 | AP25: 60.05 | AQ25: =IF(AND(ISNUMBER(AP24),ISNUMBER(AP25)),AP25/AP24-1,"") -> 0.005189153 | AR25: =IF(ISNUMBER(AP25),AP25/MAX(AP$22:AP25)-1,"") -> -0.017988553 | AT25: 50.07 | AU25: =IF(AND(ISNUMBER(AT24),ISNUMBER(AT25)),AT25/AT24-1,"") -> -0.00019968051 | AV25: =IF(ISNUMBER(AT25),AT25/MAX(AT$22:AT25)-1,"") -> -0.00039928129 | AX25: 312.38 | AY25: =IF(AND(ISNUMBER(AX24),ISNUMBER(AX25)),AX25/AX24-1,"") -> -0.0034454157 | AZ25: =IF(ISNUMBER(AX25),AX25/MAX(AX$22:AX25)-1,"") -> -0.02231542 | BB25: 61.54 | BC25: =IF(AND(ISNUMBER(BB24),ISNUMBER(BB25)),BB25/BB24-1,"") -> 0.019042888 | BD25: =IF(ISNUMBER(BB25),BB25/MAX(BB$22:BB25)-1,"") -> -0.0054945055 | BF25: 51.53 | BG25: =IF(AND(ISNUMBER(BF24),ISNUMBER(BF25)),BF25/BF24-1,"") -> -0.030479774 | BH25: =IF(ISNUMBER(BF25),BF25/MAX(BF$22:BF25)-1,"") -> -0.039694372 | BJ25: =BJ24*(1+BK25) -> 100.62359 | BK25: =$L$12*S25+$L$13*W25+$L$14*AA25+$L$15*AE25+$L$16*AI25+$L$17*AM25+$L$18*AQ25+$L$19*AU25+$L$20*AY25 -> -0.0053609519 | BL25: =IF(ISNUMBER(BJ25),BJ25/MAX(BJ$22:BJ25)-1,"") -> -0.016515314 | BN25: =BN24*(1+BO25) -> 101.33147 | BO25: =$L$35*W25+$L$36*S25+$L$37*AA25+$L$38*AE25+$L$39*AQ25+$L$40*AY25+$L$41*BC25+$L$42*BG25+$L$43*AI25 -> -0.005690347 | BP25: =IF(ISNUMBER(BN25),BN25/MAX(BN$22:BN25)-1,"") -> -0.012488514 | BR25: =BR24*(1+BS25) -> 102.11993 | BS25: =$L$58*W25+$L$59*AE25+$L$60*S25+$L$61*AQ25+$L$62*BC25+$L$63*AA25+$L$64*BG25+$L$65*AY25+$L$66*AI25 -> -0.001655314 | BT25: =IF(ISNUMBER(BR25),BR25/MAX(BR$22:BR25)-1,"") -> -0.0078493897 | BV25: 45657 | BW25: =BR63/BR60-1 -> 0.068569115 | BX25: =BN63/BN60-1 -> 0.074800193 | BY25: =BJ63/BJ60-1 -> 0.074552425
E26: Australia | F26: =SUMIF($D$12:$D$20, E26, $L$12:$L$20) -> 0.21 | I26: =SUM(I24:I25) -> 1 | Q26: 44530 | R26: 100.23 | S26: =IF(AND(ISNUMBER(R25),ISNUMBER(R26)),R26/R25-1,"") -> -9.9760575e-05 | T26: =IF(ISNUMBER(R26),R26/MAX(R$22:R26)-1,"") -> -0.00029922202 | V26: 651.76 | W26: =IF(AND(ISNUMBER(V25),ISNUMBER(V26)),V26/V25-1,"") -> 0.077289256 | X26: =IF(ISNUMBER(V26),V26/MAX(V$22:V26)-1,"") -> 0 | Z26: 30.48 | AA26: =IF(AND(ISNUMBER(Z25),ISNUMBER(Z26)),Z26/Z25-1,"") -> 0.040628201 | AB26: =IF(ISNUMBER(Z26),Z26/MAX(Z$22:Z26)-1,"") -> 0 | AD26: 16.26 | AE26: =IF(AND(ISNUMBER(AD25),ISNUMBER(AD26)),AD26/AD25-1,"") -> 0.013715711 | AF26: =IF(ISNUMBER(AD26),AD26/MAX(AD$22:AD26)-1,"") -> 0 | AH26: 23.39 | AI26: =IF(AND(ISNUMBER(AH25),ISNUMBER(AH26)),AH26/AH25-1,"") -> 0.055791279 | AJ26: =IF(ISNUMBER(AH26),AH26/MAX(AH$22:AH26)-1,"") -> 0 | AL26: 49.2 | AM26: =IF(AND(ISNUMBER(AL25),ISNUMBER(AL26)),AL26/AL25-1,"") -> 0.0028536486 | AN26: =IF(ISNUMBER(AL26),AL26/MAX(AL$22:AL26)-1,"") -> -0.014028056 | AP26: 62.44 | AQ26: =IF(AND(ISNUMBER(AP25),ISNUMBER(AP26)),AP26/AP25-1,"") -> 0.039800167 | AR26: =IF(ISNUMBER(AP26),AP26/MAX(AP$22:AP26)-1,"") -> 0 | AT26: 50.07 | AU26: =IF(AND(ISNUMBER(AT25),ISNUMBER(AT26)),AT26/AT25-1,"") -> 0 | AV26: =IF(ISNUMBER(AT26),AT26/MAX(AT$22:AT26)-1,"") -> -0.00039928129 | AX26: 333.96 | AY26: =IF(AND(ISNUMBER(AX25),ISNUMBER(AX26)),AX26/AX25-1,"") -> 0.069082528 | AZ26: =IF(ISNUMBER(AX26),AX26/MAX(AX$22:AX26)-1,"") -> 0 | BB26: 59.86 | BC26: =IF(AND(ISNUMBER(BB25),ISNUMBER(BB26)),BB26/BB25-1,"") -> -0.027299318 | BD26: =IF(ISNUMBER(BB26),BB26/MAX(BB$22:BB26)-1,"") -> -0.032643827 | BF26: 51.92 | BG26: =IF(AND(ISNUMBER(BF25),ISNUMBER(BF26)),BF26/BF25-1,"") -> 0.0075684068 | BH26: =IF(ISNUMBER(BF26),BF26/MAX(BF$22:BF26)-1,"") -> -0.032426388 | BJ26: =BJ25*(1+BK26) -> 104.75188 | BK26: =$L$12*S26+$L$13*W26+$L$14*AA26+$L$15*AE26+$L$16*AI26+$L$17*AM26+$L$18*AQ26+$L$19*AU26+$L$20*AY26 -> 0.041027048 | BL26: =IF(ISNUMBER(BJ26),BJ26/MAX(BJ$22:BJ26)-1,"") -> 0 | BN26: =BN25*(1+BO26) -> 105.25265 | BO26: =$L$35*W26+$L$36*S26+$L$37*AA26+$L$38*AE26+$L$39*AQ26+$L$40*AY26+$L$41*BC26+$L$42*BG26+$L$43*AI26 -> 0.038696516 | BP26: =IF(ISNUMBER(BN26),BN26/MAX(BN$22:BN26)-1,"") -> 0 | BR26: =BR25*(1+BS26) -> 105.32353 | BS26: =$L$58*W26+$L$59*AE26+$L$60*S26+$L$61*AQ26+$L$62*BC26+$L$63*AA26+$L$64*BG26+$L$65*AY26+$L$66*AI26 -> 0.031371008 | BT26: =IF(ISNUMBER(BR26),BR26/MAX(BR$22:BR26)-1,"") -> 0 | BV26: 45747 | BW26: =BR66/BR63-1 -> -0.029213349 | BX26: =BN66/BN63-1 -> -0.017658008 | BY26: =BJ66/BJ63-1 -> -0.00098420647
E27: Japan | F27: =SUMIF($D$12:$D$20, E27, $L$12:$L$20) -> 0.1 | Q27: 44561 | R27: 100.24 | S27: =IF(AND(ISNUMBER(R26),ISNUMBER(R27)),R27/R26-1,"") -> 9.9770528e-05 | T27: =IF(ISNUMBER(R27),R27/MAX(R$22:R27)-1,"") -> -0.00019948135 | V27: 655.9 | W27: =IF(AND(ISNUMBER(V26),ISNUMBER(V27)),V27/V26-1,"") -> 0.0063520314 | X27: =IF(ISNUMBER(V27),V27/MAX(V$22:V27)-1,"") -> 0 | Z27: 31.06 | AA27: =IF(AND(ISNUMBER(Z26),ISNUMBER(Z27)),Z27/Z26-1,"") -> 0.019028871 | AB27: =IF(ISNUMBER(Z27),Z27/MAX(Z$22:Z27)-1,"") -> 0 | AD27: 16.56 | AE27: =IF(AND(ISNUMBER(AD26),ISNUMBER(AD27)),AD27/AD26-1,"") -> 0.018450185 | AF27: =IF(ISNUMBER(AD27),AD27/MAX(AD$22:AD27)-1,"") -> 0 | AH27: 23.37 | AI27: =IF(AND(ISNUMBER(AH26),ISNUMBER(AH27)),AH27/AH26-1,"") -> -0.00085506627 | AJ27: =IF(ISNUMBER(AH27),AH27/MAX(AH$22:AH27)-1,"") -> -0.00085506627 | AL27: 49.04 | AM27: =IF(AND(ISNUMBER(AL26),ISNUMBER(AL27)),AL27/AL26-1,"") -> -0.0032520325 | AN27: =IF(ISNUMBER(AL27),AL27/MAX(AL$22:AL27)-1,"") -> -0.017234469 | AP27: 64.14 | AQ27: =IF(AND(ISNUMBER(AP26),ISNUMBER(AP27)),AP27/AP26-1,"") -> 0.027226137 | AR27: =IF(ISNUMBER(AP27),AP27/MAX(AP$22:AP27)-1,"") -> 0 | AT27: 50.08 | AU27: =IF(AND(ISNUMBER(AT26),ISNUMBER(AT27)),AT27/AT26-1,"") -> 0.00019972039 | AV27: =IF(ISNUMBER(AT27),AT27/MAX(AT$22:AT27)-1,"") -> -0.00019964065 | AX27: 333.63 | AY27: =IF(AND(ISNUMBER(AX26),ISNUMBER(AX27)),AX27/AX26-1,"") -> -0.00098814229 | AZ27: =IF(ISNUMBER(AX27),AX27/MAX(AX$22:AX27)-1,"") -> -0.00098814229 | BB27: 61.6 | BC27: =IF(AND(ISNUMBER(BB26),ISNUMBER(BB27)),BB27/BB26-1,"") -> 0.029067825 | BD27: =IF(ISNUMBER(BB27),BB27/MAX(BB$22:BB27)-1,"") -> -0.0045248869 | BF27: 52.19 | BG27: =IF(AND(ISNUMBER(BF26),ISNUMBER(BF27)),BF27/BF26-1,"") -> 0.0052003082 | BH27: =IF(ISNUMBER(BF27),BF27/MAX(BF$22:BF27)-1,"") -> -0.027394707 | BJ27: =BJ26*(1+BK27) -> 105.55013 | BK27: =$L$12*S27+$L$13*W27+$L$14*AA27+$L$15*AE27+$L$16*AI27+$L$17*AM27+$L$18*AQ27+$L$19*AU27+$L$20*AY27 -> 0.0076204058 | BL27: =IF(ISNUMBER(BJ27),BJ27/MAX(BJ$22:BJ27)-1,"") -> 0 | BN27: =BN26*(1+BO27) -> 106.27681 | BO27: =$L$35*W27+$L$36*S27+$L$37*AA27+$L$38*AE27+$L$39*AQ27+$L$40*AY27+$L$41*BC27+$L$42*BG27+$L$43*AI27 -> 0.0097304628 | BP27: =IF(ISNUMBER(BN27),BN27/MAX(BN$22:BN27)-1,"") -> 0 | BR27: =BR26*(1+BS27) -> 106.72523 | BS27: =$L$58*W27+$L$59*AE27+$L$60*S27+$L$61*AQ27+$L$62*BC27+$L$63*AA27+$L$64*BG27+$L$65*AY27+$L$66*AI27 -> 0.013308476 | BT27: =IF(ISNUMBER(BR27),BR27/MAX(BR$22:BR27)-1,"") -> 0 | BV27: 45838 | BW27: =BR69/BR66-1 -> 0.051180328 | BX27: =BN69/BN66-1 -> 0.048826179 | BY27: =BJ69/BJ66-1 -> 0.041127357
E28: China | F28: =SUMIF($D$12:$D$20, E28, $L$12:$L$20) -> 0 | Q28: 44592 | R28: 100.26 | S28: =IF(AND(ISNUMBER(R27),ISNUMBER(R28)),R28/R27-1,"") -> 0.00019952115 | T28: =IF(ISNUMBER(R28),R28/MAX(R$22:R28)-1,"") -> 0 | V28: 632 | W28: =IF(AND(ISNUMBER(V27),ISNUMBER(V28)),V28/V27-1,"") -> -0.036438481 | X28: =IF(ISNUMBER(V28),V28/MAX(V$22:V28)-1,"") -> -0.036438481 | Z28: 30 | AA28: =IF(AND(ISNUMBER(Z27),ISNUMBER(Z28)),Z28/Z27-1,"") -> -0.034127495 | AB28: =IF(ISNUMBER(Z28),Z28/MAX(Z$22:Z28)-1,"") -> -0.034127495 | AD28: 15.25 | AE28: =IF(AND(ISNUMBER(AD27),ISNUMBER(AD28)),AD28/AD27-1,"") -> -0.07910628 | AF28: =IF(ISNUMBER(AD28),AD28/MAX(AD$22:AD28)-1,"") -> -0.07910628 | AH28: 23.753 | AI28: =IF(AND(ISNUMBER(AH27),ISNUMBER(AH28)),AH28/AH27-1,"") -> 0.016388532 | AJ28: =IF(ISNUMBER(AH28),AH28/MAX(AH$22:AH28)-1,"") -> 0 | AL28: 48.1 | AM28: =IF(AND(ISNUMBER(AL27),ISNUMBER(AL28)),AL28/AL27-1,"") -> -0.019168026 | AN28: =IF(ISNUMBER(AL28),AL28/MAX(AL$22:AL28)-1,"") -> -0.036072144 | AP28: 63.46 | AQ28: =IF(AND(ISNUMBER(AP27),ISNUMBER(AP28)),AP28/AP27-1,"") -> -0.010601809 | AR28: =IF(ISNUMBER(AP28),AP28/MAX(AP$22:AP28)-1,"") -> -0.010601809 | AT28: 50.08 | AU28: =IF(AND(ISNUMBER(AT27),ISNUMBER(AT28)),AT28/AT27-1,"") -> 0 | AV28: =IF(ISNUMBER(AT28),AT28/MAX(AT$22:AT28)-1,"") -> -0.00019964065 | AX28: 317.3 | AY28: =IF(AND(ISNUMBER(AX27),ISNUMBER(AX28)),AX28/AX27-1,"") -> -0.048946438 | AZ28: =IF(ISNUMBER(AX28),AX28/MAX(AX$22:AX28)-1,"") -> -0.049886214 | BB28: 56.06 | BC28: =IF(AND(ISNUMBER(BB27),ISNUMBER(BB28)),BB28/BB27-1,"") -> -0.089935065 | BD28: =IF(ISNUMBER(BB28),BB28/MAX(BB$22:BB28)-1,"") -> -0.094053006 | BF28: 51.56 | BG28: =IF(AND(ISNUMBER(BF27),ISNUMBER(BF28)),BF28/BF27-1,"") -> -0.012071278 | BH28: =IF(ISNUMBER(BF28),BF28/MAX(BF$22:BF28)-1,"") -> -0.039135296 | BJ28: =BJ27*(1+BK28) -> 103.12369 | BK28: =$L$12*S28+$L$13*W28+$L$14*AA28+$L$15*AE28+$L$16*AI28+$L$17*AM28+$L$18*AQ28+$L$19*AU28+$L$20*AY28 -> -0.022988517 | BL28: =IF(ISNUMBER(BJ28),BJ28/MAX(BJ$22:BJ28)-1,"") -> -0.022988517 | BN28: =BN27*(1+BO28) -> 103.01338 | BO28: =$L$35*W28+$L$36*S28+$L$37*AA28+$L$38*AE28+$L$39*AQ28+$L$40*AY28+$L$41*BC28+$L$42*BG28+$L$43*AI28 -> -0.030706884 | BP28: =IF(ISNUMBER(BN28),BN28/MAX(BN$22:BN28)-1,"") -> -0.030706884 | BR28: =BR27*(1+BS28) -> 102.44512 | BS28: =$L$58*W28+$L$59*AE28+$L$60*S28+$L$61*AQ28+$L$62*BC28+$L$63*AA28+$L$64*BG28+$L$65*AY28+$L$66*AI28 -> -0.040104009 | BT28: =IF(ISNUMBER(BR28),BR28/MAX(BR$22:BR28)-1,"") -> -0.040104009 | BV28: 45930 | BW28: =BR72/BR69-1 -> 0.041670945 | BX28: =BN72/BN69-1 -> 0.039962037 | BY28: =BJ72/BJ69-1 -> 0.046556556
E29: Emerging Markets | F29: =SUMIF($D$12:$D$20, E29, $L$12:$L$20) -> 0 | Q29: 44620 | R29: 100.26 | S29: =IF(AND(ISNUMBER(R28),ISNUMBER(R29)),R29/R28-1,"") -> 0 | T29: =IF(ISNUMBER(R29),R29/MAX(R$22:R29)-1,"") -> 0 | V29: 595.64 | W29: =IF(AND(ISNUMBER(V28),ISNUMBER(V29)),V29/V28-1,"") -> -0.057531646 | X29: =IF(ISNUMBER(V29),V29/MAX(V$22:V29)-1,"") -> -0.091873761 | Z29: 27.84 | AA29: =IF(AND(ISNUMBER(Z28),ISNUMBER(Z29)),Z29/Z28-1,"") -> -0.072 | AB29: =IF(ISNUMBER(Z29),Z29/MAX(Z$22:Z29)-1,"") -> -0.10367032 | AD29: 14.79 | AE29: =IF(AND(ISNUMBER(AD28),ISNUMBER(AD29)),AD29/AD28-1,"") -> -0.030163934 | AF29: =IF(ISNUMBER(AD29),AD29/MAX(AD$22:AD29)-1,"") -> -0.10688406 | AH29: 24.794 | AI29: =IF(AND(ISNUMBER(AH28),ISNUMBER(AH29)),AH29/AH28-1,"") -> 0.043826043 | AJ29: =IF(ISNUMBER(AH29),AH29/MAX(AH$22:AH29)-1,"") -> 0 | AL29: 47.4 | AM29: =IF(AND(ISNUMBER(AL28),ISNUMBER(AL29)),AL29/AL28-1,"") -> -0.014553015 | AN29: =IF(ISNUMBER(AL29),AL29/MAX(AL$22:AL29)-1,"") -> -0.0501002 | AP29: 61.03 | AQ29: =IF(AND(ISNUMBER(AP28),ISNUMBER(AP29)),AP29/AP28-1,"") -> -0.038291837 | AR29: =IF(ISNUMBER(AP29),AP29/MAX(AP$22:AP29)-1,"") -> -0.048487683 | AT29: 50.07 | AU29: =IF(AND(ISNUMBER(AT28),ISNUMBER(AT29)),AT29/AT28-1,"") -> -0.00019968051 | AV29: =IF(ISNUMBER(AT29),AT29/MAX(AT$22:AT29)-1,"") -> -0.00039928129 | AX29: 301.16 | AY29: =IF(AND(ISNUMBER(AX28),ISNUMBER(AX29)),AX29/AX28-1,"") -> -0.050866688 | AZ29: =IF(ISNUMBER(AX29),AX29/MAX(AX$22:AX29)-1,"") -> -0.098215355 | BB29: 56.48 | BC29: =IF(AND(ISNUMBER(BB28),ISNUMBER(BB29)),BB29/BB28-1,"") -> 0.0074919729 | BD29: =IF(ISNUMBER(BB29),BB29/MAX(BB$22:BB29)-1,"") -> -0.087265676 | BF29: 50.96 | BG29: =IF(AND(ISNUMBER(BF28),ISNUMBER(BF29)),BF29/BF28-1,"") -> -0.011636928 | BH29: =IF(ISNUMBER(BF29),BF29/MAX(BF$22:BF29)-1,"") -> -0.05031681 | BJ29: =BJ28*(1+BK29) -> 100.33086 | BK29: =$L$12*S29+$L$13*W29+$L$14*AA29+$L$15*AE29+$L$16*AI29+$L$17*AM29+$L$18*AQ29+$L$19*AU29+$L$20*AY29 -> -0.027082356 | BL29: =IF(ISNUMBER(BJ29),BJ29/MAX(BJ$22:BJ29)-1,"") -> -0.04944829 | BN29: =BN28*(1+BO29) -> 99.540123 | BO29: =$L$35*W29+$L$36*S29+$L$37*AA29+$L$38*AE29+$L$39*AQ29+$L$40*AY29+$L$41*BC29+$L$42*BG29+$L$43*AI29 -> -0.033716533 | BP29: =IF(ISNUMBER(BN29),BN29/MAX(BN$22:BN29)-1,"") -> -0.063388087 | BR29: =BR28*(1+BS29) -> 99.1183 | BS29: =$L$58*W29+$L$59*AE29+$L$60*S29+$L$61*AQ29+$L$62*BC29+$L$63*AA29+$L$64*BG29+$L$65*AY29+$L$66*AI29 -> -0.03247415 | BT29: =IF(ISNUMBER(BR29),BR29/MAX(BR$22:BR29)-1,"") -> -0.071275815 | BV29: 46022 | BW29: =BR75/BR72-1 -> 0.025298788 | BX29: =BN75/BN72-1 -> 0.033413402 | BY29: =BJ75/BJ72-1 -> 0.033722671
F30: =SUM(F24:F29) -> 1 | Q30: 44651 | R30: 100.26 | S30: =IF(AND(ISNUMBER(R29),ISNUMBER(R30)),R30/R29-1,"") -> 0 | T30: =IF(ISNUMBER(R30),R30/MAX(R$22:R30)-1,"") -> 0 | V30: 614.1 | W30: =IF(AND(ISNUMBER(V29),ISNUMBER(V30)),V30/V29-1,"") -> 0.030991874 | X30: =IF(ISNUMBER(V30),V30/MAX(V$22:V30)-1,"") -> -0.063729227 | Z30: 28.11 | AA30: =IF(AND(ISNUMBER(Z29),ISNUMBER(Z30)),Z30/Z29-1,"") -> 0.0096982759 | AB30: =IF(ISNUMBER(Z30),Z30/MAX(Z$22:Z30)-1,"") -> -0.094977463 | AD30: 15.53 | AE30: =IF(AND(ISNUMBER(AD29),ISNUMBER(AD30)),AD30/AD29-1,"") -> 0.050033807 | AF30: =IF(ISNUMBER(AD30),AD30/MAX(AD$22:AD30)-1,"") -> -0.062198068 | AH30: 23.924 | AI30: =IF(AND(ISNUMBER(AH29),ISNUMBER(AH30)),AH30/AH29-1,"") -> -0.035089134 | AJ30: =IF(ISNUMBER(AH30),AH30/MAX(AH$22:AH30)-1,"") -> -0.035089134 | AL30: 46.07 | AM30: =IF(AND(ISNUMBER(AL29),ISNUMBER(AL30)),AL30/AL29-1,"") -> -0.028059072 | AN30: =IF(ISNUMBER(AL30),AL30/MAX(AL$22:AL30)-1,"") -> -0.076753507 | AP30: 64.86 | AQ30: =IF(AND(ISNUMBER(AP29),ISNUMBER(AP30)),AP30/AP29-1,"") -> 0.062756022 | AR30: =IF(ISNUMBER(AP30),AP30/MAX(AP$22:AP30)-1,"") -> 0 | AT30: 50.07 | AU30: =IF(AND(ISNUMBER(AT29),ISNUMBER(AT30)),AT30/AT29-1,"") -> 0 | AV30: =IF(ISNUMBER(AT30),AT30/MAX(AT$22:AT30)-1,"") -> -0.00039928129 | AX30: 309.74 | AY30: =IF(AND(ISNUMBER(AX29),ISNUMBER(AX30)),AX30/AX29-1,"") -> 0.028489839 | AZ30: =IF(ISNUMBER(AX30),AX30/MAX(AX$22:AX30)-1,"") -> -0.072523656 | BB30: 60.63 | BC30: =IF(AND(ISNUMBER(BB29),ISNUMBER(BB30)),BB30/BB29-1,"") -> 0.073477337 | BD30: =IF(ISNUMBER(BB30),BB30/MAX(BB$22:BB30)-1,"") -> -0.020200388 | BF30: 49.44 | BG30: =IF(AND(ISNUMBER(BF29),ISNUMBER(BF30)),BF30/BF29-1,"") -> -0.029827316 | BH30: =IF(ISNUMBER(BF30),BF30/MAX(BF$22:BF30)-1,"") -> -0.07864331 | BJ30: =BJ29*(1+BK30) -> 101.55984 | BK30: =$L$12*S30+$L$13*W30+$L$14*AA30+$L$15*AE30+$L$16*AI30+$L$17*AM30+$L$18*AQ30+$L$19*AU30+$L$20*AY30 -> 0.012249278 | BL30: =IF(ISNUMBER(BJ30),BJ30/MAX(BJ$22:BJ30)-1,"") -> -0.037804718 | BN30: =BN29*(1+BO30) -> 101.44956 | BO30: =$L$35*W30+$L$36*S30+$L$37*AA30+$L$38*AE30+$L$39*AQ30+$L$40*AY30+$L$41*BC30+$L$42*BG30+$L$43*AI30 -> 0.019182628 | BP30: =IF(ISNUMBER(BN30),BN30/MAX(BN$22:BN30)-1,"") -> -0.045421409 | BR30: =BR29*(1+BS30) -> 102.48779 | BS30: =$L$58*W30+$L$59*AE30+$L$60*S30+$L$61*AQ30+$L$62*BC30+$L$63*AA30+$L$64*BG30+$L$65*AY30+$L$66*AI30 -> 0.033994676 | BT30: =IF(ISNUMBER(BR30),BR30/MAX(BR$22:BR30)-1,"") -> -0.039704137 | BV30: 46112 | BW30: =BR78/BR75-1 -> -0.02866822 | BX30: =BN78/BN75-1 -> -0.037665844 | BY30: =BJ78/BJ75-1 -> -0.034105212
Q31: 44680 | R31: 100.26 | S31: =IF(AND(ISNUMBER(R30),ISNUMBER(R31)),R31/R30-1,"") -> 0 | T31: =IF(ISNUMBER(R31),R31/MAX(R$22:R31)-1,"") -> 0 | V31: 596.53 | W31: =IF(AND(ISNUMBER(V30),ISNUMBER(V31)),V31/V30-1,"") -> -0.028610975 | X31: =IF(ISNUMBER(V31),V31/MAX(V$22:V31)-1,"") -> -0.090516847 | Z31: 27.59 | AA31: =IF(AND(ISNUMBER(Z30),ISNUMBER(Z31)),Z31/Z30-1,"") -> -0.018498755 | AB31: =IF(ISNUMBER(Z31),Z31/MAX(Z$22:Z31)-1,"") -> -0.11171925 | AD31: 15.16 | AE31: =IF(AND(ISNUMBER(AD30),ISNUMBER(AD31)),AD31/AD30-1,"") -> -0.023824855 | AF31: =IF(ISNUMBER(AD31),AD31/MAX(AD$22:AD31)-1,"") -> -0.084541063 | AH31: 24.817 | AI31: =IF(AND(ISNUMBER(AH30),ISNUMBER(AH31)),AH31/AH30-1,"") -> 0.037326534 | AJ31: =IF(ISNUMBER(AH31),AH31/MAX(AH$22:AH31)-1,"") -> 0 | AL31: 44.8 | AM31: =IF(AND(ISNUMBER(AL30),ISNUMBER(AL31)),AL31/AL30-1,"") -> -0.027566746 | AN31: =IF(ISNUMBER(AL31),AL31/MAX(AL$22:AL31)-1,"") -> -0.10220441 | AP31: 65.4 | AQ31: =IF(AND(ISNUMBER(AP30),ISNUMBER(AP31)),AP31/AP30-1,"") -> 0.0083256244 | AR31: =IF(ISNUMBER(AP31),AP31/MAX(AP$22:AP31)-1,"") -> 0 | AT31: 50.07 | AU31: =IF(AND(ISNUMBER(AT30),ISNUMBER(AT31)),AT31/AT30-1,"") -> 0 | AV31: =IF(ISNUMBER(AT31),AT31/MAX(AT$22:AT31)-1,"") -> -0.00039928129 | AX31: 299.49 | AY31: =IF(AND(ISNUMBER(AX30),ISNUMBER(AX31)),AX31/AX30-1,"") -> -0.033092271 | AZ31: =IF(ISNUMBER(AX31),AX31/MAX(AX$22:AX31)-1,"") -> -0.10321595 | BB31: 59.6 | BC31: =IF(AND(ISNUMBER(BB30),ISNUMBER(BB31)),BB31/BB30-1,"") -> -0.01698829 | BD31: =IF(ISNUMBER(BB31),BB31/MAX(BB$22:BB31)-1,"") -> -0.036845507 | BF31: 48.38 | BG31: =IF(AND(ISNUMBER(BF30),ISNUMBER(BF31)),BF31/BF30-1,"") -> -0.021440129 | BH31: =IF(ISNUMBER(BF31),BF31/MAX(BF$22:BF31)-1,"") -> -0.098397316 | BJ31: =BJ30*(1+BK31) -> 100.64673 | BK31: =$L$12*S31+$L$13*W31+$L$14*AA31+$L$15*AE31+$L$16*AI31+$L$17*AM31+$L$18*AQ31+$L$19*AU31+$L$20*AY31 -> -0.0089908401 | BL31: =IF(ISNUMBER(BJ31),BJ31/MAX(BJ$22:BJ31)-1,"") -> -0.046455662 | BN31: =BN30*(1+BO31) -> 100.1088 | BO31: =$L$35*W31+$L$36*S31+$L$37*AA31+$L$38*AE31+$L$39*AQ31+$L$40*AY31+$L$41*BC31+$L$42*BG31+$L$43*AI31 -> -0.0132161 | BP31: =IF(ISNUMBER(BN31),BN31/MAX(BN$22:BN31)-1,"") -> -0.058037216 | BR31: =BR30*(1+BS31) -> 100.88922 | BS31: =$L$58*W31+$L$59*AE31+$L$60*S31+$L$61*AQ31+$L$62*BC31+$L$63*AA31+$L$64*BG31+$L$65*AY31+$L$66*AI31 -> -0.01559767 | BT31: =IF(ISNUMBER(BR31),BR31/MAX(BR$22:BR31)-1,"") -> -0.054682515 | BV31: 46203 | BW31: =BR81/BR78-1 -> 0.10922536 | BX31: =BN81/BN78-1 -> 0.11090034 | BY31: =BJ81/BJ78-1 -> 0.079622211
Q32: 44712 | R32: 100.27 | S32: =IF(AND(ISNUMBER(R31),ISNUMBER(R32)),R32/R31-1,"") -> 9.9740674e-05 | T32: =IF(ISNUMBER(R32),R32/MAX(R$22:R32)-1,"") -> 0 | V32: 579.32 | W32: =IF(AND(ISNUMBER(V31),ISNUMBER(V32)),V32/V31-1,"") -> -0.028850184 | X32: =IF(ISNUMBER(V32),V32/MAX(V$22:V32)-1,"") -> -0.1167556 | Z32: 27.57 | AA32: =IF(AND(ISNUMBER(Z31),ISNUMBER(Z32)),Z32/Z31-1,"") -> -0.00072490033 | AB32: =IF(ISNUMBER(Z32),Z32/MAX(Z$22:Z32)-1,"") -> -0.11236317 | AD32: 15.08 | AE32: =IF(AND(ISNUMBER(AD31),ISNUMBER(AD32)),AD32/AD31-1,"") -> -0.0052770449 | AF32: =IF(ISNUMBER(AD32),AD32/MAX(AD$22:AD32)-1,"") -> -0.089371981 | AH32: 24.01 | AI32: =IF(AND(ISNUMBER(AH31),ISNUMBER(AH32)),AH32/AH31-1,"") -> -0.032518032 | AJ32: =IF(ISNUMBER(AH32),AH32/MAX(AH$22:AH32)-1,"") -> -0.032518032 | AL32: 44.61 | AM32: =IF(AND(ISNUMBER(AL31),ISNUMBER(AL32)),AL32/AL31-1,"") -> -0.0042410714 | AN32: =IF(ISNUMBER(AL32),AL32/MAX(AL$22:AL32)-1,"") -> -0.10601202 | AP32: 65.03 | AQ32: =IF(AND(ISNUMBER(AP31),ISNUMBER(AP32)),AP32/AP31-1,"") -> -0.0056574924 | AR32: =IF(ISNUMBER(AP32),AP32/MAX(AP$22:AP32)-1,"") -> -0.0056574924 | AT32: 50.08 | AU32: =IF(AND(ISNUMBER(AT31),ISNUMBER(AT32)),AT32/AT31-1,"") -> 0.00019972039 | AV32: =IF(ISNUMBER(AT32),AT32/MAX(AT$22:AT32)-1,"") -> -0.00019964065 | AX32: 290.4 | AY32: =IF(AND(ISNUMBER(AX31),ISNUMBER(AX32)),AX32/AX31-1,"") -> -0.030351598 | AZ32: =IF(ISNUMBER(AX32),AX32/MAX(AX$22:AX32)-1,"") -> -0.13043478 | BB32: 57.47 | BC32: =IF(AND(ISNUMBER(BB31),ISNUMBER(BB32)),BB32/BB31-1,"") -> -0.035738255 | BD32: =IF(ISNUMBER(BB32),BB32/MAX(BB$22:BB32)-1,"") -> -0.071266968 | BF32: 48.2 | BG32: =IF(AND(ISNUMBER(BF31),ISNUMBER(BF32)),BF32/BF31-1,"") -> -0.0037205457 | BH32: =IF(ISNUMBER(BF32),BF32/MAX(BF$22:BF32)-1,"") -> -0.10175177 | BJ32: =BJ31*(1+BK32) -> 99.177984 | BK32: =$L$12*S32+$L$13*W32+$L$14*AA32+$L$15*AE32+$L$16*AI32+$L$17*AM32+$L$18*AQ32+$L$19*AU32+$L$20*AY32 -> -0.014593082 | BL32: =IF(ISNUMBER(BJ32),BJ32/MAX(BJ$22:BJ32)-1,"") -> -0.060370813 | BN32: =BN31*(1+BO32) -> 98.822279 | BO32: =$L$35*W32+$L$36*S32+$L$37*AA32+$L$38*AE32+$L$39*AQ32+$L$40*AY32+$L$41*BC32+$L$42*BG32+$L$43*AI32 -> -0.012851191 | BP32: =IF(ISNUMBER(BN32),BN32/MAX(BN$22:BN32)-1,"") -> -0.07014256 | BR32: =BR31*(1+BS32) -> 99.412599 | BS32: =$L$58*W32+$L$59*AE32+$L$60*S32+$L$61*AQ32+$L$62*BC32+$L$63*AA32+$L$64*BG32+$L$65*AY32+$L$66*AI32 -> -0.014636104 | BT32: =IF(ISNUMBER(BR32),BR32/MAX(BR$22:BR32)-1,"") -> -0.06851828
B33: 70/30 | Q33: 44742 | R33: 100.3 | S33: =IF(AND(ISNUMBER(R32),ISNUMBER(R33)),R33/R32-1,"") -> 0.00029919218 | T33: =IF(ISNUMBER(R33),R33/MAX(R$22:R33)-1,"") -> 0 | V33: 547.38 | W33: =IF(AND(ISNUMBER(V32),ISNUMBER(V33)),V33/V32-1,"") -> -0.055133605 | X33: =IF(ISNUMBER(V33),V33/MAX(V$22:V33)-1,"") -> -0.16545205 | Z33: 26.24 | AA33: =IF(AND(ISNUMBER(Z32),ISNUMBER(Z33)),Z33/Z32-1,"") -> -0.048240841 | AB33: =IF(ISNUMBER(Z33),Z33/MAX(Z$22:Z33)-1,"") -> -0.15518352 | AD33: 14.48 | AE33: =IF(AND(ISNUMBER(AD32),ISNUMBER(AD33)),AD33/AD32-1,"") -> -0.039787798 | AF33: =IF(ISNUMBER(AD33),AD33/MAX(AD$22:AD33)-1,"") -> -0.12560386 | AH33: 24.5 | AI33: =IF(AND(ISNUMBER(AH32),ISNUMBER(AH33)),AH33/AH32-1,"") -> 0.020408163 | AJ33: =IF(ISNUMBER(AH33),AH33/MAX(AH$22:AH33)-1,"") -> -0.012773502 | AL33: 43.52 | AM33: =IF(AND(ISNUMBER(AL32),ISNUMBER(AL33)),AL33/AL32-1,"") -> -0.024433983 | AN33: =IF(ISNUMBER(AL33),AL33/MAX(AL$22:AL33)-1,"") -> -0.12785571 | AP33: 62.95 | AQ33: =IF(AND(ISNUMBER(AP32),ISNUMBER(AP33)),AP33/AP32-1,"") -> -0.031985238 | AR33: =IF(ISNUMBER(AP33),AP33/MAX(AP$22:AP33)-1,"") -> -0.037461774 | AT33: 50.11 | AU33: =IF(AND(ISNUMBER(AT32),ISNUMBER(AT33)),AT33/AT32-1,"") -> 0.00059904153 | AV33: =IF(ISNUMBER(AT33),AT33/MAX(AT$22:AT33)-1,"") -> 0 | AX33: 273.52 | AY33: =IF(AND(ISNUMBER(AX32),ISNUMBER(AX33)),AX33/AX32-1,"") -> -0.058126722 | AZ33: =IF(ISNUMBER(AX33),AX33/MAX(AX$22:AX33)-1,"") -> -0.18097976 | BB33: 51.46 | BC33: =IF(AND(ISNUMBER(BB32),ISNUMBER(BB33)),BB33/BB32-1,"") -> -0.1045763 | BD33: =IF(ISNUMBER(BB33),BB33/MAX(BB$22:BB33)-1,"") -> -0.16839043 | BF33: 47.55 | BG33: =IF(AND(ISNUMBER(BF32),ISNUMBER(BF33)),BF33/BF32-1,"") -> -0.013485477 | BH33: =IF(ISNUMBER(BF33),BF33/MAX(BF$22:BF33)-1,"") -> -0.11386508 | BJ33: =BJ32*(1+BK33) -> 96.469829 | BK33: =$L$12*S33+$L$13*W33+$L$14*AA33+$L$15*AE33+$L$16*AI33+$L$17*AM33+$L$18*AQ33+$L$19*AU33+$L$20*AY33 -> -0.027306011 | BL33: =IF(ISNUMBER(BJ33),BJ33/MAX(BJ$22:BJ33)-1,"") -> -0.086028338 | BN33: =BN32*(1+BO33) -> 95.569647 | BO33: =$L$35*W33+$L$36*S33+$L$37*AA33+$L$38*AE33+$L$39*AQ33+$L$40*AY33+$L$41*BC33+$L$42*BG33+$L$43*AI33 -> -0.03291396 | BP33: =IF(ISNUMBER(BN33),BN33/MAX(BN$22:BN33)-1,"") -> -0.10074785 | BR33: =BR32*(1+BS33) -> 95.101456 | BS33: =$L$58*W33+$L$59*AE33+$L$60*S33+$L$61*AQ33+$L$62*BC33+$L$63*AA33+$L$64*BG33+$L$65*AY33+$L$66*AI33 -> -0.043366157 | BT33: =IF(ISNUMBER(BR33),BR33/MAX(BR$22:BR33)-1,"") -> -0.10891306
B34: Ric | C34: Name | D34: Region | E34: Asset Class | F34: Type | G34: MER | H34: Return | I34: Return - MER | J34: Risk | K34: Drawdown | L34: Weight | M34: Total Risk | N34: Total Drawdown | O34: Total Return | Q34: 44771 | R34: 100.31 | S34: =IF(AND(ISNUMBER(R33),ISNUMBER(R34)),R34/R33-1,"") -> 9.9700897e-05 | T34: =IF(ISNUMBER(R34),R34/MAX(R$22:R34)-1,"") -> 0 | V34: 583.45 | W34: =IF(AND(ISNUMBER(V33),ISNUMBER(V34)),V34/V33-1,"") -> 0.065895721 | X34: =IF(ISNUMBER(V34),V34/MAX(V$22:V34)-1,"") -> -0.11045891 | Z34: 26.55 | AA34: =IF(AND(ISNUMBER(Z33),ISNUMBER(Z34)),Z34/Z33-1,"") -> 0.011814024 | AB34: =IF(ISNUMBER(Z34),Z34/MAX(Z$22:Z34)-1,"") -> -0.14520283 | AD34: 13.94 | AE34: =IF(AND(ISNUMBER(AD33),ISNUMBER(AD34)),AD34/AD33-1,"") -> -0.037292818 | AF34: =IF(ISNUMBER(AD34),AD34/MAX(AD$22:AD34)-1,"") -> -0.15821256 | AH34: 23.39 | AI34: =IF(AND(ISNUMBER(AH33),ISNUMBER(AH34)),AH34/AH33-1,"") -> -0.045306122 | AJ34: =IF(ISNUMBER(AH34),AH34/MAX(AH$22:AH34)-1,"") -> -0.057500907 | AL34: 44.76 | AM34: =IF(AND(ISNUMBER(AL33),ISNUMBER(AL34)),AL34/AL33-1,"") -> 0.028492647 | AN34: =IF(ISNUMBER(AL34),AL34/MAX(AL$22:AL34)-1,"") -> -0.10300601 | AP34: 65.32 | AQ34: =IF(AND(ISNUMBER(AP33),ISNUMBER(AP34)),AP34/AP33-1,"") -> 0.037648928 | AR34: =IF(ISNUMBER(AP34),AP34/MAX(AP$22:AP34)-1,"") -> -0.0012232416 | AT34: 50.13 | AU34: =IF(AND(ISNUMBER(AT33),ISNUMBER(AT34)),AT34/AT33-1,"") -> 0.00039912193 | AV34: =IF(ISNUMBER(AT34),AT34/MAX(AT$22:AT34)-1,"") -> 0 | AX34: 292.03 | AY34: =IF(AND(ISNUMBER(AX33),ISNUMBER(AX34)),AX34/AX33-1,"") -> 0.067673296 | AZ34: =IF(ISNUMBER(AX34),AX34/MAX(AX$22:AX34)-1,"") -> -0.12555396 | BB34: 54.54 | BC34: =IF(AND(ISNUMBER(BB33),ISNUMBER(BB34)),BB34/BB33-1,"") -> 0.059852312 | BD34: =IF(ISNUMBER(BB34),BB34/MAX(BB$22:BB34)-1,"") -> -0.11861668 | BF34: 48.76 | BG34: =IF(AND(ISNUMBER(BF33),ISNUMBER(BF34)),BF34/BF33-1,"") -> 0.025446898 | BH34: =IF(ISNUMBER(BF34),BF34/MAX(BF$22:BF34)-1,"") -> -0.091315691 | BJ34: =BJ33*(1+BK34) -> 97.817108 | BK34: =$L$12*S34+$L$13*W34+$L$14*AA34+$L$15*AE34+$L$16*AI34+$L$17*AM34+$L$18*AQ34+$L$19*AU34+$L$20*AY34 -> 0.013965806 | BL34: =IF(ISNUMBER(BJ34),BJ34/MAX(BJ$22:BJ34)-1,"") -> -0.073263987 | BN34: =BN33*(1+BO34) -> 96.942271 | BO34: =$L$35*W34+$L$36*S34+$L$37*AA34+$L$38*AE34+$L$39*AQ34+$L$40*AY34+$L$41*BC34+$L$42*BG34+$L$43*AI34 -> 0.014362558 | BP34: =IF(ISNUMBER(BN34),BN34/MAX(BN$22:BN34)-1,"") -> -0.087832289 | BR34: =BR33*(1+BS34) -> 97.416804 | BS34: =$L$58*W34+$L$59*AE34+$L$60*S34+$L$61*AQ34+$L$62*BC34+$L$63*AA34+$L$64*BG34+$L$65*AY34+$L$66*AI34 -> 0.02434608 | BT34: =IF(ISNUMBER(BR34),BR34/MAX(BR$22:BR34)-1,"") -> -0.087218588
B35: SPY.AX | C35: SPDR S&P 500 ETF Trust | D35: United States | E35: Equities | F35: Growth | G35: 0.0009 | H35: =X15 -> 0.12566444 | I35: =H35-G35 -> 0.12476444 | J35: =X16 -> 0.13229761 | K35: =X18 -> -0.16545205 | L35: 0.29 | M35: =J35*L35 -> 0.038366307 | N35: =K35*L35 -> -0.047981095 | O35: =I35*L35 -> 0.036181687 | Q35: 44804 | R35: 100.39 | S35: =IF(AND(ISNUMBER(R34),ISNUMBER(R35)),R35/R34-1,"") -> 0.00079752766 | T35: =IF(ISNUMBER(R35),R35/MAX(R$22:R35)-1,"") -> 0 | V35: 581.71 | W35: =IF(AND(ISNUMBER(V34),ISNUMBER(V35)),V35/V34-1,"") -> -0.0029822607 | X35: =IF(ISNUMBER(V35),V35/MAX(V$22:V35)-1,"") -> -0.11311175 | Z35: 25.8 | AA35: =IF(AND(ISNUMBER(Z34),ISNUMBER(Z35)),Z35/Z34-1,"") -> -0.028248588 | AB35: =IF(ISNUMBER(Z35),Z35/MAX(Z$22:Z35)-1,"") -> -0.16934965 | AD35: 14.14 | AE35: =IF(AND(ISNUMBER(AD34),ISNUMBER(AD35)),AD35/AD34-1,"") -> 0.014347202 | AF35: =IF(ISNUMBER(AD35),AD35/MAX(AD$22:AD35)-1,"") -> -0.14613527 | AH35: 23.23 | AI35: =IF(AND(ISNUMBER(AH34),ISNUMBER(AH35)),AH35/AH34-1,"") -> -0.0068405301 | AJ35: =IF(ISNUMBER(AH35),AH35/MAX(AH$22:AH35)-1,"") -> -0.0639481 | AL35: 43.41 | AM35: =IF(AND(ISNUMBER(AL34),ISNUMBER(AL35)),AL35/AL34-1,"") -> -0.030160858 | AN35: =IF(ISNUMBER(AL35),AL35/MAX(AL$22:AL35)-1,"") -> -0.13006012 | AP35: 66.08 | AQ35: =IF(AND(ISNUMBER(AP34),ISNUMBER(AP35)),AP35/AP34-1,"") -> 0.011635028 | AR35: =IF(ISNUMBER(AP35),AP35/MAX(AP$22:AP35)-1,"") -> 0 | AT35: 50.16 | AU35: =IF(AND(ISNUMBER(AT34),ISNUMBER(AT35)),AT35/AT34-1,"") -> 0.00059844405 | AV35: =IF(ISNUMBER(AT35),AT35/MAX(AT$22:AT35)-1,"") -> 0 | AX35: 292.1 | AY35: =IF(AND(ISNUMBER(AX34),ISNUMBER(AX35)),AX35/AX34-1,"") -> 0.0002397014 | AZ35: =IF(ISNUMBER(AX35),AX35/MAX(AX$22:AX35)-1,"") -> -0.12534435 | BB35: 54.67 | BC35: =IF(AND(ISNUMBER(BB34),ISNUMBER(BB35)),BB35/BB34-1,"") -> 0.0023835717 | BD35: =IF(ISNUMBER(BB35),BB35/MAX(BB$22:BB35)-1,"") -> -0.11651584 | BF35: 48.04 | BG35: =IF(AND(ISNUMBER(BF34),ISNUMBER(BF35)),BF35/BF34-1,"") -> -0.014766202 | BH35: =IF(ISNUMBER(BF35),BF35/MAX(BF$22:BF35)-1,"") -> -0.10473351 | BJ35: =BJ34*(1+BK35) -> 97.296154 | BK35: =$L$12*S35+$L$13*W35+$L$14*AA35+$L$15*AE35+$L$16*AI35+$L$17*AM35+$L$18*AQ35+$L$19*AU35+$L$20*AY35 -> -0.0053257869 | BL35: =IF(ISNUMBER(BJ35),BJ35/MAX(BJ$22:BJ35)-1,"") -> -0.078199586 | BN35: =BN34*(1+BO35) -> 96.558789 | BO35: =$L$35*W35+$L$36*S35+$L$37*AA35+$L$38*AE35+$L$39*AQ35+$L$40*AY35+$L$41*BC35+$L$42*BG35+$L$43*AI35 -> -0.0039557804 | BP35: =IF(ISNUMBER(BN35),BN35/MAX(BN$22:BN35)-1,"") -> -0.091440624 | BR35: =BR34*(1+BS35) -> 97.493696 | BS35: =$L$58*W35+$L$59*AE35+$L$60*S35+$L$61*AQ35+$L$62*BC35+$L$63*AA35+$L$64*BG35+$L$65*AY35+$L$66*AI35 -> 0.00078931446 | BT35: =IF(ISNUMBER(BR35),BR35/MAX(BR$22:BR35)-1,"") -> -0.086498116
B36: BILL.AX | C36: iShares Core Cash ETF | D36: Australia | E36: Cash | F36: Defensive | G36: 0.0007 | H36: =T15 -> 0.00086268851 | I36: =H36-G36 -> 0.00016268851 | J36: =T16 -> 0.0014583498 | K36: =T18 -> -0.0015873016 | L36: 0.21 | M36: =J36*L36 -> 0.00030625345 | N36: =K36*L36 -> -0.00033333333 | O36: =I36*L36 -> 3.4164587e-05 | Q36: 44834 | R36: 100.37 | S36: =IF(AND(ISNUMBER(R35),ISNUMBER(R36)),R36/R35-1,"") -> -0.00019922303 | T36: =IF(ISNUMBER(R36),R36/MAX(R$22:R36)-1,"") -> -0.00019922303 | V36: 558.6 | W36: =IF(AND(ISNUMBER(V35),ISNUMBER(V36)),V36/V35-1,"") -> -0.039727699 | X36: =IF(ISNUMBER(V36),V36/MAX(V$22:V36)-1,"") -> -0.14834578 | Z36: 24.76 | AA36: =IF(AND(ISNUMBER(Z35),ISNUMBER(Z36)),Z36/Z35-1,"") -> -0.040310078 | AB36: =IF(ISNUMBER(Z36),Z36/MAX(Z$22:Z36)-1,"") -> -0.20283323 | AD36: 13 | AE36: =IF(AND(ISNUMBER(AD35),ISNUMBER(AD36)),AD36/AD35-1,"") -> -0.080622348 | AF36: =IF(ISNUMBER(AD36),AD36/MAX(AD$22:AD36)-1,"") -> -0.21497585 | AH36: 23.84 | AI36: =IF(AND(ISNUMBER(AH35),ISNUMBER(AH36)),AH36/AH35-1,"") -> 0.026259148 | AJ36: =IF(ISNUMBER(AH36),AH36/MAX(AH$22:AH36)-1,"") -> -0.039368175 | AL36: 41.7 | AM36: =IF(AND(ISNUMBER(AL35),ISNUMBER(AL36)),AL36/AL35-1,"") -> -0.039391845 | AN36: =IF(ISNUMBER(AL36),AL36/MAX(AL$22:AL36)-1,"") -> -0.16432866 | AP36: 61.81 | AQ36: =IF(AND(ISNUMBER(AP35),ISNUMBER(AP36)),AP36/AP35-1,"") -> -0.064618644 | AR36: =IF(ISNUMBER(AP36),AP36/MAX(AP$22:AP36)-1,"") -> -0.064618644 | AT36: 50.17 | AU36: =IF(AND(ISNUMBER(AT35),ISNUMBER(AT36)),AT36/AT35-1,"") -> 0.00019936204 | AV36: =IF(ISNUMBER(AT36),AT36/MAX(AT$22:AT36)-1,"") -> 0 | AX36: 280.43 | AY36: =IF(AND(ISNUMBER(AX35),ISNUMBER(AX36)),AX36/AX35-1,"") -> -0.039952071 | AZ36: =IF(ISNUMBER(AX36),AX36/MAX(AX$22:AX36)-1,"") -> -0.16028866 | BB36: 50.82 | BC36: =IF(AND(ISNUMBER(BB35),ISNUMBER(BB36)),BB36/BB35-1,"") -> -0.070422535 | BD36: =IF(ISNUMBER(BB36),BB36/MAX(BB$22:BB36)-1,"") -> -0.17873303 | BF36: 47.4 | BG36: =IF(AND(ISNUMBER(BF35),ISNUMBER(BF36)),BF36/BF35-1,"") -> -0.013322231 | BH36: =IF(ISNUMBER(BF36),BF36/MAX(BF$22:BF36)-1,"") -> -0.11666045 | BJ36: =BJ35*(1+BK36) -> 94.6859 | BK36: =$L$12*S36+$L$13*W36+$L$14*AA36+$L$15*AE36+$L$16*AI36+$L$17*AM36+$L$18*AQ36+$L$19*AU36+$L$20*AY36 -> -0.026827927 | BL36: =IF(ISNUMBER(BJ36),BJ36/MAX(BJ$22:BJ36)-1,"") -> -0.10292958 | BN36: =BN35*(1+BO36) -> 93.281587 | BO36: =$L$35*W36+$L$36*S36+$L$37*AA36+$L$38*AE36+$L$39*AQ36+$L$40*AY36+$L$41*BC36+$L$42*BG36+$L$43*AI36 -> -0.033939965 | BP36: =IF(ISNUMBER(BN36),BN36/MAX(BN$22:BN36)-1,"") -> -0.1222771 | BR36: =BR35*(1+BS36) -> 93.046061 | BS36: =$L$58*W36+$L$59*AE36+$L$60*S36+$L$61*AQ36+$L$62*BC36+$L$63*AA36+$L$64*BG36+$L$65*AY36+$L$66*AI36 -> -0.045619725 | BT36: =IF(ISNUMBER(BR36),BR36/MAX(BR$22:BR36)-1,"") -> -0.12817182
B37: ESGI.AX | C37: VanEck MSCI International Sustainable Equity ETF | D37: Global | E37: Equities | F37: Growth | G37: 0.0055 | H37: =AB15 -> 0.060929507 | I37: =H37-G37 -> 0.055429507 | J37: =AB16 -> 0.12936696 | K37: =AB18 -> -0.20283323 | L37: 0.19 | M37: =J37*L37 -> 0.024579723 | N37: =K37*L37 -> -0.038538313 | O37: =I37*L37 -> 0.010531606 | Q37: 44865 | R37: 100.48 | S37: =IF(AND(ISNUMBER(R36),ISNUMBER(R37)),R37/R36-1,"") -> 0.001095945 | T37: =IF(ISNUMBER(R37),R37/MAX(R$22:R37)-1,"") -> 0 | V37: 605 | W37: =IF(AND(ISNUMBER(V36),ISNUMBER(V37)),V37/V36-1,"") -> 0.083064805 | X37: =IF(ISNUMBER(V37),V37/MAX(V$22:V37)-1,"") -> -0.077603293 | Z37: 27.01 | AA37: =IF(AND(ISNUMBER(Z36),ISNUMBER(Z37)),Z37/Z36-1,"") -> 0.090872375 | AB37: =IF(ISNUMBER(Z37),Z37/MAX(Z$22:Z37)-1,"") -> -0.13039279 | AD37: 13.81 | AE37: =IF(AND(ISNUMBER(AD36),ISNUMBER(AD37)),AD37/AD36-1,"") -> 0.062307692 | AF37: =IF(ISNUMBER(AD37),AD37/MAX(AD$22:AD37)-1,"") -> -0.1660628 | AH37: 23.8 | AI37: =IF(AND(ISNUMBER(AH36),ISNUMBER(AH37)),AH37/AH36-1,"") -> -0.0016778523 | AJ37: =IF(ISNUMBER(AH37),AH37/MAX(AH$22:AH37)-1,"") -> -0.040979973 | AL37: 41.5 | AM37: =IF(AND(ISNUMBER(AL36),ISNUMBER(AL37)),AL37/AL36-1,"") -> -0.0047961631 | AN37: =IF(ISNUMBER(AL37),AL37/MAX(AL$22:AL37)-1,"") -> -0.16833667 | AP37: 63.43 | AQ37: =IF(AND(ISNUMBER(AP36),ISNUMBER(AP37)),AP37/AP36-1,"") -> 0.026209351 | AR37: =IF(ISNUMBER(AP37),AP37/MAX(AP$22:AP37)-1,"") -> -0.040102906 | AT37: 50.18 | AU37: =IF(AND(ISNUMBER(AT36),ISNUMBER(AT37)),AT37/AT36-1,"") -> 0.0001993223 | AV37: =IF(ISNUMBER(AT37),AT37/MAX(AT$22:AT37)-1,"") -> 0 | AX37: 303.98 | AY37: =IF(AND(ISNUMBER(AX36),ISNUMBER(AX37)),AX37/AX36-1,"") -> 0.083978176 | AZ37: =IF(ISNUMBER(AX37),AX37/MAX(AX$22:AX37)-1,"") -> -0.08977123 | BB37: 53.52 | BC37: =IF(AND(ISNUMBER(BB36),ISNUMBER(BB37)),BB37/BB36-1,"") -> 0.053128689 | BD37: =IF(ISNUMBER(BB37),BB37/MAX(BB$22:BB37)-1,"") -> -0.13510019 | BF37: 47.63 | BG37: =IF(AND(ISNUMBER(BF36),ISNUMBER(BF37)),BF37/BF36-1,"") -> 0.0048523207 | BH37: =IF(ISNUMBER(BF37),BF37/MAX(BF$22:BF37)-1,"") -> -0.11237421 | BJ37: =BJ36*(1+BK37) -> 99.056871 | BK37: =$L$12*S37+$L$13*W37+$L$14*AA37+$L$15*AE37+$L$16*AI37+$L$17*AM37+$L$18*AQ37+$L$19*AU37+$L$20*AY37 -> 0.046162843 | BL37: =IF(ISNUMBER(BJ37),BJ37/MAX(BJ$22:BJ37)-1,"") -> -0.061518259 | BN37: =BN36*(1+BO37) -> 98.328854 | BO37: =$L$35*W37+$L$36*S37+$L$37*AA37+$L$38*AE37+$L$39*AQ37+$L$40*AY37+$L$41*BC37+$L$42*BG37+$L$43*AI37 -> 0.054107861 | BP37: =IF(ISNUMBER(BN37),BN37/MAX(BN$22:BN37)-1,"") -> -0.074785388 | BR37: =BR36*(1+BS37) -> 98.059727 | BS37: =$L$58*W37+$L$59*AE37+$L$60*S37+$L$61*AQ37+$L$62*BC37+$L$63*AA37+$L$64*BG37+$L$65*AY37+$L$66*AI37 -> 0.053883701 | BT37: =IF(ISNUMBER(BR37),BR37/MAX(BR$22:BR37)-1,"") -> -0.081194493
B38: HJPN.AX | C38: BetaShares Japan ETF (Currency Hedged) | D38: Japan | E38: Equities | F38: Growth | G38: 0.0056 | H38: =AF15 -> 0.1556891 | I38: =H38-G38 -> 0.1500891 | J38: =AF16 -> 0.17112888 | K38: =AF18 -> -0.21497585 | L38: 0.1661 | M38: =J38*L38 -> 0.028424506 | N38: =K38*L38 -> -0.035707488 | O38: =I38*L38 -> 0.0249298 | Q38: 44895 | R38: 100.5 | S38: =IF(AND(ISNUMBER(R37),ISNUMBER(R38)),R38/R37-1,"") -> 0.00019904459 | T38: =IF(ISNUMBER(R38),R38/MAX(R$22:R38)-1,"") -> 0 | V38: 591.35 | W38: =IF(AND(ISNUMBER(V37),ISNUMBER(V38)),V38/V37-1,"") -> -0.022561983 | X38: =IF(ISNUMBER(V38),V38/MAX(V$22:V38)-1,"") -> -0.098414392 | Z38: 28.28 | AA38: =IF(AND(ISNUMBER(Z37),ISNUMBER(Z38)),Z38/Z37-1,"") -> 0.047019622 | AB38: =IF(ISNUMBER(Z38),Z38/MAX(Z$22:Z38)-1,"") -> -0.089504185 | AD38: 14.34 | AE38: =IF(AND(ISNUMBER(AD37),ISNUMBER(AD38)),AD38/AD37-1,"") -> 0.038377987 | AF38: =IF(ISNUMBER(AD38),AD38/MAX(AD$22:AD38)-1,"") -> -0.13405797 | AH38: 24.31 | AI38: =IF(AND(ISNUMBER(AH37),ISNUMBER(AH38)),AH38/AH37-1,"") -> 0.021428571 | AJ38: =IF(ISNUMBER(AH38),AH38/MAX(AH$22:AH38)-1,"") -> -0.020429544 | AL38: 42.29 | AM38: =IF(AND(ISNUMBER(AL37),ISNUMBER(AL38)),AL38/AL37-1,"") -> 0.019036145 | AN38: =IF(ISNUMBER(AL38),AL38/MAX(AL$22:AL38)-1,"") -> -0.15250501 | AP38: 64.54 | AQ38: =IF(AND(ISNUMBER(AP37),ISNUMBER(AP38)),AP38/AP37-1,"") -> 0.017499606 | AR38: =IF(ISNUMBER(AP38),AP38/MAX(AP$22:AP38)-1,"") -> -0.023305085 | AT38: 50.195 | AU38: =IF(AND(ISNUMBER(AT37),ISNUMBER(AT38)),AT38/AT37-1,"") -> 0.00029892387 | AV38: =IF(ISNUMBER(AT38),AT38/MAX(AT$22:AT38)-1,"") -> 0 | AX38: 296.2 | AY38: =IF(AND(ISNUMBER(AX37),ISNUMBER(AX38)),AX38/AX37-1,"") -> -0.025593789 | AZ38: =IF(ISNUMBER(AX38),AX38/MAX(AX$22:AX38)-1,"") -> -0.11306743 | BB38: 56.5 | BC38: =IF(AND(ISNUMBER(BB37),ISNUMBER(BB38)),BB38/BB37-1,"") -> 0.05568012 | BD38: =IF(ISNUMBER(BB38),BB38/MAX(BB$22:BB38)-1,"") -> -0.086942469 | BF38: 48.31 | BG38: =IF(AND(ISNUMBER(BF37),ISNUMBER(BF38)),BF38/BF37-1,"") -> 0.014276716 | BH38: =IF(ISNUMBER(BF38),BF38/MAX(BF$22:BF38)-1,"") -> -0.099701826 | BJ38: =BJ37*(1+BK38) -> 99.959797 | BK38: =$L$12*S38+$L$13*W38+$L$14*AA38+$L$15*AE38+$L$16*AI38+$L$17*AM38+$L$18*AQ38+$L$19*AU38+$L$20*AY38 -> 0.009115227 | BL38: =IF(ISNUMBER(BJ38),BJ38/MAX(BJ$22:BJ38)-1,"") -> -0.052963784 | BN38: =BN37*(1+BO38) -> 99.465367 | BO38: =$L$35*W38+$L$36*S38+$L$37*AA38+$L$38*AE38+$L$39*AQ38+$L$40*AY38+$L$41*BC38+$L$42*BG38+$L$43*AI38 -> 0.011558289 | BP38: =IF(ISNUMBER(BN38),BN38/MAX(BN$22:BN38)-1,"") -> -0.06409149 | BR38: =BR37*(1+BS38) -> 99.349887 | BS38: =$L$58*W38+$L$59*AE38+$L$60*S38+$L$61*AQ38+$L$62*BC38+$L$63*AA38+$L$64*BG38+$L$65*AY38+$L$66*AI38 -> 0.013156882 | BT38: =IF(ISNUMBER(BR38),BR38/MAX(BR$22:BR38)-1,"") -> -0.069105877
B39: VBLD.AX | C39: Vanguard Global Infrastructure Index ETF | D39: Global | E39: Infrastructure | F39: Growth | G39: 0.0047 | H39: =AR15 -> 0.04674658 | I39: =H39-G39 -> 0.04204658 | J39: =AR16 -> 0.10222536 | K39: =AR18 -> -0.11622276 | L39: 0.0339 | M39: =J39*L39 -> 0.0034654398 | N39: =K39*L39 -> -0.0039399516 | O39: =I39*L39 -> 0.0014253791 | Q39: 44925 | R39: 100.55 | S39: =IF(AND(ISNUMBER(R38),ISNUMBER(R39)),R39/R38-1,"") -> 0.00049751244 | T39: =IF(ISNUMBER(R39),R39/MAX(R$22:R39)-1,"") -> 0 | V39: 565 | W39: =IF(AND(ISNUMBER(V38),ISNUMBER(V39)),V39/V38-1,"") -> -0.04455906 | X39: =IF(ISNUMBER(V39),V39/MAX(V$22:V39)-1,"") -> -0.1385882 | Z39: 28.05 | AA39: =IF(AND(ISNUMBER(Z38),ISNUMBER(Z39)),Z39/Z38-1,"") -> -0.0081329562 | AB39: =IF(ISNUMBER(Z39),Z39/MAX(Z$22:Z39)-1,"") -> -0.096909208 | AD39: 13.24 | AE39: =IF(AND(ISNUMBER(AD38),ISNUMBER(AD39)),AD39/AD38-1,"") -> -0.076708508 | AF39: =IF(ISNUMBER(AD39),AD39/MAX(AD$22:AD39)-1,"") -> -0.20048309 | AH39: 24.89 | AI39: =IF(AND(ISNUMBER(AH38),ISNUMBER(AH39)),AH39/AH38-1,"") -> 0.023858494 | AJ39: =IF(ISNUMBER(AH39),AH39/MAX(AH$22:AH39)-1,"") -> 0 | AL39: 42.02 | AM39: =IF(AND(ISNUMBER(AL38),ISNUMBER(AL39)),AL39/AL38-1,"") -> -0.0063844881 | AN39: =IF(ISNUMBER(AL39),AL39/MAX(AL$22:AL39)-1,"") -> -0.15791583 | AP39: 63.66 | AQ39: =IF(AND(ISNUMBER(AP38),ISNUMBER(AP39)),AP39/AP38-1,"") -> -0.013634955 | AR39: =IF(ISNUMBER(AP39),AP39/MAX(AP$22:AP39)-1,"") -> -0.036622276 | AT39: 50.2 | AU39: =IF(AND(ISNUMBER(AT38),ISNUMBER(AT39)),AT39/AT38-1,"") -> 9.9611515e-05 | AV39: =IF(ISNUMBER(AT39),AT39/MAX(AT$22:AT39)-1,"") -> 0 | AX39: 282.68 | AY39: =IF(AND(ISNUMBER(AX38),ISNUMBER(AX39)),AX39/AX38-1,"") -> -0.045644835 | AZ39: =IF(ISNUMBER(AX39),AX39/MAX(AX$22:AX39)-1,"") -> -0.15355132 | BB39: 54.56 | BC39: =IF(AND(ISNUMBER(BB38),ISNUMBER(BB39)),BB39/BB38-1,"") -> -0.034336283 | BD39: =IF(ISNUMBER(BB39),BB39/MAX(BB$22:BB39)-1,"") -> -0.11829347 | BF39: 48.01 | BG39: =IF(AND(ISNUMBER(BF38),ISNUMBER(BF39)),BF39/BF38-1,"") -> -0.0062098944 | BH39: =IF(ISNUMBER(BF39),BF39/MAX(BF$22:BF39)-1,"") -> -0.10529258 | BJ39: =BJ38*(1+BK39) -> 98.010279 | BK39: =$L$12*S39+$L$13*W39+$L$14*AA39+$L$15*AE39+$L$16*AI39+$L$17*AM39+$L$18*AQ39+$L$19*AU39+$L$20*AY39 -> -0.019503016 | BL39: =IF(ISNUMBER(BJ39),BJ39/MAX(BJ$22:BJ39)-1,"") -> -0.071433847 | BN39: =BN38*(1+BO39) -> 96.827581 | BO39: =$L$35*W39+$L$36*S39+$L$37*AA39+$L$38*AE39+$L$39*AQ39+$L$40*AY39+$L$41*BC39+$L$42*BG39+$L$43*AI39 -> -0.02651965 | BP39: =IF(ISNUMBER(BN39),BN39/MAX(BN$22:BN39)-1,"") -> -0.088911457 | BR39: =BR38*(1+BS39) -> 96.005331 | BS39: =$L$58*W39+$L$59*AE39+$L$60*S39+$L$61*AQ39+$L$62*BC39+$L$63*AA39+$L$64*BG39+$L$65*AY39+$L$66*AI39 -> -0.033664419 | BT39: =IF(ISNUMBER(BR39),BR39/MAX(BR$22:BR39)-1,"") -> -0.10044389
B40: VTS.AX | C40: Vanguard US Total Market Shares Index ETF | D40: United States | E40: Equities | F40: Growth | G40: 0.0003 | H40: =AZ15 -> 0.11643426 | I40: =H40-G40 -> 0.11613426 | J40: =AZ16 -> 0.1337603 | K40: =AZ18 -> -0.18097976 | L40: 0.01 | M40: =J40*L40 -> 0.001337603 | N40: =K40*L40 -> -0.0018097976 | O40: =I40*L40 -> 0.0011613426 | Q40: 44957 | R40: 100.62 | S40: =IF(AND(ISNUMBER(R39),ISNUMBER(R40)),R40/R39-1,"") -> 0.00069617106 | T40: =IF(ISNUMBER(R40),R40/MAX(R$22:R40)-1,"") -> 0 | V40: 569.5 | W40: =IF(AND(ISNUMBER(V39),ISNUMBER(V40)),V40/V39-1,"") -> 0.0079646018 | X40: =IF(ISNUMBER(V40),V40/MAX(V$22:V40)-1,"") -> -0.1317274 | Z40: 28.3 | AA40: =IF(AND(ISNUMBER(Z39),ISNUMBER(Z40)),Z40/Z39-1,"") -> 0.008912656 | AB40: =IF(ISNUMBER(Z40),Z40/MAX(Z$22:Z40)-1,"") -> -0.08886027 | AD40: 14.02 | AE40: =IF(AND(ISNUMBER(AD39),ISNUMBER(AD40)),AD40/AD39-1,"") -> 0.058912387 | AF40: =IF(ISNUMBER(AD40),AD40/MAX(AD$22:AD40)-1,"") -> -0.15338164 | AH40: 25.31 | AI40: =IF(AND(ISNUMBER(AH39),ISNUMBER(AH40)),AH40/AH39-1,"") -> 0.016874247 | AJ40: =IF(ISNUMBER(AH40),AH40/MAX(AH$22:AH40)-1,"") -> 0 | AL40: 42.4 | AM40: =IF(AND(ISNUMBER(AL39),ISNUMBER(AL40)),AL40/AL39-1,"") -> 0.0090433127 | AN40: =IF(ISNUMBER(AL40),AL40/MAX(AL$22:AL40)-1,"") -> -0.1503006 | AP40: 60.73 | AQ40: =IF(AND(ISNUMBER(AP39),ISNUMBER(AP40)),AP40/AP39-1,"") -> -0.046025762 | AR40: =IF(ISNUMBER(AP40),AP40/MAX(AP$22:AP40)-1,"") -> -0.08096247 | AT40: 50.21 | AU40: =IF(AND(ISNUMBER(AT39),ISNUMBER(AT40)),AT40/AT39-1,"") -> 0.00019920319 | AV40: =IF(ISNUMBER(AT40),AT40/MAX(AT$22:AT40)-1,"") -> 0 | AX40: 285.76 | AY40: =IF(AND(ISNUMBER(AX39),ISNUMBER(AX40)),AX40/AX39-1,"") -> 0.010895712 | AZ40: =IF(ISNUMBER(AX40),AX40/MAX(AX$22:AX40)-1,"") -> -0.14432866 | BB40: 57.36 | BC40: =IF(AND(ISNUMBER(BB39),ISNUMBER(BB40)),BB40/BB39-1,"") -> 0.051319648 | BD40: =IF(ISNUMBER(BB40),BB40/MAX(BB$22:BB40)-1,"") -> -0.073044602 | BF40: 49.07 | BG40: =IF(AND(ISNUMBER(BF39),ISNUMBER(BF40)),BF40/BF39-1,"") -> 0.022078734 | BH40: =IF(ISNUMBER(BF40),BF40/MAX(BF$22:BF40)-1,"") -> -0.085538576 | BJ40: =BJ39*(1+BK40) -> 99.051282 | BK40: =$L$12*S40+$L$13*W40+$L$14*AA40+$L$15*AE40+$L$16*AI40+$L$17*AM40+$L$18*AQ40+$L$19*AU40+$L$20*AY40 -> 0.010621365 | BL40: =IF(ISNUMBER(BJ40),BJ40/MAX(BJ$22:BJ40)-1,"") -> -0.061571206 | BN40: =BN39*(1+BO40) -> 98.238096 | BO40: =$L$35*W40+$L$36*S40+$L$37*AA40+$L$38*AE40+$L$39*AQ40+$L$40*AY40+$L$41*BC40+$L$42*BG40+$L$43*AI40 -> 0.01456729 | BP40: =IF(ISNUMBER(BN40),BN40/MAX(BN$22:BN40)-1,"") -> -0.075639366 | BR40: =BR39*(1+BS40) -> 97.489466 | BS40: =$L$58*W40+$L$59*AE40+$L$60*S40+$L$61*AQ40+$L$62*BC40+$L$63*AA40+$L$64*BG40+$L$65*AY40+$L$66*AI40 -> 0.015458883 | BT40: =IF(ISNUMBER(BR40),BR40/MAX(BR$22:BR40)-1,"") -> -0.086537755
B41: VETH.AX | C41: Vanguard Ethically Conscious Australian Shares ETF | D41: Australia | E41: Equities | F41: Growth | G41: 0.0016 | H41: =BD15 -> 0.03979497 | I41: =H41-G41 -> 0.03819497 | J41: =BD16 -> 0.13625391 | K41: =BD18 -> -0.17873303 | L41: 0.01 | M41: =J41*L41 -> 0.0013625391 | N41: =K41*L41 -> -0.0017873303 | O41: =I41*L41 -> 0.0003819497 | Q41: 44985 | R41: 100.52 | S41: =IF(AND(ISNUMBER(R40),ISNUMBER(R41)),R41/R40-1,"") -> -0.0009938382 | T41: =IF(ISNUMBER(R41),R41/MAX(R$22:R41)-1,"") -> -0.0009938382 | V41: 592.19 | W41: =IF(AND(ISNUMBER(V40),ISNUMBER(V41)),V41/V40-1,"") -> 0.039841967 | X41: =IF(ISNUMBER(V41),V41/MAX(V$22:V41)-1,"") -> -0.097133709 | Z41: 28.72 | AA41: =IF(AND(ISNUMBER(Z40),ISNUMBER(Z41)),Z41/Z40-1,"") -> 0.014840989 | AB41: =IF(ISNUMBER(Z41),Z41/MAX(Z$22:Z41)-1,"") -> -0.075338055 | AD41: 14.05 | AE41: =IF(AND(ISNUMBER(AD40),ISNUMBER(AD41)),AD41/AD40-1,"") -> 0.0021398003 | AF41: =IF(ISNUMBER(AD41),AD41/MAX(AD$22:AD41)-1,"") -> -0.15157005 | AH41: 25.02 | AI41: =IF(AND(ISNUMBER(AH40),ISNUMBER(AH41)),AH41/AH40-1,"") -> -0.011457922 | AJ41: =IF(ISNUMBER(AH41),AH41/MAX(AH$22:AH41)-1,"") -> -0.011457922 | AL41: 41.71 | AM41: =IF(AND(ISNUMBER(AL40),ISNUMBER(AL41)),AL41/AL40-1,"") -> -0.016273585 | AN41: =IF(ISNUMBER(AL41),AL41/MAX(AL$22:AL41)-1,"") -> -0.16412826 | AP41: 61.57 | AQ41: =IF(AND(ISNUMBER(AP40),ISNUMBER(AP41)),AP41/AP40-1,"") -> 0.013831714 | AR41: =IF(ISNUMBER(AP41),AP41/MAX(AP$22:AP41)-1,"") -> -0.068250605 | AT41: 50.19 | AU41: =IF(AND(ISNUMBER(AT40),ISNUMBER(AT41)),AT41/AT40-1,"") -> -0.00039832703 | AV41: =IF(ISNUMBER(AT41),AT41/MAX(AT$22:AT41)-1,"") -> -0.00039832703 | AX41: 297.77 | AY41: =IF(AND(ISNUMBER(AX40),ISNUMBER(AX41)),AX41/AX40-1,"") -> 0.042028275 | AZ41: =IF(ISNUMBER(AX41),AX41/MAX(AX$22:AX41)-1,"") -> -0.10836627 | BB41: 56.12 | BC41: =IF(AND(ISNUMBER(BB40),ISNUMBER(BB41)),BB41/BB40-1,"") -> -0.021617852 | BD41: =IF(ISNUMBER(BB41),BB41/MAX(BB$22:BB41)-1,"") -> -0.093083387 | BF41: 48.63 | BG41: =IF(AND(ISNUMBER(BF40),ISNUMBER(BF41)),BF41/BF40-1,"") -> -0.0089667821 | BH41: =IF(ISNUMBER(BF41),BF41/MAX(BF$22:BF41)-1,"") -> -0.093738353 | BJ41: =BJ40*(1+BK41) -> 100.29321 | BK41: =$L$12*S41+$L$13*W41+$L$14*AA41+$L$15*AE41+$L$16*AI41+$L$17*AM41+$L$18*AQ41+$L$19*AU41+$L$20*AY41 -> 0.012538225 | BL41: =IF(ISNUMBER(BJ41),BJ41/MAX(BJ$22:BJ41)-1,"") -> -0.049804974 | BN41: =BN40*(1+BO41) -> 99.631836 | BO41: =$L$35*W41+$L$36*S41+$L$37*AA41+$L$38*AE41+$L$39*AQ41+$L$40*AY41+$L$41*BC41+$L$42*BG41+$L$43*AI41 -> 0.014187371 | BP41: =IF(ISNUMBER(BN41),BN41/MAX(BN$22:BN41)-1,"") -> -0.062525119 | BR41: =BR40*(1+BS41) -> 98.706421 | BS41: =$L$58*W41+$L$59*AE41+$L$60*S41+$L$61*AQ41+$L$62*BC41+$L$63*AA41+$L$64*BG41+$L$65*AY41+$L$66*AI41 -> 0.012482937 | BT41: =IF(ISNUMBER(BR41),BR41/MAX(BR$22:BR41)-1,"") -> -0.075135063
B42: VACF.AX | C42: Vanguard Australia Corporate Fixed Interest Index ETF | D42: Australia | E42: Bonds | F42: Defensive | G42: 0.002 | H42: =BH15 -> -0.0089862279 | I42: =H42-G42 -> -0.010986228 | J42: =BH16 -> 0.04180311 | K42: =BH18 -> -0.11666045 | L42: 0.01 | M42: =J42*L42 -> 0.0004180311 | N42: =K42*L42 -> -0.0011666045 | O42: =I42*L42 -> -0.00010986228 | Q42: 45016 | R42: 100.59 | S42: =IF(AND(ISNUMBER(R41),ISNUMBER(R42)),R42/R41-1,"") -> 0.00069637883 | T42: =IF(ISNUMBER(R42),R42/MAX(R$22:R42)-1,"") -> -0.00029815146 | V42: 602.51 | W42: =IF(AND(ISNUMBER(V41),ISNUMBER(V42)),V42/V41-1,"") -> 0.017426839 | X42: =IF(ISNUMBER(V42),V42/MAX(V$22:V42)-1,"") -> -0.081399604 | Z42: 29.36 | AA42: =IF(AND(ISNUMBER(Z41),ISNUMBER(Z42)),Z42/Z41-1,"") -> 0.022284123 | AB42: =IF(ISNUMBER(Z42),Z42/MAX(Z$22:Z42)-1,"") -> -0.054732775 | AD42: 14.8 | AE42: =IF(AND(ISNUMBER(AD41),ISNUMBER(AD42)),AD42/AD41-1,"") -> 0.053380783 | AF42: =IF(ISNUMBER(AD42),AD42/MAX(AD$22:AD42)-1,"") -> -0.10628019 | AH42: 27.33 | AI42: =IF(AND(ISNUMBER(AH41),ISNUMBER(AH42)),AH42/AH41-1,"") -> 0.092326139 | AJ42: =IF(ISNUMBER(AH42),AH42/MAX(AH$22:AH42)-1,"") -> 0 | AL42: 42.45 | AM42: =IF(AND(ISNUMBER(AL41),ISNUMBER(AL42)),AL42/AL41-1,"") -> 0.017741549 | AN42: =IF(ISNUMBER(AL42),AL42/MAX(AL$22:AL42)-1,"") -> -0.1492986 | AP42: 62.37 | AQ42: =IF(AND(ISNUMBER(AP41),ISNUMBER(AP42)),AP42/AP41-1,"") -> 0.012993341 | AR42: =IF(ISNUMBER(AP42),AP42/MAX(AP$22:AP42)-1,"") -> -0.056144068 | AT42: 50.22 | AU42: =IF(AND(ISNUMBER(AT41),ISNUMBER(AT42)),AT42/AT41-1,"") -> 0.00059772863 | AV42: =IF(ISNUMBER(AT42),AT42/MAX(AT$22:AT42)-1,"") -> 0 | AX42: 300.33 | AY42: =IF(AND(ISNUMBER(AX41),ISNUMBER(AX42)),AX42/AX41-1,"") -> 0.0085972395 | AZ42: =IF(ISNUMBER(AX42),AX42/MAX(AX$22:AX42)-1,"") -> -0.10070068 | BB42: 55.5 | BC42: =IF(AND(ISNUMBER(BB41),ISNUMBER(BB42)),BB42/BB41-1,"") -> -0.011047755 | BD42: =IF(ISNUMBER(BB42),BB42/MAX(BB$22:BB42)-1,"") -> -0.10310278 | BF42: 49.73 | BG42: =IF(AND(ISNUMBER(BF41),ISNUMBER(BF42)),BF42/BF41-1,"") -> 0.022619782 | BH42: =IF(ISNUMBER(BF42),BF42/MAX(BF$22:BF42)-1,"") -> -0.073238912 | BJ42: =BJ41*(1+BK42) -> 103.22326 | BK42: =$L$12*S42+$L$13*W42+$L$14*AA42+$L$15*AE42+$L$16*AI42+$L$17*AM42+$L$18*AQ42+$L$19*AU42+$L$20*AY42 -> 0.029214835 | BL42: =IF(ISNUMBER(BJ42),BJ42/MAX(BJ$22:BJ42)-1,"") -> -0.022045184 | BN42: =BN41*(1+BO42) -> 102.25502 | BO42: =$L$35*W42+$L$36*S42+$L$37*AA42+$L$38*AE42+$L$39*AQ42+$L$40*AY42+$L$41*BC42+$L$42*BG42+$L$43*AI42 -> 0.026328812 | BP42: =IF(ISNUMBER(BN42),BN42/MAX(BN$22:BN42)-1,"") -> -0.037842518 | BR42: =BR41*(1+BS42) -> 100.55779 | BS42: =$L$58*W42+$L$59*AE42+$L$60*S42+$L$61*AQ42+$L$62*BC42+$L$63*AA42+$L$64*BG42+$L$65*AY42+$L$66*AI42 -> 0.018756304 | BT42: =IF(ISNUMBER(BR42),BR42/MAX(BR$22:BR42)-1,"") -> -0.057788015 | BV42: Scholarship Projection - 70/30 Strategic
B43: GOLD.AX | C43: Global X Physical Gold | D43: Global | E43: Alternatives (Gold) | F43: Defensive | G43: 0.004 | H43: =AJ15 -> 0.18941503 | I43: =H43-G43 -> 0.18541503 | J43: =AJ16 -> 0.1578302 | K43: =AJ18 -> -0.22099853 | L43: 0.08 | M43: =J43*L43 -> 0.012626416 | N43: =K43*L43 -> -0.017679883 | O43: =I43*L43 -> 0.014833202 | Q43: 45044 | R43: 100.58 | S43: =IF(AND(ISNUMBER(R42),ISNUMBER(R43)),R43/R42-1,"") -> -9.9413461e-05 | T43: =IF(ISNUMBER(R43),R43/MAX(R$22:R43)-1,"") -> -0.00039753528 | V43: 622.87 | W43: =IF(AND(ISNUMBER(V42),ISNUMBER(V43)),V43/V42-1,"") -> 0.03379197 | X43: =IF(ISNUMBER(V43),V43/MAX(V$22:V43)-1,"") -> -0.050358286 | Z43: 30.41 | AA43: =IF(AND(ISNUMBER(Z42),ISNUMBER(Z43)),Z43/Z42-1,"") -> 0.035762943 | AB43: =IF(ISNUMBER(Z43),Z43/MAX(Z$22:Z43)-1,"") -> -0.020927238 | AD43: 14.92 | AE43: =IF(AND(ISNUMBER(AD42),ISNUMBER(AD43)),AD43/AD42-1,"") -> 0.0081081081 | AF43: =IF(ISNUMBER(AD43),AD43/MAX(AD$22:AD43)-1,"") -> -0.099033816 | AH43: 27.8 | AI43: =IF(AND(ISNUMBER(AH42),ISNUMBER(AH43)),AH43/AH42-1,"") -> 0.017197219 | AJ43: =IF(ISNUMBER(AH43),AH43/MAX(AH$22:AH43)-1,"") -> 0 | AL43: 42.35 | AM43: =IF(AND(ISNUMBER(AL42),ISNUMBER(AL43)),AL43/AL42-1,"") -> -0.0023557126 | AN43: =IF(ISNUMBER(AL43),AL43/MAX(AL$22:AL43)-1,"") -> -0.15130261 | AP43: 64.1 | AQ43: =IF(AND(ISNUMBER(AP42),ISNUMBER(AP43)),AP43/AP42-1,"") -> 0.027737694 | AR43: =IF(ISNUMBER(AP43),AP43/MAX(AP$22:AP43)-1,"") -> -0.02996368 | AT43: 50.21 | AU43: =IF(AND(ISNUMBER(AT42),ISNUMBER(AT43)),AT43/AT42-1,"") -> -0.00019912386 | AV43: =IF(ISNUMBER(AT43),AT43/MAX(AT$22:AT43)-1,"") -> -0.00019912386 | AX43: 308.99 | AY43: =IF(AND(ISNUMBER(AX42),ISNUMBER(AX43)),AX43/AX42-1,"") -> 0.028834948 | AZ43: =IF(ISNUMBER(AX43),AX43/MAX(AX$22:AX43)-1,"") -> -0.074769433 | BB43: 56.91 | BC43: =IF(AND(ISNUMBER(BB42),ISNUMBER(BB43)),BB43/BB42-1,"") -> 0.025405405 | BD43: =IF(ISNUMBER(BB43),BB43/MAX(BB$22:BB43)-1,"") -> -0.080316742 | BF43: 49.64 | BG43: =IF(AND(ISNUMBER(BF42),ISNUMBER(BF43)),BF43/BF42-1,"") -> -0.0018097728 | BH43: =IF(ISNUMBER(BF43),BF43/MAX(BF$22:BF43)-1,"") -> -0.074916139 | BJ43: =BJ42*(1+BK43) -> 105.3031 | BK43: =$L$12*S43+$L$13*W43+$L$14*AA43+$L$15*AE43+$L$16*AI43+$L$17*AM43+$L$18*AQ43+$L$19*AU43+$L$20*AY43 -> 0.020148949 | BL43: =IF(ISNUMBER(BJ43),BJ43/MAX(BJ$22:BJ43)-1,"") -> -0.0023404216 | BN43: =BN42*(1+BO43) -> 104.37793 | BO43: =$L$35*W43+$L$36*S43+$L$37*AA43+$L$38*AE43+$L$39*AQ43+$L$40*AY43+$L$41*BC43+$L$42*BG43+$L$43*AI43 -> 0.020760902 | BP43: =IF(ISNUMBER(BN43),BN43/MAX(BN$22:BN43)-1,"") -> -0.017867261 | BR43: =BR42*(1+BS43) -> 102.65329 | BS43: =$L$58*W43+$L$59*AE43+$L$60*S43+$L$61*AQ43+$L$62*BC43+$L$63*AA43+$L$64*BG43+$L$65*AY43+$L$66*AI43 -> 0.020838762 | BT43: =IF(ISNUMBER(BR43),BR43/MAX(BR$22:BR43)-1,"") -> -0.038153484 | BV43: Starting Value (A$) | BY43: 100000000
L44: =SUM(L35:L43) -> 1 | M44: =SUM(M35:M43) -> 0.11088682 | N44: =SUM(N35:N43) -> -0.1489438 | O44: =SUM(O35:O43) -> 0.089369269 | Q44: 45077 | R44: 100.63 | S44: =IF(AND(ISNUMBER(R43),ISNUMBER(R44)),R44/R43-1,"") -> 0.00049711672 | T44: =IF(ISNUMBER(R44),R44/MAX(R$22:R44)-1,"") -> 0 | V44: 645.4 | W44: =IF(AND(ISNUMBER(V43),ISNUMBER(V44)),V44/V43-1,"") -> 0.036171272 | X44: =IF(ISNUMBER(V44),V44/MAX(V$22:V44)-1,"") -> -0.016008538 | Z44: 29.83 | AA44: =IF(AND(ISNUMBER(Z43),ISNUMBER(Z44)),Z44/Z43-1,"") -> -0.019072673 | AB44: =IF(ISNUMBER(Z44),Z44/MAX(Z$22:Z44)-1,"") -> -0.039600773 | AD44: 15.96 | AE44: =IF(AND(ISNUMBER(AD43),ISNUMBER(AD44)),AD44/AD43-1,"") -> 0.069705094 | AF44: =IF(ISNUMBER(AD44),AD44/MAX(AD$22:AD44)-1,"") -> -0.036231884 | AH44: 28.03 | AI44: =IF(AND(ISNUMBER(AH43),ISNUMBER(AH44)),AH44/AH43-1,"") -> 0.0082733813 | AJ44: =IF(ISNUMBER(AH44),AH44/MAX(AH$22:AH44)-1,"") -> 0 | AL44: 42.23 | AM44: =IF(AND(ISNUMBER(AL43),ISNUMBER(AL44)),AL44/AL43-1,"") -> -0.0028335301 | AN44: =IF(ISNUMBER(AL44),AL44/MAX(AL$22:AL44)-1,"") -> -0.15370741 | AP44: 61.7 | AQ44: =IF(AND(ISNUMBER(AP43),ISNUMBER(AP44)),AP44/AP43-1,"") -> -0.037441498 | AR44: =IF(ISNUMBER(AP44),AP44/MAX(AP$22:AP44)-1,"") -> -0.066283293 | AT44: 50.25 | AU44: =IF(AND(ISNUMBER(AT43),ISNUMBER(AT44)),AT44/AT43-1,"") -> 0.00079665405 | AV44: =IF(ISNUMBER(AT44),AT44/MAX(AT$22:AT44)-1,"") -> 0 | AX44: 319.84 | AY44: =IF(AND(ISNUMBER(AX43),ISNUMBER(AX44)),AX44/AX43-1,"") -> 0.035114405 | AZ44: =IF(ISNUMBER(AX44),AX44/MAX(AX$22:AX44)-1,"") -> -0.042280513 | BB44: 55.46 | BC44: =IF(AND(ISNUMBER(BB43),ISNUMBER(BB44)),BB44/BB43-1,"") -> -0.025478826 | BD44: =IF(ISNUMBER(BB44),BB44/MAX(BB$22:BB44)-1,"") -> -0.10374919 | BF44: 49.5 | BG44: =IF(AND(ISNUMBER(BF43),ISNUMBER(BF44)),BF44/BF43-1,"") -> -0.0028203062 | BH44: =IF(ISNUMBER(BF44),BF44/MAX(BF$22:BF44)-1,"") -> -0.077525158 | BJ44: =BJ43*(1+BK44) -> 106.81886 | BK44: =$L$12*S44+$L$13*W44+$L$14*AA44+$L$15*AE44+$L$16*AI44+$L$17*AM44+$L$18*AQ44+$L$19*AU44+$L$20*AY44 -> 0.014394225 | BL44: =IF(ISNUMBER(BJ44),BJ44/MAX(BJ$22:BJ44)-1,"") -> 0 | BN44: =BN43*(1+BO44) -> 106.25768 | BO44: =$L$35*W44+$L$36*S44+$L$37*AA44+$L$38*AE44+$L$39*AQ44+$L$40*AY44+$L$41*BC44+$L$42*BG44+$L$43*AI44 -> 0.018009028 | BP44: =IF(ISNUMBER(BN44),BN44/MAX(BN$22:BN44)-1,"") -> -0.00018000562 | BR44: =BR43*(1+BS44) -> 104.24826 | BS44: =$L$58*W44+$L$59*AE44+$L$60*S44+$L$61*AQ44+$L$62*BC44+$L$63*AA44+$L$64*BG44+$L$65*AY44+$L$66*AI44 -> 0.015537443 | BT44: =IF(ISNUMBER(BR44),BR44/MAX(BR$22:BR44)-1,"") -> -0.023208849 | BV44: Expected Return (70/30, net of MER) | BY44: =O44 -> 0.089369269
L45: Actual portfolio | M45: =BP16 -> 0.081030196 | N45: =BP18 -> -0.1222771 | O45: =BP15-SUMPRODUCT(G35:G43,L35:L43) -> 0.089369269 | Q45: 45107 | R45: 100.6 | S45: =IF(AND(ISNUMBER(R44),ISNUMBER(R45)),R45/R44-1,"") -> -0.00029812183 | T45: =IF(ISNUMBER(R45),R45/MAX(R$22:R45)-1,"") -> -0.00029812183 | V45: 662.05 | W45: =IF(AND(ISNUMBER(V44),ISNUMBER(V45)),V45/V44-1,"") -> 0.025797955 | X45: =IF(ISNUMBER(V45),V45/MAX(V$22:V45)-1,"") -> 0 | Z45: 30.38 | AA45: =IF(AND(ISNUMBER(Z44),ISNUMBER(Z45)),Z45/Z44-1,"") -> 0.018437814 | AB45: =IF(ISNUMBER(Z45),Z45/MAX(Z$22:Z45)-1,"") -> -0.02189311 | AD45: 17.21 | AE45: =IF(AND(ISNUMBER(AD44),ISNUMBER(AD45)),AD45/AD44-1,"") -> 0.078320802 | AF45: =IF(ISNUMBER(AD45),AD45/MAX(AD$22:AD45)-1,"") -> 0 | AH45: 26.62 | AI45: =IF(AND(ISNUMBER(AH44),ISNUMBER(AH45)),AH45/AH44-1,"") -> -0.050303247 | AJ45: =IF(ISNUMBER(AH45),AH45/MAX(AH$22:AH45)-1,"") -> -0.050303247 | AL45: 42.14 | AM45: =IF(AND(ISNUMBER(AL44),ISNUMBER(AL45)),AL45/AL44-1,"") -> -0.0021311864 | AN45: =IF(ISNUMBER(AL45),AL45/MAX(AL$22:AL45)-1,"") -> -0.15551102 | AP45: 62.27 | AQ45: =IF(AND(ISNUMBER(AP44),ISNUMBER(AP45)),AP45/AP44-1,"") -> 0.0092382496 | AR45: =IF(ISNUMBER(AP45),AP45/MAX(AP$22:AP45)-1,"") -> -0.057657385 | AT45: 50.23 | AU45: =IF(AND(ISNUMBER(AT44),ISNUMBER(AT45)),AT45/AT44-1,"") -> -0.00039800995 | AV45: =IF(ISNUMBER(AT45),AT45/MAX(AT$22:AT45)-1,"") -> -0.00039800995 | AX45: 329.34 | AY45: =IF(AND(ISNUMBER(AX44),ISNUMBER(AX45)),AX45/AX44-1,"") -> 0.029702351 | AZ45: =IF(ISNUMBER(AX45),AX45/MAX(AX$22:AX45)-1,"") -> -0.013833992 | BB45: 55.81 | BC45: =IF(AND(ISNUMBER(BB44),ISNUMBER(BB45)),BB45/BB44-1,"") -> 0.0063108547 | BD45: =IF(ISNUMBER(BB45),BB45/MAX(BB$22:BB45)-1,"") -> -0.098093083 | BF45: 48.78 | BG45: =IF(AND(ISNUMBER(BF44),ISNUMBER(BF45)),BF45/BF44-1,"") -> -0.014545455 | BH45: =IF(ISNUMBER(BF45),BF45/MAX(BF$22:BF45)-1,"") -> -0.090942974 | BJ45: =BJ44*(1+BK45) -> 108.01354 | BK45: =$L$12*S45+$L$13*W45+$L$14*AA45+$L$15*AE45+$L$16*AI45+$L$17*AM45+$L$18*AQ45+$L$19*AU45+$L$20*AY45 -> 0.011184234 | BL45: =IF(ISNUMBER(BJ45),BJ45/MAX(BJ$22:BJ45)-1,"") -> 0 | BN45: =BN44*(1+BO45) -> 108.42902 | BO45: =$L$35*W45+$L$36*S45+$L$37*AA45+$L$38*AE45+$L$39*AQ45+$L$40*AY45+$L$41*BC45+$L$42*BG45+$L$43*AI45 -> 0.020434666 | BP45: =IF(ISNUMBER(BN45),BN45/MAX(BN$22:BN45)-1,"") -> 0 | BR45: =BR44*(1+BS45) -> 106.88496 | BS45: =$L$58*W45+$L$59*AE45+$L$60*S45+$L$61*AQ45+$L$62*BC45+$L$63*AA45+$L$64*BG45+$L$65*AY45+$L$66*AI45 -> 0.025292497 | BT45: =IF(ISNUMBER(BR45),BR45/MAX(BR$22:BR45)-1,"") -> 0 | BV45: Max Drawdown (70/30 Total Drawdown) | BY45: =N44 -> -0.1489438
Q46: 45138 | R46: 100.72 | S46: =IF(AND(ISNUMBER(R45),ISNUMBER(R46)),R46/R45-1,"") -> 0.0011928429 | T46: =IF(ISNUMBER(R46),R46/MAX(R$22:R46)-1,"") -> 0 | V46: 683 | W46: =IF(AND(ISNUMBER(V45),ISNUMBER(V46)),V46/V45-1,"") -> 0.031644136 | X46: =IF(ISNUMBER(V46),V46/MAX(V$22:V46)-1,"") -> 0 | Z46: 30.38 | AA46: =IF(AND(ISNUMBER(Z45),ISNUMBER(Z46)),Z46/Z45-1,"") -> 0 | AB46: =IF(ISNUMBER(Z46),Z46/MAX(Z$22:Z46)-1,"") -> -0.02189311 | AD46: 16.83 | AE46: =IF(AND(ISNUMBER(AD45),ISNUMBER(AD46)),AD46/AD45-1,"") -> -0.022080186 | AF46: =IF(ISNUMBER(AD46),AD46/MAX(AD$22:AD46)-1,"") -> -0.022080186 | AH46: 27.07 | AI46: =IF(AND(ISNUMBER(AH45),ISNUMBER(AH46)),AH46/AH45-1,"") -> 0.016904583 | AJ46: =IF(ISNUMBER(AH46),AH46/MAX(AH$22:AH46)-1,"") -> -0.034249019 | AL46: 41.76 | AM46: =IF(AND(ISNUMBER(AL45),ISNUMBER(AL46)),AL46/AL45-1,"") -> -0.0090175605 | AN46: =IF(ISNUMBER(AL46),AL46/MAX(AL$22:AL46)-1,"") -> -0.16312625 | AP46: 62.9 | AQ46: =IF(AND(ISNUMBER(AP45),ISNUMBER(AP46)),AP46/AP45-1,"") -> 0.010117231 | AR46: =IF(ISNUMBER(AP46),AP46/MAX(AP$22:AP46)-1,"") -> -0.048123487 | AT46: 50.25 | AU46: =IF(AND(ISNUMBER(AT45),ISNUMBER(AT46)),AT46/AT45-1,"") -> 0.00039816843 | AV46: =IF(ISNUMBER(AT46),AT46/MAX(AT$22:AT46)-1,"") -> 0 | AX46: 340.33 | AY46: =IF(AND(ISNUMBER(AX45),ISNUMBER(AX46)),AX46/AX45-1,"") -> 0.03336977 | AZ46: =IF(ISNUMBER(AX46),AX46/MAX(AX$22:AX46)-1,"") -> 0 | BB46: 56.57 | BC46: =IF(AND(ISNUMBER(BB45),ISNUMBER(BB46)),BB46/BB45-1,"") -> 0.013617631 | BD46: =IF(ISNUMBER(BB46),BB46/MAX(BB$22:BB46)-1,"") -> -0.085811248 | BF46: 49.04 | BG46: =IF(AND(ISNUMBER(BF45),ISNUMBER(BF46)),BF46/BF45-1,"") -> 0.0053300533 | BH46: =IF(ISNUMBER(BF46),BF46/MAX(BF$22:BF46)-1,"") -> -0.086097652 | BJ46: =BJ45*(1+BK46) -> 109.11327 | BK46: =$L$12*S46+$L$13*W46+$L$14*AA46+$L$15*AE46+$L$16*AI46+$L$17*AM46+$L$18*AQ46+$L$19*AU46+$L$20*AY46 -> 0.010181359 | BL46: =IF(ISNUMBER(BJ46),BJ46/MAX(BJ$22:BJ46)-1,"") -> 0 | BN46: =BN45*(1+BO46) -> 109.29409 | BO46: =$L$35*W46+$L$36*S46+$L$37*AA46+$L$38*AE46+$L$39*AQ46+$L$40*AY46+$L$41*BC46+$L$42*BG46+$L$43*AI46 -> 0.0079782928 | BP46: =IF(ISNUMBER(BN46),BN46/MAX(BN$22:BN46)-1,"") -> 0 | BR46: =BR45*(1+BS46) -> 107.78057 | BS46: =$L$58*W46+$L$59*AE46+$L$60*S46+$L$61*AQ46+$L$62*BC46+$L$63*AA46+$L$64*BG46+$L$65*AY46+$L$66*AI46 -> 0.0083792534 | BT46: =IF(ISNUMBER(BR46),BR46/MAX(BR$22:BR46)-1,"") -> 0
E47: United States | F47: =SUMIF($D$35:$D$43, E47, $L$35:$L$43) -> 0.3 | H47: Growth | I47: =SUMIF($F$35:$F$43, H47, $L$35:$L$43) -> 0.7 | Q47: 45169 | R47: 100.71 | S47: =IF(AND(ISNUMBER(R46),ISNUMBER(R47)),R47/R46-1,"") -> -9.9285147e-05 | T47: =IF(ISNUMBER(R47),R47/MAX(R$22:R47)-1,"") -> -9.9285147e-05 | V47: 696.42 | W47: =IF(AND(ISNUMBER(V46),ISNUMBER(V47)),V47/V46-1,"") -> 0.019648609 | X47: =IF(ISNUMBER(V47),V47/MAX(V$22:V47)-1,"") -> 0 | Z47: 30.99 | AA47: =IF(AND(ISNUMBER(Z46),ISNUMBER(Z47)),Z47/Z46-1,"") -> 0.020078999 | AB47: =IF(ISNUMBER(Z47),Z47/MAX(Z$22:Z47)-1,"") -> -0.0022537025 | AD47: 16.79 | AE47: =IF(AND(ISNUMBER(AD46),ISNUMBER(AD47)),AD47/AD46-1,"") -> -0.0023767083 | AF47: =IF(ISNUMBER(AD47),AD47/MAX(AD$22:AD47)-1,"") -> -0.024404416 | AH47: 27.76 | AI47: =IF(AND(ISNUMBER(AH46),ISNUMBER(AH47)),AH47/AH46-1,"") -> 0.025489472 | AJ47: =IF(ISNUMBER(AH47),AH47/MAX(AH$22:AH47)-1,"") -> -0.0096325366 | AL47: 41.51 | AM47: =IF(AND(ISNUMBER(AL46),ISNUMBER(AL47)),AL47/AL46-1,"") -> -0.00598659 | AN47: =IF(ISNUMBER(AL47),AL47/MAX(AL$22:AL47)-1,"") -> -0.16813627 | AP47: 62.02 | AQ47: =IF(AND(ISNUMBER(AP46),ISNUMBER(AP47)),AP47/AP46-1,"") -> -0.013990461 | AR47: =IF(ISNUMBER(AP47),AP47/MAX(AP$22:AP47)-1,"") -> -0.061440678 | AT47: 50.24 | AU47: =IF(AND(ISNUMBER(AT46),ISNUMBER(AT47)),AT47/AT46-1,"") -> -0.00019900498 | AV47: =IF(ISNUMBER(AT47),AT47/MAX(AT$22:AT47)-1,"") -> -0.00019900498 | AX47: 346.25 | AY47: =IF(AND(ISNUMBER(AX46),ISNUMBER(AX47)),AX47/AX46-1,"") -> 0.017394881 | AZ47: =IF(ISNUMBER(AX47),AX47/MAX(AX$22:AX47)-1,"") -> 0 | BB47: 56.55 | BC47: =IF(AND(ISNUMBER(BB46),ISNUMBER(BB47)),BB47/BB46-1,"") -> -0.00035354428 | BD47: =IF(ISNUMBER(BB47),BB47/MAX(BB$22:BB47)-1,"") -> -0.086134454 | BF47: 49.54 | BG47: =IF(AND(ISNUMBER(BF46),ISNUMBER(BF47)),BF47/BF46-1,"") -> 0.010195759 | BH47: =IF(ISNUMBER(BF47),BF47/MAX(BF$22:BF47)-1,"") -> -0.076779724 | BJ47: =BJ46*(1+BK47) -> 110.38539 | BK47: =$L$12*S47+$L$13*W47+$L$14*AA47+$L$15*AE47+$L$16*AI47+$L$17*AM47+$L$18*AQ47+$L$19*AU47+$L$20*AY47 -> 0.011658717 | BL47: =IF(ISNUMBER(BJ47),BJ47/MAX(BJ$22:BJ47)-1,"") -> 0 | BN47: =BN46*(1+BO47) -> 110.4892 | BO47: =$L$35*W47+$L$36*S47+$L$37*AA47+$L$38*AE47+$L$39*AQ47+$L$40*AY47+$L$41*BC47+$L$42*BG47+$L$43*AI47 -> 0.010934737 | BP47: =IF(ISNUMBER(BN47),BN47/MAX(BN$22:BN47)-1,"") -> 0 | BR47: =BR46*(1+BS47) -> 108.42541 | BS47: =$L$58*W47+$L$59*AE47+$L$60*S47+$L$61*AQ47+$L$62*BC47+$L$63*AA47+$L$64*BG47+$L$65*AY47+$L$66*AI47 -> 0.0059829143 | BT47: =IF(ISNUMBER(BR47),BR47/MAX(BR$22:BR47)-1,"") -> 0 | BV47: Date | BW47: Initial Investment AUD | BX47: Drawdowns
E48: Global | F48: =SUMIF($D$35:$D$43, E48, $L$35:$L$43) -> 0.3039 | H48: Defensive | I48: =SUMIF($F$35:$F$43, H48, $L$35:$L$43) -> 0.3 | Q48: 45198 | R48: 100.69 | S48: =IF(AND(ISNUMBER(R47),ISNUMBER(R48)),R48/R47-1,"") -> -0.00019859001 | T48: =IF(ISNUMBER(R48),R48/MAX(R$22:R48)-1,"") -> -0.00029785544 | V48: 663.47 | W48: =IF(AND(ISNUMBER(V47),ISNUMBER(V48)),V48/V47-1,"") -> -0.047313403 | X48: =IF(ISNUMBER(V48),V48/MAX(V$22:V48)-1,"") -> -0.047313403 | Z48: 29.53 | AA48: =IF(AND(ISNUMBER(Z47),ISNUMBER(Z48)),Z48/Z47-1,"") -> -0.047111972 | AB48: =IF(ISNUMBER(Z48),Z48/MAX(Z$22:Z48)-1,"") -> -0.049259498 | AD48: 16.57 | AE48: =IF(AND(ISNUMBER(AD47),ISNUMBER(AD48)),AD48/AD47-1,"") -> -0.013103038 | AF48: =IF(ISNUMBER(AD48),AD48/MAX(AD$22:AD48)-1,"") -> -0.037187682 | AH48: 26.73 | AI48: =IF(AND(ISNUMBER(AH47),ISNUMBER(AH48)),AH48/AH47-1,"") -> -0.037103746 | AJ48: =IF(ISNUMBER(AH48),AH48/MAX(AH$22:AH48)-1,"") -> -0.04637888 | AL48: 40.62 | AM48: =IF(AND(ISNUMBER(AL47),ISNUMBER(AL48)),AL48/AL47-1,"") -> -0.021440617 | AN48: =IF(ISNUMBER(AL48),AL48/MAX(AL$22:AL48)-1,"") -> -0.18597194 | AP48: 58.57 | AQ48: =IF(AND(ISNUMBER(AP47),ISNUMBER(AP48)),AP48/AP47-1,"") -> -0.055627217 | AR48: =IF(ISNUMBER(AP48),AP48/MAX(AP$22:AP48)-1,"") -> -0.11365012 | AT48: 50.24 | AU48: =IF(AND(ISNUMBER(AT47),ISNUMBER(AT48)),AT48/AT47-1,"") -> 0 | AV48: =IF(ISNUMBER(AT48),AT48/MAX(AT$22:AT48)-1,"") -> -0.00019900498 | AX48: 330.13 | AY48: =IF(AND(ISNUMBER(AX47),ISNUMBER(AX48)),AX48/AX47-1,"") -> -0.046555957 | AZ48: =IF(ISNUMBER(AX48),AX48/MAX(AX$22:AX48)-1,"") -> -0.046555957 | BB48: 54.23 | BC48: =IF(AND(ISNUMBER(BB47),ISNUMBER(BB48)),BB48/BB47-1,"") -> -0.041025641 | BD48: =IF(ISNUMBER(BB48),BB48/MAX(BB$22:BB48)-1,"") -> -0.12362637 | BF48: 49.3 | BG48: =IF(AND(ISNUMBER(BF47),ISNUMBER(BF48)),BF48/BF47-1,"") -> -0.00484457 | BH48: =IF(ISNUMBER(BF48),BF48/MAX(BF$22:BF48)-1,"") -> -0.081252329 | BJ48: =BJ47*(1+BK48) -> 106.87841 | BK48: =$L$12*S48+$L$13*W48+$L$14*AA48+$L$15*AE48+$L$16*AI48+$L$17*AM48+$L$18*AQ48+$L$19*AU48+$L$20*AY48 -> -0.031770344 | BL48: =IF(ISNUMBER(BJ48),BJ48/MAX(BJ$22:BJ48)-1,"") -> -0.031770344 | BN48: =BN47*(1+BO48) -> 107.10065 | BO48: =$L$35*W48+$L$36*S48+$L$37*AA48+$L$38*AE48+$L$39*AQ48+$L$40*AY48+$L$41*BC48+$L$42*BG48+$L$43*AI48 -> -0.030668604 | BP48: =IF(ISNUMBER(BN48),BN48/MAX(BN$22:BN48)-1,"") -> -0.030668604 | BR48: =BR47*(1+BS48) -> 104.95316 | BS48: =$L$58*W48+$L$59*AE48+$L$60*S48+$L$61*AQ48+$L$62*BC48+$L$63*AA48+$L$64*BG48+$L$65*AY48+$L$66*AI48 -> -0.032024407 | BT48: =IF(ISNUMBER(BR48),BR48/MAX(BR$22:BR48)-1,"") -> -0.032024407 | BV48: 46023 | BW48: =$BY$43 -> 100000000
E49: Australia | F49: =SUMIF($D$35:$D$43, E49, $L$35:$L$43) -> 0.23 | I49: =SUM(I47:I48) -> 1 | Q49: 45230 | R49: 100.67 | S49: =IF(AND(ISNUMBER(R48),ISNUMBER(R49)),R49/R48-1,"") -> -0.00019862946 | T49: =IF(ISNUMBER(R49),R49/MAX(R$22:R49)-1,"") -> -0.00049642573 | V49: 652.94 | W49: =IF(AND(ISNUMBER(V48),ISNUMBER(V49)),V49/V48-1,"") -> -0.015871102 | X49: =IF(ISNUMBER(V49),V49/MAX(V$22:V49)-1,"") -> -0.062433589 | Z49: 29.15 | AA49: =IF(AND(ISNUMBER(Z48),ISNUMBER(Z49)),Z49/Z48-1,"") -> -0.01286827 | AB49: =IF(ISNUMBER(Z49),Z49/MAX(Z$22:Z49)-1,"") -> -0.061493883 | AD49: 15.93 | AE49: =IF(AND(ISNUMBER(AD48),ISNUMBER(AD49)),AD49/AD48-1,"") -> -0.038624019 | AF49: =IF(ISNUMBER(AD49),AD49/MAX(AD$22:AD49)-1,"") -> -0.074375363 | AH49: 29.05 | AI49: =IF(AND(ISNUMBER(AH48),ISNUMBER(AH49)),AH49/AH48-1,"") -> 0.086793865 | AJ49: =IF(ISNUMBER(AH49),AH49/MAX(AH$22:AH49)-1,"") -> 0 | AL49: 40.29 | AM49: =IF(AND(ISNUMBER(AL48),ISNUMBER(AL49)),AL49/AL48-1,"") -> -0.0081240768 | AN49: =IF(ISNUMBER(AL49),AL49/MAX(AL$22:AL49)-1,"") -> -0.19258517 | AP49: 58.4 | AQ49: =IF(AND(ISNUMBER(AP48),ISNUMBER(AP49)),AP49/AP48-1,"") -> -0.0029025098 | AR49: =IF(ISNUMBER(AP49),AP49/MAX(AP$22:AP49)-1,"") -> -0.11622276 | AT49: 50.25 | AU49: =IF(AND(ISNUMBER(AT48),ISNUMBER(AT49)),AT49/AT48-1,"") -> 0.00019904459 | AV49: =IF(ISNUMBER(AT49),AT49/MAX(AT$22:AT49)-1,"") -> 0 | AX49: 322.69 | AY49: =IF(AND(ISNUMBER(AX48),ISNUMBER(AX49)),AX49/AX48-1,"") -> -0.022536577 | AZ49: =IF(ISNUMBER(AX49),AX49/MAX(AX$22:AX49)-1,"") -> -0.068043321 | BB49: 51.08 | BC49: =IF(AND(ISNUMBER(BB48),ISNUMBER(BB49)),BB49/BB48-1,"") -> -0.05808593 | BD49: =IF(ISNUMBER(BB49),BB49/MAX(BB$22:BB49)-1,"") -> -0.17453135 | BF49: 48.6 | BG49: =IF(AND(ISNUMBER(BF48),ISNUMBER(BF49)),BF49/BF48-1,"") -> -0.014198783 | BH49: =IF(ISNUMBER(BF49),BF49/MAX(BF$22:BF49)-1,"") -> -0.094297428 | BJ49: =BJ48*(1+BK49) -> 107.07579 | BK49: =$L$12*S49+$L$13*W49+$L$14*AA49+$L$15*AE49+$L$16*AI49+$L$17*AM49+$L$18*AQ49+$L$19*AU49+$L$20*AY49 -> 0.0018467786 | BL49: =IF(ISNUMBER(BJ49),BJ49/MAX(BJ$22:BJ49)-1,"") -> -0.029982238 | BN49: =BN48*(1+BO49) -> 106.28584 | BO49: =$L$35*W49+$L$36*S49+$L$37*AA49+$L$38*AE49+$L$39*AQ49+$L$40*AY49+$L$41*BC49+$L$42*BG49+$L$43*AI49 -> -0.0076078514 | BP49: =IF(ISNUMBER(BN49),BN49/MAX(BN$22:BN49)-1,"") -> -0.038043133 | BR49: =BR48*(1+BS49) -> 102.9249 | BS49: =$L$58*W49+$L$59*AE49+$L$60*S49+$L$61*AQ49+$L$62*BC49+$L$63*AA49+$L$64*BG49+$L$65*AY49+$L$66*AI49 -> -0.019325363 | BT49: =IF(ISNUMBER(BR49),BR49/MAX(BR$22:BR49)-1,"") -> -0.050730887 | BV49: 46388 | BW49: =BW48*(1+$BY$44) -> 1.0893693e+08 | BX49: =ABS(BW49*$BY$45) -> 16225479
E50: Japan | F50: =SUMIF($D$35:$D$43, E50, $L$35:$L$43) -> 0.1661 | Q50: 45260 | R50: 100.68 | S50: =IF(AND(ISNUMBER(R49),ISNUMBER(R50)),R50/R49-1,"") -> 9.9334459e-05 | T50: =IF(ISNUMBER(R50),R50/MAX(R$22:R50)-1,"") -> -0.00039714059 | V50: 685.57 | W50: =IF(AND(ISNUMBER(V49),ISNUMBER(V50)),V50/V49-1,"") -> 0.049973964 | X50: =IF(ISNUMBER(V50),V50/MAX(V$22:V50)-1,"") -> -0.015579679 | Z50: 30.88 | AA50: =IF(AND(ISNUMBER(Z49),ISNUMBER(Z50)),Z50/Z49-1,"") -> 0.059348199 | AB50: =IF(ISNUMBER(Z50),Z50/MAX(Z$22:Z50)-1,"") -> -0.005795235 | AD50: 17.37 | AE50: =IF(AND(ISNUMBER(AD49),ISNUMBER(AD50)),AD50/AD49-1,"") -> 0.09039548 | AF50: =IF(ISNUMBER(AD50),AD50/MAX(AD$22:AD50)-1,"") -> 0 | AH50: 28.44 | AI50: =IF(AND(ISNUMBER(AH49),ISNUMBER(AH50)),AH50/AH49-1,"") -> -0.020998279 | AJ50: =IF(ISNUMBER(AH50),AH50/MAX(AH$22:AH50)-1,"") -> -0.020998279 | AL50: 41.64 | AM50: =IF(AND(ISNUMBER(AL49),ISNUMBER(AL50)),AL50/AL49-1,"") -> 0.033507074 | AN50: =IF(ISNUMBER(AL50),AL50/MAX(AL$22:AL50)-1,"") -> -0.16553106 | AP50: 60.2 | AQ50: =IF(AND(ISNUMBER(AP49),ISNUMBER(AP50)),AP50/AP49-1,"") -> 0.030821918 | AR50: =IF(ISNUMBER(AP50),AP50/MAX(AP$22:AP50)-1,"") -> -0.088983051 | AT50: 50.24 | AU50: =IF(AND(ISNUMBER(AT49),ISNUMBER(AT50)),AT50/AT49-1,"") -> -0.00019900498 | AV50: =IF(ISNUMBER(AT50),AT50/MAX(AT$22:AT50)-1,"") -> -0.00019900498 | AX50: 339.66 | AY50: =IF(AND(ISNUMBER(AX49),ISNUMBER(AX50)),AX50/AX49-1,"") -> 0.052589172 | AZ50: =IF(ISNUMBER(AX50),AX50/MAX(AX$22:AX50)-1,"") -> -0.019032491 | BB50: 54.4 | BC50: =IF(AND(ISNUMBER(BB49),ISNUMBER(BB50)),BB50/BB49-1,"") -> 0.064996085 | BD50: =IF(ISNUMBER(BB50),BB50/MAX(BB$22:BB50)-1,"") -> -0.12087912 | BF50: 49.51 | BG50: =IF(AND(ISNUMBER(BF49),ISNUMBER(BF50)),BF50/BF49-1,"") -> 0.01872428 | BH50: =IF(ISNUMBER(BF50),BF50/MAX(BF$22:BF50)-1,"") -> -0.0773388 | BJ50: =BJ49*(1+BK50) -> 110.59164 | BK50: =$L$12*S50+$L$13*W50+$L$14*AA50+$L$15*AE50+$L$16*AI50+$L$17*AM50+$L$18*AQ50+$L$19*AU50+$L$20*AY50 -> 0.032835149 | BL50: =IF(ISNUMBER(BJ50),BJ50/MAX(BJ$22:BJ50)-1,"") -> 0 | BN50: =BN49*(1+BO50) -> 110.70013 | BO50: =$L$35*W50+$L$36*S50+$L$37*AA50+$L$38*AE50+$L$39*AQ50+$L$40*AY50+$L$41*BC50+$L$42*BG50+$L$43*AI50 -> 0.041532253 | BP50: =IF(ISNUMBER(BN50),BN50/MAX(BN$22:BN50)-1,"") -> 0 | BR50: =BR49*(1+BS50) -> 107.86943 | BS50: =$L$58*W50+$L$59*AE50+$L$60*S50+$L$61*AQ50+$L$62*BC50+$L$63*AA50+$L$64*BG50+$L$65*AY50+$L$66*AI50 -> 0.048040154 | BT50: =IF(ISNUMBER(BR50),BR50/MAX(BR$22:BR50)-1,"") -> -0.0051278524 | BV50: 46753 | BW50: =BW49*(1+$BY$44) -> 1.1867254e+08 | BX50: =ABS(BW50*$BY$45) -> 17675539
E51: China | F51: =SUMIF($D$35:$D$43, E51, $L$35:$L$43) -> 0 | Q51: 45289 | R51: 100.71 | S51: =IF(AND(ISNUMBER(R50),ISNUMBER(R51)),R51/R50-1,"") -> 0.00029797378 | T51: =IF(ISNUMBER(R51),R51/MAX(R$22:R51)-1,"") -> -9.9285147e-05 | V51: 697.76 | W51: =IF(AND(ISNUMBER(V50),ISNUMBER(V51)),V51/V50-1,"") -> 0.017780825 | X51: =IF(ISNUMBER(V51),V51/MAX(V$22:V51)-1,"") -> 0 | Z51: 31.66 | AA51: =IF(AND(ISNUMBER(Z50),ISNUMBER(Z51)),Z51/Z50-1,"") -> 0.025259067 | AB51: =IF(ISNUMBER(Z51),Z51/MAX(Z$22:Z51)-1,"") -> 0 | AD51: 17.22 | AE51: =IF(AND(ISNUMBER(AD50),ISNUMBER(AD51)),AD51/AD50-1,"") -> -0.0086355786 | AF51: =IF(ISNUMBER(AD51),AD51/MAX(AD$22:AD51)-1,"") -> -0.0086355786 | AH51: 27.96 | AI51: =IF(AND(ISNUMBER(AH50),ISNUMBER(AH51)),AH51/AH50-1,"") -> -0.016877637 | AJ51: =IF(ISNUMBER(AH51),AH51/MAX(AH$22:AH51)-1,"") -> -0.037521515 | AL51: 42.96 | AM51: =IF(AND(ISNUMBER(AL50),ISNUMBER(AL51)),AL51/AL50-1,"") -> 0.031700288 | AN51: =IF(ISNUMBER(AL51),AL51/MAX(AL$22:AL51)-1,"") -> -0.13907816 | AP51: 61.11 | AQ51: =IF(AND(ISNUMBER(AP50),ISNUMBER(AP51)),AP51/AP50-1,"") -> 0.015116279 | AR51: =IF(ISNUMBER(AP51),AP51/MAX(AP$22:AP51)-1,"") -> -0.075211864 | AT51: 50.26 | AU51: =IF(AND(ISNUMBER(AT50),ISNUMBER(AT51)),AT51/AT50-1,"") -> 0.00039808917 | AV51: =IF(ISNUMBER(AT51),AT51/MAX(AT$22:AT51)-1,"") -> 0 | AX51: 348.8 | AY51: =IF(AND(ISNUMBER(AX50),ISNUMBER(AX51)),AX51/AX50-1,"") -> 0.026909262 | AZ51: =IF(ISNUMBER(AX51),AX51/MAX(AX$22:AX51)-1,"") -> 0 | BB51: 58.7 | BC51: =IF(AND(ISNUMBER(BB50),ISNUMBER(BB51)),BB51/BB50-1,"") -> 0.079044118 | BD51: =IF(ISNUMBER(BB51),BB51/MAX(BB$22:BB51)-1,"") -> -0.051389787 | BF51: 50.45 | BG51: =IF(AND(ISNUMBER(BF50),ISNUMBER(BF51)),BF51/BF50-1,"") -> 0.018986063 | BH51: =IF(ISNUMBER(BF51),BF51/MAX(BF$22:BF51)-1,"") -> -0.059821096 | BJ51: =BJ50*(1+BK51) -> 111.47097 | BK51: =$L$12*S51+$L$13*W51+$L$14*AA51+$L$15*AE51+$L$16*AI51+$L$17*AM51+$L$18*AQ51+$L$19*AU51+$L$20*AY51 -> 0.0079512179 | BL51: =IF(ISNUMBER(BJ51),BJ51/MAX(BJ$22:BJ51)-1,"") -> 0 | BN51: =BN50*(1+BO51) -> 111.69593 | BO51: =$L$35*W51+$L$36*S51+$L$37*AA51+$L$38*AE51+$L$39*AQ51+$L$40*AY51+$L$41*BC51+$L$42*BG51+$L$43*AI51 -> 0.0089954922 | BP51: =IF(ISNUMBER(BN51),BN51/MAX(BN$22:BN51)-1,"") -> 0 | BR51: =BR50*(1+BS51) -> 109.64952 | BS51: =$L$58*W51+$L$59*AE51+$L$60*S51+$L$61*AQ51+$L$62*BC51+$L$63*AA51+$L$64*BG51+$L$65*AY51+$L$66*AI51 -> 0.016502327 | BT51: =IF(ISNUMBER(BR51),BR51/MAX(BR$22:BR51)-1,"") -> 0 | BV51: 47119 | BW51: =BW50*(1+$BY$44) -> 1.2927822e+08 | BX51: =ABS(BW51*$BY$45) -> 19255189
E52: Emerging Markets | F52: =SUMIF($D$35:$D$43, E52, $L$35:$L$43) -> 0 | Q52: 45322 | R52: 100.71 | S52: =IF(AND(ISNUMBER(R51),ISNUMBER(R52)),R52/R51-1,"") -> 0 | T52: =IF(ISNUMBER(R52),R52/MAX(R$22:R52)-1,"") -> -9.9285147e-05 | V52: 744.3 | W52: =IF(AND(ISNUMBER(V51),ISNUMBER(V52)),V52/V51-1,"") -> 0.066699152 | X52: =IF(ISNUMBER(V52),V52/MAX(V$22:V52)-1,"") -> 0 | Z52: 34.05 | AA52: =IF(AND(ISNUMBER(Z51),ISNUMBER(Z52)),Z52/Z51-1,"") -> 0.075489577 | AB52: =IF(ISNUMBER(Z52),Z52/MAX(Z$22:Z52)-1,"") -> 0 | AD52: 18.73 | AE52: =IF(AND(ISNUMBER(AD51),ISNUMBER(AD52)),AD52/AD51-1,"") -> 0.087688734 | AF52: =IF(ISNUMBER(AD52),AD52/MAX(AD$22:AD52)-1,"") -> 0 | AH52: 28.6 | AI52: =IF(AND(ISNUMBER(AH51),ISNUMBER(AH52)),AH52/AH51-1,"") -> 0.022889843 | AJ52: =IF(ISNUMBER(AH52),AH52/MAX(AH$22:AH52)-1,"") -> -0.015490534 | AL52: 42.44 | AM52: =IF(AND(ISNUMBER(AL51),ISNUMBER(AL52)),AL52/AL51-1,"") -> -0.012104283 | AN52: =IF(ISNUMBER(AL52),AL52/MAX(AL$22:AL52)-1,"") -> -0.149499 | AP52: 61.6 | AQ52: =IF(AND(ISNUMBER(AP51),ISNUMBER(AP52)),AP52/AP51-1,"") -> 0.0080183276 | AR52: =IF(ISNUMBER(AP52),AP52/MAX(AP$22:AP52)-1,"") -> -0.06779661 | AT52: 50.27 | AU52: =IF(AND(ISNUMBER(AT51),ISNUMBER(AT52)),AT52/AT51-1,"") -> 0.00019896538 | AV52: =IF(ISNUMBER(AT52),AT52/MAX(AT$22:AT52)-1,"") -> 0 | AX52: 370.54 | AY52: =IF(AND(ISNUMBER(AX51),ISNUMBER(AX52)),AX52/AX51-1,"") -> 0.062327982 | AZ52: =IF(ISNUMBER(AX52),AX52/MAX(AX$22:AX52)-1,"") -> 0 | BB52: 59.11 | BC52: =IF(AND(ISNUMBER(BB51),ISNUMBER(BB52)),BB52/BB51-1,"") -> 0.0069846678 | BD52: =IF(ISNUMBER(BB52),BB52/MAX(BB$22:BB52)-1,"") -> -0.044764059 | BF52: 50.19 | BG52: =IF(AND(ISNUMBER(BF51),ISNUMBER(BF52)),BF52/BF51-1,"") -> -0.0051536174 | BH52: =IF(ISNUMBER(BF52),BF52/MAX(BF$22:BF52)-1,"") -> -0.064666418 | BJ52: =BJ51*(1+BK52) -> 116.34308 | BK52: =$L$12*S52+$L$13*W52+$L$14*AA52+$L$15*AE52+$L$16*AI52+$L$17*AM52+$L$18*AQ52+$L$19*AU52+$L$20*AY52 -> 0.043707428 | BL52: =IF(ISNUMBER(BJ52),BJ52/MAX(BJ$22:BJ52)-1,"") -> 0 | BN52: =BN51*(1+BO52) -> 117.39192 | BO52: =$L$35*W52+$L$36*S52+$L$37*AA52+$L$38*AE52+$L$39*AQ52+$L$40*AY52+$L$41*BC52+$L$42*BG52+$L$43*AI52 -> 0.050995471 | BP52: =IF(ISNUMBER(BN52),BN52/MAX(BN$22:BN52)-1,"") -> 0 | BR52: =BR51*(1+BS52) -> 114.60665 | BS52: =$L$58*W52+$L$59*AE52+$L$60*S52+$L$61*AQ52+$L$62*BC52+$L$63*AA52+$L$64*BG52+$L$65*AY52+$L$66*AI52 -> 0.045208812 | BT52: =IF(ISNUMBER(BR52),BR52/MAX(BR$22:BR52)-1,"") -> 0 | BV52: 47484 | BW52: =BW51*(1+$BY$44) -> 1.4083172e+08 | BX52: =ABS(BW52*$BY$45) -> 20976011
F53: =SUM(F47:F52) -> 1 | Q53: 45351 | R53: 100.7 | S53: =IF(AND(ISNUMBER(R52),ISNUMBER(R53)),R53/R52-1,"") -> -9.9295005e-05 | T53: =IF(ISNUMBER(R53),R53/MAX(R$22:R53)-1,"") -> -0.00019857029 | V53: 777.54 | W53: =IF(AND(ISNUMBER(V52),ISNUMBER(V53)),V53/V52-1,"") -> 0.044659412 | X53: =IF(ISNUMBER(V53),V53/MAX(V$22:V53)-1,"") -> 0 | Z53: 35.31 | AA53: =IF(AND(ISNUMBER(Z52),ISNUMBER(Z53)),Z53/Z52-1,"") -> 0.037004405 | AB53: =IF(ISNUMBER(Z53),Z53/MAX(Z$22:Z53)-1,"") -> 0 | AD53: 20.21 | AE53: =IF(AND(ISNUMBER(AD52),ISNUMBER(AD53)),AD53/AD52-1,"") -> 0.079017619 | AF53: =IF(ISNUMBER(AD53),AD53/MAX(AD$22:AD53)-1,"") -> 0 | AH53: 28.81 | AI53: =IF(AND(ISNUMBER(AH52),ISNUMBER(AH53)),AH53/AH52-1,"") -> 0.0073426573 | AJ53: =IF(ISNUMBER(AH53),AH53/MAX(AH$22:AH53)-1,"") -> -0.0082616179 | AL53: 42.01 | AM53: =IF(AND(ISNUMBER(AL52),ISNUMBER(AL53)),AL53/AL52-1,"") -> -0.010131951 | AN53: =IF(ISNUMBER(AL53),AL53/MAX(AL$22:AL53)-1,"") -> -0.15811623 | AP53: 62.29 | AQ53: =IF(AND(ISNUMBER(AP52),ISNUMBER(AP53)),AP53/AP52-1,"") -> 0.011201299 | AR53: =IF(ISNUMBER(AP53),AP53/MAX(AP$22:AP53)-1,"") -> -0.057354722 | AT53: 50.25 | AU53: =IF(AND(ISNUMBER(AT52),ISNUMBER(AT53)),AT53/AT52-1,"") -> -0.0003978516 | AV53: =IF(ISNUMBER(AT53),AT53/MAX(AT$22:AT53)-1,"") -> -0.0003978516 | AX53: 386.37 | AY53: =IF(AND(ISNUMBER(AX52),ISNUMBER(AX53)),AX53/AX52-1,"") -> 0.042721434 | AZ53: =IF(ISNUMBER(AX53),AX53/MAX(AX$22:AX53)-1,"") -> 0 | BB53: 60.69 | BC53: =IF(AND(ISNUMBER(BB52),ISNUMBER(BB53)),BB53/BB52-1,"") -> 0.026729826 | BD53: =IF(ISNUMBER(BB53),BB53/MAX(BB$22:BB53)-1,"") -> -0.019230769 | BF53: 50.27 | BG53: =IF(AND(ISNUMBER(BF52),ISNUMBER(BF53)),BF53/BF52-1,"") -> 0.001593943 | BH53: =IF(ISNUMBER(BF53),BF53/MAX(BF$22:BF53)-1,"") -> -0.06317555 | BJ53: =BJ52*(1+BK53) -> 119.62125 | BK53: =$L$12*S53+$L$13*W53+$L$14*AA53+$L$15*AE53+$L$16*AI53+$L$17*AM53+$L$18*AQ53+$L$19*AU53+$L$20*AY53 -> 0.028176748 | BL53: =IF(ISNUMBER(BJ53),BJ53/MAX(BJ$22:BJ53)-1,"") -> 0 | BN53: =BN52*(1+BO53) -> 121.47289 | BO53: =$L$35*W53+$L$36*S53+$L$37*AA53+$L$38*AE53+$L$39*AQ53+$L$40*AY53+$L$41*BC53+$L$42*BG53+$L$43*AI53 -> 0.03476363 | BP53: =IF(ISNUMBER(BN53),BN53/MAX(BN$22:BN53)-1,"") -> 0 | BR53: =BR52*(1+BS53) -> 118.72471 | BS53: =$L$58*W53+$L$59*AE53+$L$60*S53+$L$61*AQ53+$L$62*BC53+$L$63*AA53+$L$64*BG53+$L$65*AY53+$L$66*AI53 -> 0.035932196 | BT53: =IF(ISNUMBER(BR53),BR53/MAX(BR$22:BR53)-1,"") -> 0 | BV53: 47849 | BW53: =BW52*(1+$BY$44) -> 1.5341775e+08 | BX53: =ABS(BW53*$BY$45) -> 22850621
Q54: 45379 | R54: 100.67 | S54: =IF(AND(ISNUMBER(R53),ISNUMBER(R54)),R54/R53-1,"") -> -0.0002979146 | T54: =IF(ISNUMBER(R54),R54/MAX(R$22:R54)-1,"") -> -0.00049642573 | V54: 801.49 | W54: =IF(AND(ISNUMBER(V53),ISNUMBER(V54)),V54/V53-1,"") -> 0.030802274 | X54: =IF(ISNUMBER(V54),V54/MAX(V$22:V54)-1,"") -> 0 | Z54: 36.24 | AA54: =IF(AND(ISNUMBER(Z53),ISNUMBER(Z54)),Z54/Z53-1,"") -> 0.026338148 | AB54: =IF(ISNUMBER(Z54),Z54/MAX(Z$22:Z54)-1,"") -> 0 | AD54: 21.14 | AE54: =IF(AND(ISNUMBER(AD53),ISNUMBER(AD54)),AD54/AD53-1,"") -> 0.046016823 | AF54: =IF(ISNUMBER(AD54),AD54/MAX(AD$22:AD54)-1,"") -> 0 | AH54: 31.02 | AI54: =IF(AND(ISNUMBER(AH53),ISNUMBER(AH54)),AH54/AH53-1,"") -> 0.076709476 | AJ54: =IF(ISNUMBER(AH54),AH54/MAX(AH$22:AH54)-1,"") -> 0 | AL54: 42.3 | AM54: =IF(AND(ISNUMBER(AL53),ISNUMBER(AL54)),AL54/AL53-1,"") -> 0.0069031183 | AN54: =IF(ISNUMBER(AL54),AL54/MAX(AL$22:AL54)-1,"") -> -0.15230461 | AP54: 63.98 | AQ54: =IF(AND(ISNUMBER(AP53),ISNUMBER(AP54)),AP54/AP53-1,"") -> 0.027131161 | AR54: =IF(ISNUMBER(AP54),AP54/MAX(AP$22:AP54)-1,"") -> -0.031779661 | AT54: 50.26 | AU54: =IF(AND(ISNUMBER(AT53),ISNUMBER(AT54)),AT54/AT53-1,"") -> 0.00019900498 | AV54: =IF(ISNUMBER(AT54),AT54/MAX(AT$22:AT54)-1,"") -> -0.0001989258 | AX54: 397.71 | AY54: =IF(AND(ISNUMBER(AX53),ISNUMBER(AX54)),AX54/AX53-1,"") -> 0.029350105 | AZ54: =IF(ISNUMBER(AX54),AX54/MAX(AX$22:AX54)-1,"") -> 0 | BB54: 62.69 | BC54: =IF(AND(ISNUMBER(BB53),ISNUMBER(BB54)),BB54/BB53-1,"") -> 0.032954358 | BD54: =IF(ISNUMBER(BB54),BB54/MAX(BB$22:BB54)-1,"") -> 0 | BF54: 50.6 | BG54: =IF(AND(ISNUMBER(BF53),ISNUMBER(BF54)),BF54/BF53-1,"") -> 0.0065645514 | BH54: =IF(ISNUMBER(BF54),BF54/MAX(BF$22:BF54)-1,"") -> -0.057025717 | BJ54: =BJ53*(1+BK54) -> 123.31236 | BK54: =$L$12*S54+$L$13*W54+$L$14*AA54+$L$15*AE54+$L$16*AI54+$L$17*AM54+$L$18*AQ54+$L$19*AU54+$L$20*AY54 -> 0.030856587 | BL54: =IF(ISNUMBER(BJ54),BJ54/MAX(BJ$22:BJ54)-1,"") -> 0 | BN54: =BN53*(1+BO54) -> 125.02754 | BO54: =$L$35*W54+$L$36*S54+$L$37*AA54+$L$38*AE54+$L$39*AQ54+$L$40*AY54+$L$41*BC54+$L$42*BG54+$L$43*AI54 -> 0.029262934 | BP54: =IF(ISNUMBER(BN54),BN54/MAX(BN$22:BN54)-1,"") -> 0 | BR54: =BR53*(1+BS54) -> 122.01563 | BS54: =$L$58*W54+$L$59*AE54+$L$60*S54+$L$61*AQ54+$L$62*BC54+$L$63*AA54+$L$64*BG54+$L$65*AY54+$L$66*AI54 -> 0.02771887 | BT54: =IF(ISNUMBER(BR54),BR54/MAX(BR$22:BR54)-1,"") -> 0 | BV54: 48214 | BW54: =BW53*(1+$BY$44) -> 1.6712858e+08 | BX54: =ABS(BW54*$BY$45) -> 24892765
Q55: 45412 | R55: 100.66 | S55: =IF(AND(ISNUMBER(R54),ISNUMBER(R55)),R55/R54-1,"") -> -9.9334459e-05 | T55: =IF(ISNUMBER(R55),R55/MAX(R$22:R55)-1,"") -> -0.00059571088 | V55: 780.58 | W55: =IF(AND(ISNUMBER(V54),ISNUMBER(V55)),V55/V54-1,"") -> -0.026088909 | X55: =IF(ISNUMBER(V55),V55/MAX(V$22:V55)-1,"") -> -0.026088909 | Z55: 34.85 | AA55: =IF(AND(ISNUMBER(Z54),ISNUMBER(Z55)),Z55/Z54-1,"") -> -0.038355408 | AB55: =IF(ISNUMBER(Z55),Z55/MAX(Z$22:Z55)-1,"") -> -0.038355408 | AD55: 20.87 | AE55: =IF(AND(ISNUMBER(AD54),ISNUMBER(AD55)),AD55/AD54-1,"") -> -0.012771996 | AF55: =IF(ISNUMBER(AD55),AD55/MAX(AD$22:AD55)-1,"") -> -0.012771996 | AH55: 32.86 | AI55: =IF(AND(ISNUMBER(AH54),ISNUMBER(AH55)),AH55/AH54-1,"") -> 0.05931657 | AJ55: =IF(ISNUMBER(AH55),AH55/MAX(AH$22:AH55)-1,"") -> 0 | AL55: 41.61 | AM55: =IF(AND(ISNUMBER(AL54),ISNUMBER(AL55)),AL55/AL54-1,"") -> -0.016312057 | AN55: =IF(ISNUMBER(AL55),AL55/MAX(AL$22:AL55)-1,"") -> -0.16613226 | AP55: 63 | AQ55: =IF(AND(ISNUMBER(AP54),ISNUMBER(AP55)),AP55/AP54-1,"") -> -0.015317287 | AR55: =IF(ISNUMBER(AP55),AP55/MAX(AP$22:AP55)-1,"") -> -0.046610169 | AT55: 50.27 | AU55: =IF(AND(ISNUMBER(AT54),ISNUMBER(AT55)),AT55/AT54-1,"") -> 0.00019896538 | AV55: =IF(ISNUMBER(AT55),AT55/MAX(AT$22:AT55)-1,"") -> 0 | AX55: 387.29 | AY55: =IF(AND(ISNUMBER(AX54),ISNUMBER(AX55)),AX55/AX54-1,"") -> -0.026199995 | AZ55: =IF(ISNUMBER(AX55),AX55/MAX(AX$22:AX55)-1,"") -> -0.026199995 | BB55: 60.24 | BC55: =IF(AND(ISNUMBER(BB54),ISNUMBER(BB55)),BB55/BB54-1,"") -> -0.039081193 | BD55: =IF(ISNUMBER(BB55),BB55/MAX(BB$22:BB55)-1,"") -> -0.039081193 | BF55: 49.86 | BG55: =IF(AND(ISNUMBER(BF54),ISNUMBER(BF55)),BF55/BF54-1,"") -> -0.014624506 | BH55: =IF(ISNUMBER(BF55),BF55/MAX(BF$22:BF55)-1,"") -> -0.07081625 | BJ55: =BJ54*(1+BK55) -> 122.38771 | BK55: =$L$12*S55+$L$13*W55+$L$14*AA55+$L$15*AE55+$L$16*AI55+$L$17*AM55+$L$18*AQ55+$L$19*AU55+$L$20*AY55 -> -0.0074984006 | BL55: =IF(ISNUMBER(BJ55),BJ55/MAX(BJ$22:BJ55)-1,"") -> -0.0074984006 | BN55: =BN54*(1+BO55) -> 123.3311 | BO55: =$L$35*W55+$L$36*S55+$L$37*AA55+$L$38*AE55+$L$39*AQ55+$L$40*AY55+$L$41*BC55+$L$42*BG55+$L$43*AI55 -> -0.013568587 | BP55: =IF(ISNUMBER(BN55),BN55/MAX(BN$22:BN55)-1,"") -> -0.013568587 | BR55: =BR54*(1+BS55) -> 119.6653 | BS55: =$L$58*W55+$L$59*AE55+$L$60*S55+$L$61*AQ55+$L$62*BC55+$L$63*AA55+$L$64*BG55+$L$65*AY55+$L$66*AI55 -> -0.019262515 | BT55: =IF(ISNUMBER(BR55),BR55/MAX(BR$22:BR55)-1,"") -> -0.019262515 | BV55: 48580 | BW55: =BW54*(1+$BY$44) -> 1.8206474e+08 | BX55: =ABS(BW55*$BY$45) -> 27117413
B56: 80/20 | Q56: 45443 | R56: 100.7 | S56: =IF(AND(ISNUMBER(R55),ISNUMBER(R56)),R56/R55-1,"") -> 0.00039737731 | T56: =IF(ISNUMBER(R56),R56/MAX(R$22:R56)-1,"") -> -0.00019857029 | V56: 786.97 | W56: =IF(AND(ISNUMBER(V55),ISNUMBER(V56)),V56/V55-1,"") -> 0.0081862205 | X56: =IF(ISNUMBER(V56),V56/MAX(V$22:V56)-1,"") -> -0.018116258 | Z56: 35.77 | AA56: =IF(AND(ISNUMBER(Z55),ISNUMBER(Z56)),Z56/Z55-1,"") -> 0.026398852 | AB56: =IF(ISNUMBER(Z56),Z56/MAX(Z$22:Z56)-1,"") -> -0.012969095 | AD56: 21.16 | AE56: =IF(AND(ISNUMBER(AD55),ISNUMBER(AD56)),AD56/AD55-1,"") -> 0.013895544 | AF56: =IF(ISNUMBER(AD56),AD56/MAX(AD$22:AD56)-1,"") -> 0 | AH56: 32.56 | AI56: =IF(AND(ISNUMBER(AH55),ISNUMBER(AH56)),AH56/AH55-1,"") -> -0.0091296409 | AJ56: =IF(ISNUMBER(AH56),AH56/MAX(AH$22:AH56)-1,"") -> -0.0091296409 | AL56: 41.61 | AM56: =IF(AND(ISNUMBER(AL55),ISNUMBER(AL56)),AL56/AL55-1,"") -> 0 | AN56: =IF(ISNUMBER(AL56),AL56/MAX(AL$22:AL56)-1,"") -> -0.16613226 | AP56: 63.16 | AQ56: =IF(AND(ISNUMBER(AP55),ISNUMBER(AP56)),AP56/AP55-1,"") -> 0.0025396825 | AR56: =IF(ISNUMBER(AP56),AP56/MAX(AP$22:AP56)-1,"") -> -0.044188862 | AT56: 50.26 | AU56: =IF(AND(ISNUMBER(AT55),ISNUMBER(AT56)),AT56/AT55-1,"") -> -0.0001989258 | AV56: =IF(ISNUMBER(AT56),AT56/MAX(AT$22:AT56)-1,"") -> -0.0001989258 | AX56: 388.99 | AY56: =IF(AND(ISNUMBER(AX55),ISNUMBER(AX56)),AX56/AX55-1,"") -> 0.0043894756 | AZ56: =IF(ISNUMBER(AX56),AX56/MAX(AX$22:AX56)-1,"") -> -0.021925524 | BB56: 60.6 | BC56: =IF(AND(ISNUMBER(BB55),ISNUMBER(BB56)),BB56/BB55-1,"") -> 0.0059760956 | BD56: =IF(ISNUMBER(BB56),BB56/MAX(BB$22:BB56)-1,"") -> -0.033338651 | BF56: 50.19 | BG56: =IF(AND(ISNUMBER(BF55),ISNUMBER(BF56)),BF56/BF55-1,"") -> 0.0066185319 | BH56: =IF(ISNUMBER(BF56),BF56/MAX(BF$22:BF56)-1,"") -> -0.064666418 | BJ56: =BJ55*(1+BK56) -> 123.2086 | BK56: =$L$12*S56+$L$13*W56+$L$14*AA56+$L$15*AE56+$L$16*AI56+$L$17*AM56+$L$18*AQ56+$L$19*AU56+$L$20*AY56 -> 0.0067072855 | BL56: =IF(ISNUMBER(BJ56),BJ56/MAX(BJ$22:BJ56)-1,"") -> -0.00084140909 | BN56: =BN55*(1+BO56) -> 124.47892 | BO56: =$L$35*W56+$L$36*S56+$L$37*AA56+$L$38*AE56+$L$39*AQ56+$L$40*AY56+$L$41*BC56+$L$42*BG56+$L$43*AI56 -> 0.0093068499 | BP56: =IF(ISNUMBER(BN56),BN56/MAX(BN$22:BN56)-1,"") -> -0.0043880184 | BR56: =BR55*(1+BS56) -> 120.67186 | BS56: =$L$58*W56+$L$59*AE56+$L$60*S56+$L$61*AQ56+$L$62*BC56+$L$63*AA56+$L$64*BG56+$L$65*AY56+$L$66*AI56 -> 0.0084114232 | BT56: =IF(ISNUMBER(BR56),BR56/MAX(BR$22:BR56)-1,"") -> -0.011013117 | BV56: 48945 | BW56: =BW55*(1+$BY$44) -> 1.9833573e+08 | BX56: =ABS(BW56*$BY$45) -> 29540876
B57: Ric | C57: Name | D57: Region | E57: Asset Class | F57: Type | G57: MER | H57: Return | I57: Return - MER | J57: Risk | K57: Drawdown | L57: Weight | M57: Total Risk | N57: Total Drawdown | O57: Total Return | Q57: 45471 | R57: 100.69 | S57: =IF(AND(ISNUMBER(R56),ISNUMBER(R57)),R57/R56-1,"") -> -9.9304866e-05 | T57: =IF(ISNUMBER(R57),R57/MAX(R$22:R57)-1,"") -> -0.00029785544 | V57: 826.54 | W57: =IF(AND(ISNUMBER(V56),ISNUMBER(V57)),V57/V56-1,"") -> 0.050281459 | X57: =IF(ISNUMBER(V57),V57/MAX(V$22:V57)-1,"") -> 0 | Z57: 36.9 | AA57: =IF(AND(ISNUMBER(Z56),ISNUMBER(Z57)),Z57/Z56-1,"") -> 0.031590718 | AB57: =IF(ISNUMBER(Z57),Z57/MAX(Z$22:Z57)-1,"") -> 0 | AD57: 21.5 | AE57: =IF(AND(ISNUMBER(AD56),ISNUMBER(AD57)),AD57/AD56-1,"") -> 0.016068053 | AF57: =IF(ISNUMBER(AD57),AD57/MAX(AD$22:AD57)-1,"") -> 0 | AH57: 32.39 | AI57: =IF(AND(ISNUMBER(AH56),ISNUMBER(AH57)),AH57/AH56-1,"") -> -0.0052211302 | AJ57: =IF(ISNUMBER(AH57),AH57/MAX(AH$22:AH57)-1,"") -> -0.014303104 | AL57: 42.03 | AM57: =IF(AND(ISNUMBER(AL56),ISNUMBER(AL57)),AL57/AL56-1,"") -> 0.010093727 | AN57: =IF(ISNUMBER(AL57),AL57/MAX(AL$22:AL57)-1,"") -> -0.15771543 | AP57: 62.74 | AQ57: =IF(AND(ISNUMBER(AP56),ISNUMBER(AP57)),AP57/AP56-1,"") -> -0.0066497783 | AR57: =IF(ISNUMBER(AP57),AP57/MAX(AP$22:AP57)-1,"") -> -0.050544794 | AT57: 50.28 | AU57: =IF(AND(ISNUMBER(AT56),ISNUMBER(AT57)),AT57/AT56-1,"") -> 0.00039793076 | AV57: =IF(ISNUMBER(AT57),AT57/MAX(AT$22:AT57)-1,"") -> 0 | AX57: 406.76 | AY57: =IF(AND(ISNUMBER(AX56),ISNUMBER(AX57)),AX57/AX56-1,"") -> 0.045682408 | AZ57: =IF(ISNUMBER(AX57),AX57/MAX(AX$22:AX57)-1,"") -> 0 | BB57: 61.31 | BC57: =IF(AND(ISNUMBER(BB56),ISNUMBER(BB57)),BB57/BB56-1,"") -> 0.011716172 | BD57: =IF(ISNUMBER(BB57),BB57/MAX(BB$22:BB57)-1,"") -> -0.02201308 | BF57: 50.35 | BG57: =IF(AND(ISNUMBER(BF56),ISNUMBER(BF57)),BF57/BF56-1,"") -> 0.003187886 | BH57: =IF(ISNUMBER(BF57),BF57/MAX(BF$22:BF57)-1,"") -> -0.061684681 | BJ57: =BJ56*(1+BK57) -> 125.77434 | BK57: =$L$12*S57+$L$13*W57+$L$14*AA57+$L$15*AE57+$L$16*AI57+$L$17*AM57+$L$18*AQ57+$L$19*AU57+$L$20*AY57 -> 0.020824328 | BL57: =IF(ISNUMBER(BJ57),BJ57/MAX(BJ$22:BJ57)-1,"") -> 0 | BN57: =BN56*(1+BO57) -> 127.36617 | BO57: =$L$35*W57+$L$36*S57+$L$37*AA57+$L$38*AE57+$L$39*AQ57+$L$40*AY57+$L$41*BC57+$L$42*BG57+$L$43*AI57 -> 0.023194656 | BP57: =IF(ISNUMBER(BN57),BN57/MAX(BN$22:BN57)-1,"") -> 0 | BR57: =BR56*(1+BS57) -> 123.25934 | BS57: =$L$58*W57+$L$59*AE57+$L$60*S57+$L$61*AQ57+$L$62*BC57+$L$63*AA57+$L$64*BG57+$L$65*AY57+$L$66*AI57 -> 0.021442279 | BT57: =IF(ISNUMBER(BR57),BR57/MAX(BR$22:BR57)-1,"") -> 0 | BV57: 49310 | BW57: =BW56*(1+$BY$44) -> 2.1606085e+08 | BX57: =ABS(BW57*$BY$45) -> 32180923
B58: SPY.AX | C58: SPDR S&P 500 ETF Trust | D58: United States | E58: Equities | F58: Growth | G58: 0.0009 | H58: =X15 -> 0.12566444 | I58: =H58-G58 -> 0.12476444 | J58: =X16 -> 0.13229761 | K58: =X18 -> -0.16545205 | L58: 0.29 | M58: =J58*L58 -> 0.038366307 | N58: =K58*L58 -> -0.047981095 | O58: =I58*L58 -> 0.036181687 | Q58: 45504 | R58: 100.74 | S58: =IF(AND(ISNUMBER(R57),ISNUMBER(R58)),R58/R57-1,"") -> 0.00049657364 | T58: =IF(ISNUMBER(R58),R58/MAX(R$22:R58)-1,"") -> 0 | V58: 840.56 | W58: =IF(AND(ISNUMBER(V57),ISNUMBER(V58)),V58/V57-1,"") -> 0.016962276 | X58: =IF(ISNUMBER(V58),V58/MAX(V$22:V58)-1,"") -> 0 | Z58: 35.54 | AA58: =IF(AND(ISNUMBER(Z57),ISNUMBER(Z58)),Z58/Z57-1,"") -> -0.036856369 | AB58: =IF(ISNUMBER(Z58),Z58/MAX(Z$22:Z58)-1,"") -> -0.036856369 | AD58: 20.26 | AE58: =IF(AND(ISNUMBER(AD57),ISNUMBER(AD58)),AD58/AD57-1,"") -> -0.057674419 | AF58: =IF(ISNUMBER(AD58),AD58/MAX(AD$22:AD58)-1,"") -> -0.057674419 | AH58: 34.37 | AI58: =IF(AND(ISNUMBER(AH57),ISNUMBER(AH58)),AH58/AH57-1,"") -> 0.061129978 | AJ58: =IF(ISNUMBER(AH58),AH58/MAX(AH$22:AH58)-1,"") -> 0 | AL58: 42.47 | AM58: =IF(AND(ISNUMBER(AL57),ISNUMBER(AL58)),AL58/AL57-1,"") -> 0.010468713 | AN58: =IF(ISNUMBER(AL58),AL58/MAX(AL$22:AL58)-1,"") -> -0.1488978 | AP58: 68 | AQ58: =IF(AND(ISNUMBER(AP57),ISNUMBER(AP58)),AP58/AP57-1,"") -> 0.083838062 | AR58: =IF(ISNUMBER(AP58),AP58/MAX(AP$22:AP58)-1,"") -> 0 | AT58: 50.28 | AU58: =IF(AND(ISNUMBER(AT57),ISNUMBER(AT58)),AT58/AT57-1,"") -> 0 | AV58: =IF(ISNUMBER(AT58),AT58/MAX(AT$22:AT58)-1,"") -> 0 | AX58: 416.49 | AY58: =IF(AND(ISNUMBER(AX57),ISNUMBER(AX58)),AX58/AX57-1,"") -> 0.02392074 | AZ58: =IF(ISNUMBER(AX58),AX58/MAX(AX$22:AX58)-1,"") -> 0 | BB58: 63.83 | BC58: =IF(AND(ISNUMBER(BB57),ISNUMBER(BB58)),BB58/BB57-1,"") -> 0.041102593 | BD58: =IF(ISNUMBER(BB58),BB58/MAX(BB$22:BB58)-1,"") -> 0 | BF58: 50.73 | BG58: =IF(AND(ISNUMBER(BF57),ISNUMBER(BF58)),BF58/BF57-1,"") -> 0.0075471698 | BH58: =IF(ISNUMBER(BF58),BF58/MAX(BF$22:BF58)-1,"") -> -0.054603056 | BJ58: =BJ57*(1+BK58) -> 126.68127 | BK58: =$L$12*S58+$L$13*W58+$L$14*AA58+$L$15*AE58+$L$16*AI58+$L$17*AM58+$L$18*AQ58+$L$19*AU58+$L$20*AY58 -> 0.007210778 | BL58: =IF(ISNUMBER(BJ58),BJ58/MAX(BJ$22:BJ58)-1,"") -> 0 | BN58: =BN57*(1+BO58) -> 126.97122 | BO58: =$L$35*W58+$L$36*S58+$L$37*AA58+$L$38*AE58+$L$39*AQ58+$L$40*AY58+$L$41*BC58+$L$42*BG58+$L$43*AI58 -> -0.0031008767 | BP58: =IF(ISNUMBER(BN58),BN58/MAX(BN$22:BN58)-1,"") -> -0.0031008767 | BR58: =BR57*(1+BS58) -> 123.93399 | BS58: =$L$58*W58+$L$59*AE58+$L$60*S58+$L$61*AQ58+$L$62*BC58+$L$63*AA58+$L$64*BG58+$L$65*AY58+$L$66*AI58 -> 0.0054734379 | BT58: =IF(ISNUMBER(BR58),BR58/MAX(BR$22:BR58)-1,"") -> 0 | BV58: 49675 | BW58: =BW57*(1+$BY$44) -> 2.3537005e+08 | BX58: =ABS(BW58*$BY$45) -> 35056908
B59: HJPN.AX | C59: BetaShares Japan ETF (Currency Hedged) | D59: Japan | E59: Equities | F59: Growth | G59: 0.0056 | H59: =AF15 -> 0.1556891 | I59: =H59-G59 -> 0.1500891 | J59: =AF16 -> 0.17112888 | K59: =AF18 -> -0.21497585 | L59: 0.1895 | M59: =J59*L59 -> 0.032428922 | N59: =K59*L59 -> -0.040737923 | O59: =I59*L59 -> 0.028441884 | Q59: 45534 | R59: 100.71 | S59: =IF(AND(ISNUMBER(R58),ISNUMBER(R59)),R59/R58-1,"") -> -0.00029779631 | T59: =IF(ISNUMBER(R59),R59/MAX(R$22:R59)-1,"") -> -0.00029779631 | V59: 823.06 | W59: =IF(AND(ISNUMBER(V58),ISNUMBER(V59)),V59/V58-1,"") -> -0.020819454 | X59: =IF(ISNUMBER(V59),V59/MAX(V$22:V59)-1,"") -> -0.020819454 | Z59: 35.15 | AA59: =IF(AND(ISNUMBER(Z58),ISNUMBER(Z59)),Z59/Z58-1,"") -> -0.010973551 | AB59: =IF(ISNUMBER(Z59),Z59/MAX(Z$22:Z59)-1,"") -> -0.047425474 | AD59: 19.49 | AE59: =IF(AND(ISNUMBER(AD58),ISNUMBER(AD59)),AD59/AD58-1,"") -> -0.038005923 | AF59: =IF(ISNUMBER(AD59),AD59/MAX(AD$22:AD59)-1,"") -> -0.093488372 | AH59: 34.11 | AI59: =IF(AND(ISNUMBER(AH58),ISNUMBER(AH59)),AH59/AH58-1,"") -> -0.0075647367 | AJ59: =IF(ISNUMBER(AH59),AH59/MAX(AH$22:AH59)-1,"") -> -0.0075647367 | AL59: 43.05 | AM59: =IF(AND(ISNUMBER(AL58),ISNUMBER(AL59)),AL59/AL58-1,"") -> 0.013656699 | AN59: =IF(ISNUMBER(AL59),AL59/MAX(AL$22:AL59)-1,"") -> -0.13727455 | AP59: 67.45 | AQ59: =IF(AND(ISNUMBER(AP58),ISNUMBER(AP59)),AP59/AP58-1,"") -> -0.0080882353 | AR59: =IF(ISNUMBER(AP59),AP59/MAX(AP$22:AP59)-1,"") -> -0.0080882353 | AT59: 50.29 | AU59: =IF(AND(ISNUMBER(AT58),ISNUMBER(AT59)),AT59/AT58-1,"") -> 0.00019888624 | AV59: =IF(ISNUMBER(AT59),AT59/MAX(AT$22:AT59)-1,"") -> 0 | AX59: 406.41 | AY59: =IF(AND(ISNUMBER(AX58),ISNUMBER(AX59)),AX59/AX58-1,"") -> -0.024202262 | AZ59: =IF(ISNUMBER(AX59),AX59/MAX(AX$22:AX59)-1,"") -> -0.024202262 | BB59: 64.48 | BC59: =IF(AND(ISNUMBER(BB58),ISNUMBER(BB59)),BB59/BB58-1,"") -> 0.010183299 | BD59: =IF(ISNUMBER(BB59),BB59/MAX(BB$22:BB59)-1,"") -> 0 | BF59: 51.2 | BG59: =IF(AND(ISNUMBER(BF58),ISNUMBER(BF59)),BF59/BF58-1,"") -> 0.0092647349 | BH59: =IF(ISNUMBER(BF59),BF59/MAX(BF$22:BF59)-1,"") -> -0.045844204 | BJ59: =BJ58*(1+BK59) -> 125.06109 | BK59: =$L$12*S59+$L$13*W59+$L$14*AA59+$L$15*AE59+$L$16*AI59+$L$17*AM59+$L$18*AQ59+$L$19*AU59+$L$20*AY59 -> -0.012789409 | BL59: =IF(ISNUMBER(BJ59),BJ59/MAX(BJ$22:BJ59)-1,"") -> -0.012789409 | BN59: =BN58*(1+BO59) -> 125.01271 | BO59: =$L$35*W59+$L$36*S59+$L$37*AA59+$L$38*AE59+$L$39*AQ59+$L$40*AY59+$L$41*BC59+$L$42*BG59+$L$43*AI59 -> -0.01542485 | BP59: =IF(ISNUMBER(BN59),BN59/MAX(BN$22:BN59)-1,"") -> -0.018477896 | BR59: =BR58*(1+BS59) -> 122.16426 | BS59: =$L$58*W59+$L$59*AE59+$L$60*S59+$L$61*AQ59+$L$62*BC59+$L$63*AA59+$L$64*BG59+$L$65*AY59+$L$66*AI59 -> -0.014279597 | BT59: =IF(ISNUMBER(BR59),BR59/MAX(BR$22:BR59)-1,"") -> -0.014279597
B60: BILL.AX | C60: iShares Core Cash ETF | D60: Australia | E60: Cash | F60: Defensive | G60: 0.0007 | H60: =T15 -> 0.00086268851 | I60: =H60-G60 -> 0.00016268851 | J60: =T16 -> 0.0014583498 | K60: =T18 -> -0.0015873016 | L60: 0.18 | M60: =J60*L60 -> 0.00026250296 | N60: =K60*L60 -> -0.00028571429 | O60: =I60*L60 -> 2.9283932e-05 | Q60: 45565 | R60: 100.7 | S60: =IF(AND(ISNUMBER(R59),ISNUMBER(R60)),R60/R59-1,"") -> -9.9295005e-05 | T60: =IF(ISNUMBER(R60),R60/MAX(R$22:R60)-1,"") -> -0.00039706174 | V60: 823.75 | W60: =IF(AND(ISNUMBER(V59),ISNUMBER(V60)),V60/V59-1,"") -> 0.00083833499 | X60: =IF(ISNUMBER(V60),V60/MAX(V$22:V60)-1,"") -> -0.019998572 | Z60: 34.8 | AA60: =IF(AND(ISNUMBER(Z59),ISNUMBER(Z60)),Z60/Z59-1,"") -> -0.0099573257 | AB60: =IF(ISNUMBER(Z60),Z60/MAX(Z$22:Z60)-1,"") -> -0.056910569 | AD60: 18.94 | AE60: =IF(AND(ISNUMBER(AD59),ISNUMBER(AD60)),AD60/AD59-1,"") -> -0.0282196 | AF60: =IF(ISNUMBER(AD60),AD60/MAX(AD$22:AD60)-1,"") -> -0.11906977 | AH60: 35.37 | AI60: =IF(AND(ISNUMBER(AH59),ISNUMBER(AH60)),AH60/AH59-1,"") -> 0.036939314 | AJ60: =IF(ISNUMBER(AH60),AH60/MAX(AH$22:AH60)-1,"") -> 0 | AL60: 43.52 | AM60: =IF(AND(ISNUMBER(AL59),ISNUMBER(AL60)),AL60/AL59-1,"") -> 0.010917538 | AN60: =IF(ISNUMBER(AL60),AL60/MAX(AL$22:AL60)-1,"") -> -0.12785571 | AP60: 67.77 | AQ60: =IF(AND(ISNUMBER(AP59),ISNUMBER(AP60)),AP60/AP59-1,"") -> 0.004744255 | AR60: =IF(ISNUMBER(AP60),AP60/MAX(AP$22:AP60)-1,"") -> -0.0033823529 | AT60: 50.27 | AU60: =IF(AND(ISNUMBER(AT59),ISNUMBER(AT60)),AT60/AT59-1,"") -> -0.00039769338 | AV60: =IF(ISNUMBER(AT60),AT60/MAX(AT$22:AT60)-1,"") -> -0.00039769338 | AX60: 406.78 | AY60: =IF(AND(ISNUMBER(AX59),ISNUMBER(AX60)),AX60/AX59-1,"") -> 0.00091041067 | AZ60: =IF(ISNUMBER(AX60),AX60/MAX(AX$22:AX60)-1,"") -> -0.023313885 | BB60: 66.01 | BC60: =IF(AND(ISNUMBER(BB59),ISNUMBER(BB60)),BB60/BB59-1,"") -> 0.023728288 | BD60: =IF(ISNUMBER(BB60),BB60/MAX(BB$22:BB60)-1,"") -> 0 | BF60: 51.55 | BG60: =IF(AND(ISNUMBER(BF59),ISNUMBER(BF60)),BF60/BF59-1,"") -> 0.0068359375 | BH60: =IF(ISNUMBER(BF60),BF60/MAX(BF$22:BF60)-1,"") -> -0.039321655 | BJ60: =BJ59*(1+BK60) -> 125.31909 | BK60: =$L$12*S60+$L$13*W60+$L$14*AA60+$L$15*AE60+$L$16*AI60+$L$17*AM60+$L$18*AQ60+$L$19*AU60+$L$20*AY60 -> 0.0020629509 | BL60: =IF(ISNUMBER(BJ60),BJ60/MAX(BJ$22:BJ60)-1,"") -> -0.010752842 | BN60: =BN59*(1+BO60) -> 124.6469 | BO60: =$L$35*W60+$L$36*S60+$L$37*AA60+$L$38*AE60+$L$39*AQ60+$L$40*AY60+$L$41*BC60+$L$42*BG60+$L$43*AI60 -> -0.0029261805 | BP60: =IF(ISNUMBER(BN60),BN60/MAX(BN$22:BN60)-1,"") -> -0.021350007 | BR60: =BR59*(1+BS60) -> 121.86651 | BS60: =$L$58*W60+$L$59*AE60+$L$60*S60+$L$61*AQ60+$L$62*BC60+$L$63*AA60+$L$64*BG60+$L$65*AY60+$L$66*AI60 -> -0.002437321 | BT60: =IF(ISNUMBER(BR60),BR60/MAX(BR$22:BR60)-1,"") -> -0.016682114
B61: VBLD.AX | C61: Vanguard Global Infrastructure Index ETF | D61: Global | E61: Infrastructure | F61: Growth | G61: 0.0047 | H61: =AR15 -> 0.04674658 | I61: =H61-G61 -> 0.04204658 | J61: =AR16 -> 0.10222536 | K61: =AR18 -> -0.11622276 | L61: 0.1105 | M61: =J61*L61 -> 0.011295903 | N61: =K61*L61 -> -0.012842615 | O61: =I61*L61 -> 0.0046461471 | Q61: 45596 | R61: 100.67 | S61: =IF(AND(ISNUMBER(R60),ISNUMBER(R61)),R61/R60-1,"") -> -0.0002979146 | T61: =IF(ISNUMBER(R61),R61/MAX(R$22:R61)-1,"") -> -0.00069485805 | V61: 879.4 | W61: =IF(AND(ISNUMBER(V60),ISNUMBER(V61)),V61/V60-1,"") -> 0.067556904 | X61: =IF(ISNUMBER(V61),V61/MAX(V$22:V61)-1,"") -> 0 | Z61: 35.36 | AA61: =IF(AND(ISNUMBER(Z60),ISNUMBER(Z61)),Z61/Z60-1,"") -> 0.016091954 | AB61: =IF(ISNUMBER(Z61),Z61/MAX(Z$22:Z61)-1,"") -> -0.041734417 | AD61: 19.59 | AE61: =IF(AND(ISNUMBER(AD60),ISNUMBER(AD61)),AD61/AD60-1,"") -> 0.034318902 | AF61: =IF(ISNUMBER(AD61),AD61/MAX(AD$22:AD61)-1,"") -> -0.088837209 | AH61: 39.08 | AI61: =IF(AND(ISNUMBER(AH60),ISNUMBER(AH61)),AH61/AH60-1,"") -> 0.10489115 | AJ61: =IF(ISNUMBER(AH61),AH61/MAX(AH$22:AH61)-1,"") -> 0 | AL61: 42.55 | AM61: =IF(AND(ISNUMBER(AL60),ISNUMBER(AL61)),AL61/AL60-1,"") -> -0.022288603 | AN61: =IF(ISNUMBER(AL61),AL61/MAX(AL$22:AL61)-1,"") -> -0.14729459 | AP61: 69.74 | AQ61: =IF(AND(ISNUMBER(AP60),ISNUMBER(AP61)),AP61/AP60-1,"") -> 0.02906891 | AR61: =IF(ISNUMBER(AP61),AP61/MAX(AP$22:AP61)-1,"") -> 0 | AT61: 50.29 | AU61: =IF(AND(ISNUMBER(AT60),ISNUMBER(AT61)),AT61/AT60-1,"") -> 0.0003978516 | AV61: =IF(ISNUMBER(AT61),AT61/MAX(AT$22:AT61)-1,"") -> 0 | AX61: 434.58 | AY61: =IF(AND(ISNUMBER(AX60),ISNUMBER(AX61)),AX61/AX60-1,"") -> 0.06834161 | AZ61: =IF(ISNUMBER(AX61),AX61/MAX(AX$22:AX61)-1,"") -> 0 | BB61: 65.08 | BC61: =IF(AND(ISNUMBER(BB60),ISNUMBER(BB61)),BB61/BB60-1,"") -> -0.014088774 | BD61: =IF(ISNUMBER(BB61),BB61/MAX(BB$22:BB61)-1,"") -> -0.014088774 | BF61: 50.76 | BG61: =IF(AND(ISNUMBER(BF60),ISNUMBER(BF61)),BF61/BF60-1,"") -> -0.015324927 | BH61: =IF(ISNUMBER(BF61),BF61/MAX(BF$22:BF61)-1,"") -> -0.054043981 | BJ61: =BJ60*(1+BK61) -> 130.62052 | BK61: =$L$12*S61+$L$13*W61+$L$14*AA61+$L$15*AE61+$L$16*AI61+$L$17*AM61+$L$18*AQ61+$L$19*AU61+$L$20*AY61 -> 0.042303473 | BL61: =IF(ISNUMBER(BJ61),BJ61/MAX(BJ$22:BJ61)-1,"") -> 0 | BN61: =BN60*(1+BO61) -> 129.39006 | BO61: =$L$35*W61+$L$36*S61+$L$37*AA61+$L$38*AE61+$L$39*AQ61+$L$40*AY61+$L$41*BC61+$L$42*BG61+$L$43*AI61 -> 0.038052788 | BP61: =IF(ISNUMBER(BN61),BN61/MAX(BN$22:BN61)-1,"") -> 0 | BR61: =BR60*(1+BS61) -> 125.61159 | BS61: =$L$58*W61+$L$59*AE61+$L$60*S61+$L$61*AQ61+$L$62*BC61+$L$63*AA61+$L$64*BG61+$L$65*AY61+$L$66*AI61 -> 0.030731013 | BT61: =IF(ISNUMBER(BR61),BR61/MAX(BR$22:BR61)-1,"") -> 0
B62: VETH.AX | C62: Vanguard Ethically Conscious Australian Shares ETF | D62: Australia | E62: Equities | F62: Growth | G62: 0.0016 | H62: =BD15 -> 0.03979497 | I62: =H62-G62 -> 0.03819497 | J62: =BD16 -> 0.13625391 | K62: =BD18 -> -0.17873303 | L62: 0.11 | M62: =J62*L62 -> 0.01498793 | N62: =K62*L62 -> -0.019660633 | O62: =I62*L62 -> 0.0042014467 | Q62: 45625 | R62: 100.67 | S62: =IF(AND(ISNUMBER(R61),ISNUMBER(R62)),R62/R61-1,"") -> 0 | T62: =IF(ISNUMBER(R62),R62/MAX(R$22:R62)-1,"") -> -0.00069485805 | V62: 922.12 | W62: =IF(AND(ISNUMBER(V61),ISNUMBER(V62)),V62/V61-1,"") -> 0.048578576 | X62: =IF(ISNUMBER(V62),V62/MAX(V$22:V62)-1,"") -> 0 | Z62: 36.44 | AA62: =IF(AND(ISNUMBER(Z61),ISNUMBER(Z62)),Z62/Z61-1,"") -> 0.030542986 | AB62: =IF(ISNUMBER(Z62),Z62/MAX(Z$22:Z62)-1,"") -> -0.012466125 | AD62: 19.46 | AE62: =IF(AND(ISNUMBER(AD61),ISNUMBER(AD62)),AD62/AD61-1,"") -> -0.0066360388 | AF62: =IF(ISNUMBER(AD62),AD62/MAX(AD$22:AD62)-1,"") -> -0.094883721 | AH62: 37.6 | AI62: =IF(AND(ISNUMBER(AH61),ISNUMBER(AH62)),AH62/AH61-1,"") -> -0.037871034 | AJ62: =IF(ISNUMBER(AH62),AH62/MAX(AH$22:AH62)-1,"") -> -0.037871034 | AL62: 43.04 | AM62: =IF(AND(ISNUMBER(AL61),ISNUMBER(AL62)),AL62/AL61-1,"") -> 0.011515864 | AN62: =IF(ISNUMBER(AL62),AL62/MAX(AL$22:AL62)-1,"") -> -0.13747495 | AP62: 73.31 | AQ62: =IF(AND(ISNUMBER(AP61),ISNUMBER(AP62)),AP62/AP61-1,"") -> 0.051190135 | AR62: =IF(ISNUMBER(AP62),AP62/MAX(AP$22:AP62)-1,"") -> 0 | AT62: 50.28 | AU62: =IF(AND(ISNUMBER(AT61),ISNUMBER(AT62)),AT62/AT61-1,"") -> -0.00019884669 | AV62: =IF(ISNUMBER(AT62),AT62/MAX(AT$22:AT62)-1,"") -> -0.00019884669 | AX62: 459.53 | AY62: =IF(AND(ISNUMBER(AX61),ISNUMBER(AX62)),AX62/AX61-1,"") -> 0.057411754 | AZ62: =IF(ISNUMBER(AX62),AX62/MAX(AX$22:AX62)-1,"") -> 0 | BB62: 67.76 | BC62: =IF(AND(ISNUMBER(BB61),ISNUMBER(BB62)),BB62/BB61-1,"") -> 0.041180086 | BD62: =IF(ISNUMBER(BB62),BB62/MAX(BB$22:BB62)-1,"") -> 0 | BF62: 51.11 | BG62: =IF(AND(ISNUMBER(BF61),ISNUMBER(BF62)),BF62/BF61-1,"") -> 0.0068951931 | BH62: =IF(ISNUMBER(BF62),BF62/MAX(BF$22:BF62)-1,"") -> -0.047521431 | BJ62: =BJ61*(1+BK62) -> 132.68777 | BK62: =$L$12*S62+$L$13*W62+$L$14*AA62+$L$15*AE62+$L$16*AI62+$L$17*AM62+$L$18*AQ62+$L$19*AU62+$L$20*AY62 -> 0.015826399 | BL62: =IF(ISNUMBER(BJ62),BJ62/MAX(BJ$22:BJ62)-1,"") -> 0 | BN62: =BN61*(1+BO62) -> 131.79015 | BO62: =$L$35*W62+$L$36*S62+$L$37*AA62+$L$38*AE62+$L$39*AQ62+$L$40*AY62+$L$41*BC62+$L$42*BG62+$L$43*AI62 -> 0.018549242 | BP62: =IF(ISNUMBER(BN62),BN62/MAX(BN$22:BN62)-1,"") -> 0 | BR62: =BR61*(1+BS62) -> 128.88124 | BS62: =$L$58*W62+$L$59*AE62+$L$60*S62+$L$61*AQ62+$L$62*BC62+$L$63*AA62+$L$64*BG62+$L$65*AY62+$L$66*AI62 -> 0.026029805 | BT62: =IF(ISNUMBER(BR62),BR62/MAX(BR$22:BR62)-1,"") -> 0
B63: ESGI.AX | C63: VanEck MSCI International Sustainable Equity ETF | D63: Global | E63: Equities | F63: Growth | G63: 0.0055 | H63: =AB15 -> 0.060929507 | I63: =H63-G63 -> 0.055429507 | J63: =AB16 -> 0.12936696 | K63: =AB18 -> -0.20283323 | L63: 0.09 | M63: =J63*L63 -> 0.011643027 | N63: =K63*L63 -> -0.01825499 | O63: =I63*L63 -> 0.0049886557 | Q63: 45657 | R63: 100.72 | S63: =IF(AND(ISNUMBER(R62),ISNUMBER(R63)),R63/R62-1,"") -> 0.0004966723 | T63: =IF(ISNUMBER(R63),R63/MAX(R$22:R63)-1,"") -> -0.00019853087 | V63: 945.91 | W63: =IF(AND(ISNUMBER(V62),ISNUMBER(V63)),V63/V62-1,"") -> 0.025799245 | X63: =IF(ISNUMBER(V63),V63/MAX(V$22:V63)-1,"") -> 0 | Z63: 36.45 | AA63: =IF(AND(ISNUMBER(Z62),ISNUMBER(Z63)),Z63/Z62-1,"") -> 0.00027442371 | AB63: =IF(ISNUMBER(Z63),Z63/MAX(Z$22:Z63)-1,"") -> -0.012195122 | AD63: 20.36 | AE63: =IF(AND(ISNUMBER(AD62),ISNUMBER(AD63)),AD63/AD62-1,"") -> 0.046248715 | AF63: =IF(ISNUMBER(AD63),AD63/MAX(AD$22:AD63)-1,"") -> -0.053023256 | AH63: 38.64 | AI63: =IF(AND(ISNUMBER(AH62),ISNUMBER(AH63)),AH63/AH62-1,"") -> 0.027659574 | AJ63: =IF(ISNUMBER(AH63),AH63/MAX(AH$22:AH63)-1,"") -> -0.011258956 | AL63: 42.59 | AM63: =IF(AND(ISNUMBER(AL62),ISNUMBER(AL63)),AL63/AL62-1,"") -> -0.01045539 | AN63: =IF(ISNUMBER(AL63),AL63/MAX(AL$22:AL63)-1,"") -> -0.14649299 | AP63: 71.22 | AQ63: =IF(AND(ISNUMBER(AP62),ISNUMBER(AP63)),AP63/AP62-1,"") -> -0.028509071 | AR63: =IF(ISNUMBER(AP63),AP63/MAX(AP$22:AP63)-1,"") -> -0.028509071 | AT63: 50.29 | AU63: =IF(AND(ISNUMBER(AT62),ISNUMBER(AT63)),AT63/AT62-1,"") -> 0.00019888624 | AV63: =IF(ISNUMBER(AT63),AT63/MAX(AT$22:AT63)-1,"") -> 0 | AX63: 468.59 | AY63: =IF(AND(ISNUMBER(AX62),ISNUMBER(AX63)),AX63/AX62-1,"") -> 0.019715797 | AZ63: =IF(ISNUMBER(AX63),AX63/MAX(AX$22:AX63)-1,"") -> 0 | BB63: 65.69 | BC63: =IF(AND(ISNUMBER(BB62),ISNUMBER(BB63)),BB63/BB62-1,"") -> -0.030548996 | BD63: =IF(ISNUMBER(BB63),BB63/MAX(BB$22:BB63)-1,"") -> -0.030548996 | BF63: 51.55 | BG63: =IF(AND(ISNUMBER(BF62),ISNUMBER(BF63)),BF63/BF62-1,"") -> 0.0086088828 | BH63: =IF(ISNUMBER(BF63),BF63/MAX(BF$22:BF63)-1,"") -> -0.039321655 | BJ63: =BJ62*(1+BK63) -> 134.66193 | BK63: =$L$12*S63+$L$13*W63+$L$14*AA63+$L$15*AE63+$L$16*AI63+$L$17*AM63+$L$18*AQ63+$L$19*AU63+$L$20*AY63 -> 0.014878212 | BL63: =IF(ISNUMBER(BJ63),BJ63/MAX(BJ$22:BJ63)-1,"") -> 0 | BN63: =BN62*(1+BO63) -> 133.97051 | BO63: =$L$35*W63+$L$36*S63+$L$37*AA63+$L$38*AE63+$L$39*AQ63+$L$40*AY63+$L$41*BC63+$L$42*BG63+$L$43*AI63 -> 0.0165442 | BP63: =IF(ISNUMBER(BN63),BN63/MAX(BN$22:BN63)-1,"") -> 0 | BR63: =BR62*(1+BS63) -> 130.22279 | BS63: =$L$58*W63+$L$59*AE63+$L$60*S63+$L$61*AQ63+$L$62*BC63+$L$63*AA63+$L$64*BG63+$L$65*AY63+$L$66*AI63 -> 0.010409212 | BT63: =IF(ISNUMBER(BR63),BR63/MAX(BR$22:BR63)-1,"") -> 0
B64: VACF.AX | C64: Vanguard Australia Corporate Fixed Interest Index ETF | D64: Australia | E64: Bonds | F64: Defensive | G64: 0.002 | H64: =BH15 -> -0.0089862279 | I64: =H64-G64 -> -0.010986228 | J64: =BH16 -> 0.04180311 | K64: =BH18 -> -0.11666045 | L64: 0.01 | M64: =J64*L64 -> 0.0004180311 | N64: =K64*L64 -> -0.0011666045 | O64: =I64*L64 -> -0.00010986228 | Q64: 45688 | R64: 100.71 | S64: =IF(AND(ISNUMBER(R63),ISNUMBER(R64)),R64/R63-1,"") -> -9.9285147e-05 | T64: =IF(ISNUMBER(R64),R64/MAX(R$22:R64)-1,"") -> -0.00029779631 | V64: 974.27 | W64: =IF(AND(ISNUMBER(V63),ISNUMBER(V64)),V64/V63-1,"") -> 0.029981711 | X64: =IF(ISNUMBER(V64),V64/MAX(V$22:V64)-1,"") -> 0 | Z64: 37.4 | AA64: =IF(AND(ISNUMBER(Z63),ISNUMBER(Z64)),Z64/Z63-1,"") -> 0.0260631 | AB64: =IF(ISNUMBER(Z64),Z64/MAX(Z$22:Z64)-1,"") -> 0 | AD64: 20.43 | AE64: =IF(AND(ISNUMBER(AD63),ISNUMBER(AD64)),AD64/AD63-1,"") -> 0.0034381139 | AF64: =IF(ISNUMBER(AD64),AD64/MAX(AD$22:AD64)-1,"") -> -0.049767442 | AH64: 41.36 | AI64: =IF(AND(ISNUMBER(AH63),ISNUMBER(AH64)),AH64/AH63-1,"") -> 0.070393375 | AJ64: =IF(ISNUMBER(AH64),AH64/MAX(AH$22:AH64)-1,"") -> 0 | AL64: 42.4 | AM64: =IF(AND(ISNUMBER(AL63),ISNUMBER(AL64)),AL64/AL63-1,"") -> -0.0044611411 | AN64: =IF(ISNUMBER(AL64),AL64/MAX(AL$22:AL64)-1,"") -> -0.1503006 | AP64: 72.05 | AQ64: =IF(AND(ISNUMBER(AP63),ISNUMBER(AP64)),AP64/AP63-1,"") -> 0.01165403 | AR64: =IF(ISNUMBER(AP64),AP64/MAX(AP$22:AP64)-1,"") -> -0.017187287 | AT64: 50.29 | AU64: =IF(AND(ISNUMBER(AT63),ISNUMBER(AT64)),AT64/AT63-1,"") -> 0 | AV64: =IF(ISNUMBER(AT64),AT64/MAX(AT$22:AT64)-1,"") -> 0 | AX64: 483.52 | AY64: =IF(AND(ISNUMBER(AX63),ISNUMBER(AX64)),AX64/AX63-1,"") -> 0.031861542 | AZ64: =IF(ISNUMBER(AX64),AX64/MAX(AX$22:AX64)-1,"") -> 0 | BB64: 68.15 | BC64: =IF(AND(ISNUMBER(BB63),ISNUMBER(BB64)),BB64/BB63-1,"") -> 0.037448622 | BD64: =IF(ISNUMBER(BB64),BB64/MAX(BB$22:BB64)-1,"") -> 0 | BF64: 51.17 | BG64: =IF(AND(ISNUMBER(BF63),ISNUMBER(BF64)),BF64/BF63-1,"") -> -0.007371484 | BH64: =IF(ISNUMBER(BF64),BF64/MAX(BF$22:BF64)-1,"") -> -0.04640328 | BJ64: =BJ63*(1+BK64) -> 137.93063 | BK64: =$L$12*S64+$L$13*W64+$L$14*AA64+$L$15*AE64+$L$16*AI64+$L$17*AM64+$L$18*AQ64+$L$19*AU64+$L$20*AY64 -> 0.024273393 | BL64: =IF(ISNUMBER(BJ64),BJ64/MAX(BJ$22:BJ64)-1,"") -> 0 | BN64: =BN63*(1+BO64) -> 136.76283 | BO64: =$L$35*W64+$L$36*S64+$L$37*AA64+$L$38*AE64+$L$39*AQ64+$L$40*AY64+$L$41*BC64+$L$42*BG64+$L$43*AI64 -> 0.020842834 | BP64: =IF(ISNUMBER(BN64),BN64/MAX(BN$22:BN64)-1,"") -> 0 | BR64: =BR63*(1+BS64) -> 132.5707 | BS64: =$L$58*W64+$L$59*AE64+$L$60*S64+$L$61*AQ64+$L$62*BC64+$L$63*AA64+$L$64*BG64+$L$65*AY64+$L$66*AI64 -> 0.018029979 | BT64: =IF(ISNUMBER(BR64),BR64/MAX(BR$22:BR64)-1,"") -> 0
B65: VTS.AX | C65: Vanguard US Total Market Shares Index ETF | D65: United States | E65: Equities | F65: Growth | G65: 0.0003 | H65: =AZ15 -> 0.11643426 | I65: =H65-G65 -> 0.11613426 | J65: =AZ16 -> 0.1337603 | K65: =AZ18 -> -0.18097976 | L65: 0.01 | M65: =J65*L65 -> 0.001337603 | N65: =K65*L65 -> -0.0018097976 | O65: =I65*L65 -> 0.0011613426 | Q65: 45716 | R65: 100.69 | S65: =IF(AND(ISNUMBER(R64),ISNUMBER(R65)),R65/R64-1,"") -> -0.00019859001 | T65: =IF(ISNUMBER(R65),R65/MAX(R$22:R65)-1,"") -> -0.00049632718 | V65: 942.35 | W65: =IF(AND(ISNUMBER(V64),ISNUMBER(V65)),V65/V64-1,"") -> -0.032762992 | X65: =IF(ISNUMBER(V65),V65/MAX(V$22:V65)-1,"") -> -0.032762992 | Z65: 36.98 | AA65: =IF(AND(ISNUMBER(Z64),ISNUMBER(Z65)),Z65/Z64-1,"") -> -0.011229947 | AB65: =IF(ISNUMBER(Z65),Z65/MAX(Z$22:Z65)-1,"") -> -0.011229947 | AD65: 19.5 | AE65: =IF(AND(ISNUMBER(AD64),ISNUMBER(AD65)),AD65/AD64-1,"") -> -0.045521292 | AF65: =IF(ISNUMBER(AD65),AD65/MAX(AD$22:AD65)-1,"") -> -0.093023256 | AH65: 42.27 | AI65: =IF(AND(ISNUMBER(AH64),ISNUMBER(AH65)),AH65/AH64-1,"") -> 0.022001934 | AJ65: =IF(ISNUMBER(AH65),AH65/MAX(AH$22:AH65)-1,"") -> 0 | AL65: 43.06 | AM65: =IF(AND(ISNUMBER(AL64),ISNUMBER(AL65)),AL65/AL64-1,"") -> 0.015566038 | AN65: =IF(ISNUMBER(AL65),AL65/MAX(AL$22:AL65)-1,"") -> -0.13707415 | AP65: 73.25 | AQ65: =IF(AND(ISNUMBER(AP64),ISNUMBER(AP65)),AP65/AP64-1,"") -> 0.016655101 | AR65: =IF(ISNUMBER(AP65),AP65/MAX(AP$22:AP65)-1,"") -> -0.00081844223 | AT65: 50.26 | AU65: =IF(AND(ISNUMBER(AT64),ISNUMBER(AT65)),AT65/AT64-1,"") -> -0.00059654007 | AV65: =IF(ISNUMBER(AT65),AT65/MAX(AT$22:AT65)-1,"") -> -0.00059654007 | AX65: 464.88 | AY65: =IF(AND(ISNUMBER(AX64),ISNUMBER(AX65)),AX65/AX64-1,"") -> -0.038550629 | AZ65: =IF(ISNUMBER(AX65),AX65/MAX(AX$22:AX65)-1,"") -> -0.038550629 | BB65: 65.49 | BC65: =IF(AND(ISNUMBER(BB64),ISNUMBER(BB65)),BB65/BB64-1,"") -> -0.039031548 | BD65: =IF(ISNUMBER(BB65),BB65/MAX(BB$22:BB65)-1,"") -> -0.039031548 | BF65: 51.68 | BG65: =IF(AND(ISNUMBER(BF64),ISNUMBER(BF65)),BF65/BF64-1,"") -> 0.0099667774 | BH65: =IF(ISNUMBER(BF65),BF65/MAX(BF$22:BF65)-1,"") -> -0.036898994 | BJ65: =BJ64*(1+BK65) -> 136.33945 | BK65: =$L$12*S65+$L$13*W65+$L$14*AA65+$L$15*AE65+$L$16*AI65+$L$17*AM65+$L$18*AQ65+$L$19*AU65+$L$20*AY65 -> -0.011536086 | BL65: =IF(ISNUMBER(BJ65),BJ65/MAX(BJ$22:BJ65)-1,"") -> -0.011536086 | BN65: =BN64*(1+BO65) -> 134.35729 | BO65: =$L$35*W65+$L$36*S65+$L$37*AA65+$L$38*AE65+$L$39*AQ65+$L$40*AY65+$L$41*BC65+$L$42*BG65+$L$43*AI65 -> -0.017589139 | BP65: =IF(ISNUMBER(BN65),BN65/MAX(BN$22:BN65)-1,"") -> -0.017589139 | BR65: =BR64*(1+BS65) -> 129.69486 | BS65: =$L$58*W65+$L$59*AE65+$L$60*S65+$L$61*AQ65+$L$62*BC65+$L$63*AA65+$L$64*BG65+$L$65*AY65+$L$66*AI65 -> -0.021692895 | BT65: =IF(ISNUMBER(BR65),BR65/MAX(BR$22:BR65)-1,"") -> -0.021692895
B66: GOLD.AX | C66: Global X Physical Gold | D66: Global | E66: Alternatives (Gold) | F66: Defensive | G66: 0.004 | H66: =AJ15 -> 0.18941503 | I66: =H66-G66 -> 0.18541503 | J66: =AJ16 -> 0.1578302 | K66: =AJ18 -> -0.22099853 | L66: 0.01 | M66: =J66*L66 -> 0.001578302 | N66: =K66*L66 -> -0.0022099853 | O66: =I66*L66 -> 0.0018541503 | Q66: 45747 | R66: 100.74 | S66: =IF(AND(ISNUMBER(R65),ISNUMBER(R66)),R66/R65-1,"") -> 0.00049657364 | T66: =IF(ISNUMBER(R66),R66/MAX(R$22:R66)-1,"") -> 0 | V66: 879.33 | W66: =IF(AND(ISNUMBER(V65),ISNUMBER(V66)),V66/V65-1,"") -> -0.066875365 | X66: =IF(ISNUMBER(V66),V66/MAX(V$22:V66)-1,"") -> -0.09744732 | Z66: 35.92 | AA66: =IF(AND(ISNUMBER(Z65),ISNUMBER(Z66)),Z66/Z65-1,"") -> -0.028664143 | AB66: =IF(ISNUMBER(Z66),Z66/MAX(Z$22:Z66)-1,"") -> -0.039572193 | AD66: 19.34 | AE66: =IF(AND(ISNUMBER(AD65),ISNUMBER(AD66)),AD66/AD65-1,"") -> -0.0082051282 | AF66: =IF(ISNUMBER(AD66),AD66/MAX(AD$22:AD66)-1,"") -> -0.10046512 | AH66: 45.55 | AI66: =IF(AND(ISNUMBER(AH65),ISNUMBER(AH66)),AH66/AH65-1,"") -> 0.077596404 | AJ66: =IF(ISNUMBER(AH66),AH66/MAX(AH$22:AH66)-1,"") -> 0 | AL66: 42.86 | AM66: =IF(AND(ISNUMBER(AL65),ISNUMBER(AL66)),AL66/AL65-1,"") -> -0.0046446818 | AN66: =IF(ISNUMBER(AL66),AL66/MAX(AL$22:AL66)-1,"") -> -0.14108216 | AP66: 74.05 | AQ66: =IF(AND(ISNUMBER(AP65),ISNUMBER(AP66)),AP66/AP65-1,"") -> 0.010921502 | AR66: =IF(ISNUMBER(AP66),AP66/MAX(AP$22:AP66)-1,"") -> 0 | AT66: 50.27 | AU66: =IF(AND(ISNUMBER(AT65),ISNUMBER(AT66)),AT66/AT65-1,"") -> 0.00019896538 | AV66: =IF(ISNUMBER(AT66),AT66/MAX(AT$22:AT66)-1,"") -> -0.00039769338 | AX66: 432.85 | AY66: =IF(AND(ISNUMBER(AX65),ISNUMBER(AX66)),AX66/AX65-1,"") -> -0.068899501 | AZ66: =IF(ISNUMBER(AX66),AX66/MAX(AX$22:AX66)-1,"") -> -0.10479401 | BB66: 63.63 | BC66: =IF(AND(ISNUMBER(BB65),ISNUMBER(BB66)),BB66/BB65-1,"") -> -0.028401283 | BD66: =IF(ISNUMBER(BB66),BB66/MAX(BB$22:BB66)-1,"") -> -0.066324285 | BF66: 51.72 | BG66: =IF(AND(ISNUMBER(BF65),ISNUMBER(BF66)),BF66/BF65-1,"") -> 0.00077399381 | BH66: =IF(ISNUMBER(BF66),BF66/MAX(BF$22:BF66)-1,"") -> -0.036153559 | BJ66: =BJ65*(1+BK66) -> 134.52939 | BK66: =$L$12*S66+$L$13*W66+$L$14*AA66+$L$15*AE66+$L$16*AI66+$L$17*AM66+$L$18*AQ66+$L$19*AU66+$L$20*AY66 -> -0.013276109 | BL66: =IF(ISNUMBER(BJ66),BJ66/MAX(BJ$22:BJ66)-1,"") -> -0.024659041 | BN66: =BN65*(1+BO66) -> 131.60486 | BO66: =$L$35*W66+$L$36*S66+$L$37*AA66+$L$38*AE66+$L$39*AQ66+$L$40*AY66+$L$41*BC66+$L$42*BG66+$L$43*AI66 -> -0.020485951 | BP66: =IF(ISNUMBER(BN66),BN66/MAX(BN$22:BN66)-1,"") -> -0.03771476 | BR66: =BR65*(1+BS66) -> 126.41854 | BS66: =$L$58*W66+$L$59*AE66+$L$60*S66+$L$61*AQ66+$L$62*BC66+$L$63*AA66+$L$64*BG66+$L$65*AY66+$L$66*AI66 -> -0.025261723 | BT66: =IF(ISNUMBER(BR66),BR66/MAX(BR$22:BR66)-1,"") -> -0.046406618
M67: =SUM(M58:M66) -> 0.11231853 | N67: =SUM(N58:N66) -> -0.14494936 | O67: =SUM(O58:O66) -> 0.081394735 | Q67: 45777 | R67: 100.76 | S67: =IF(AND(ISNUMBER(R66),ISNUMBER(R67)),R67/R66-1,"") -> 0.00019853087 | T67: =IF(ISNUMBER(R67),R67/MAX(R$22:R67)-1,"") -> 0 | V67: 860.65 | W67: =IF(AND(ISNUMBER(V66),ISNUMBER(V67)),V67/V66-1,"") -> -0.021243447 | X67: =IF(ISNUMBER(V67),V67/MAX(V$22:V67)-1,"") -> -0.11662065 | Z67: 35.77 | AA67: =IF(AND(ISNUMBER(Z66),ISNUMBER(Z67)),Z67/Z66-1,"") -> -0.0041759465 | AB67: =IF(ISNUMBER(Z67),Z67/MAX(Z$22:Z67)-1,"") -> -0.043582888 | AD67: 19.25 | AE67: =IF(AND(ISNUMBER(AD66),ISNUMBER(AD67)),AD67/AD66-1,"") -> -0.0046535677 | AF67: =IF(ISNUMBER(AD67),AD67/MAX(AD$22:AD67)-1,"") -> -0.10465116 | AH67: 47.35 | AI67: =IF(AND(ISNUMBER(AH66),ISNUMBER(AH67)),AH67/AH66-1,"") -> 0.039517014 | AJ67: =IF(ISNUMBER(AH67),AH67/MAX(AH$22:AH67)-1,"") -> 0 | AL67: 42.89 | AM67: =IF(AND(ISNUMBER(AL66),ISNUMBER(AL67)),AL67/AL66-1,"") -> 0.00069995334 | AN67: =IF(ISNUMBER(AL67),AL67/MAX(AL$22:AL67)-1,"") -> -0.14048096 | AP67: 72.56 | AQ67: =IF(AND(ISNUMBER(AP66),ISNUMBER(AP67)),AP67/AP66-1,"") -> -0.02012154 | AR67: =IF(ISNUMBER(AP67),AP67/MAX(AP$22:AP67)-1,"") -> -0.02012154 | AT67: 50.25 | AU67: =IF(AND(ISNUMBER(AT66),ISNUMBER(AT67)),AT67/AT66-1,"") -> -0.0003978516 | AV67: =IF(ISNUMBER(AT67),AT67/MAX(AT$22:AT67)-1,"") -> -0.00079538676 | AX67: 423.74 | AY67: =IF(AND(ISNUMBER(AX66),ISNUMBER(AX67)),AX67/AX66-1,"") -> -0.021046552 | AZ67: =IF(ISNUMBER(AX67),AX67/MAX(AX$22:AX67)-1,"") -> -0.12363501 | BB67: 66 | BC67: =IF(AND(ISNUMBER(BB66),ISNUMBER(BB67)),BB67/BB66-1,"") -> 0.037246582 | BD67: =IF(ISNUMBER(BB67),BB67/MAX(BB$22:BB67)-1,"") -> -0.031548056 | BF67: 51.72 | BG67: =IF(AND(ISNUMBER(BF66),ISNUMBER(BF67)),BF67/BF66-1,"") -> 0 | BH67: =IF(ISNUMBER(BF67),BF67/MAX(BF$22:BF67)-1,"") -> -0.036153559 | BJ67: =BJ66*(1+BK67) -> 134.20552 | BK67: =$L$12*S67+$L$13*W67+$L$14*AA67+$L$15*AE67+$L$16*AI67+$L$17*AM67+$L$18*AQ67+$L$19*AU67+$L$20*AY67 -> -0.0024074523 | BL67: =IF(ISNUMBER(BJ67),BJ67/MAX(BJ$22:BJ67)-1,"") -> -0.027007128 | BN67: =BN66*(1+BO67) -> 130.94104 | BO67: =$L$35*W67+$L$36*S67+$L$37*AA67+$L$38*AE67+$L$39*AQ67+$L$40*AY67+$L$41*BC67+$L$42*BG67+$L$43*AI67 -> -0.0050440543 | BP67: =IF(ISNUMBER(BN67),BN67/MAX(BN$22:BN67)-1,"") -> -0.042568579 | BR67: =BR66*(1+BS67) -> 125.74547 | BS67: =$L$58*W67+$L$59*AE67+$L$60*S67+$L$61*AQ67+$L$62*BC67+$L$63*AA67+$L$64*BG67+$L$65*AY67+$L$66*AI67 -> -0.0053241518 | BT67: =IF(ISNUMBER(BR67),BR67/MAX(BR$22:BR67)-1,"") -> -0.051483694
